Workbook
Name Khmer_Lunar_2025: _xlfn.LAMBDA(_xlpm.X,VLOOKUP(_xlpm.X,Khmer_Lunar_Table,2,FALSE))
Name Khmer_Lunar_Table: Khmer_Lunar_2025!$AI$2:$AJ$367

Sheet FILE #
A1: suvannaphum
A2: =VLOOKUP($B$4,DATA!A3:AH4999,4,FALSE)&" CLEARANCE WORKSHEET" -> IMPORT CLEARANCE WORKSHEET
A4: REF No: | B4: 25207 | C4: SHIPMENT MODE: | D4: =VLOOKUP($B$4,DATA!A3:AH4999,5,FALSE) -> SEA-FCL | G4: =VLOOKUP($B$4,DATA!$A$3:$AH$4999,2,FALSE)&", "&G12&" , "&H12&" , "&I12&" , "&J12 -> TH25080681, , , , | O4: 44438 | P4: 44480 | Q4: =P4-O4 -> 42 | R4: =Q4*6.6 -> 277.2
A5: REC DATE: | B5: =VLOOKUP($B$4,DATA!$A$3:$AH$4999,34,FALSE) -> 45902 | C5: VIA: | D5: =VLOOKUP($B$4,DATA!$A$3:$AH$4999,20,FALSE) -> SHV11 | G5: 1 | H5: 2 | I5: 3 | J5: 4 | K5: 5
G6: =$B$4&""&G5 -> 252071 | H6: =IFERROR($B$4&""&H5,"") -> 252072 | I6: =$B$4&""&I5 -> 252073 | J6: =$B$4&""&J5 -> 252074 | K6: =$B$4&""&K5 -> 252075
A7: SHIPPER: | B7: =VLOOKUP($B$4,DATA!$A$3:$AH$4999,33,FALSE)&" "&G7&" "&H7&" "&I7&" "&J7&" "&K7&"" -> C. PLUS STEEL | C7: ADDRESS: | D7: =VLOOKUP($B$4,DATA!$A$3:$AH$4999,19,FALSE) -> TH | G7: =IFERROR(VLOOKUP(G6,DATA!$A$3:$AH$4999,33,FALSE),"") | H7: =IFERROR(VLOOKUP(H6,DATA!$A$3:$AH$4999,33,FALSE),"") | I7: =IFERROR(VLOOKUP(I6,DATA!$A$3:$AH$4999,33,FALSE),"") | J7: =IFERROR(VLOOKUP(J6,DATA!$A$3:$AH$4999,33,FALSE),"") | K7: =IFERROR(VLOOKUP(K6,DATA!$A$3:$AH$4999,33,FALSE),"")
A8: CONSIGNEE: | B8: =VLOOKUP($B$4,DATA!$A$3:$AH$4999,6,FALSE) -> OISHI F&B (CAMBODIA) CO.,LTD | C8: ADDRESS: | D8: PNH
B9: =VLOOKUP($B$4,DATA!$A$3:$AH$4999,19,FALSE) -> TH | C9: TO: | D9: =VLOOKUP($B$4,DATA!$A$3:$AH$4999,22,FALSE) -> SISEZ | E9: VIA: | F9: =VLOOKUP($B$4,DATA!$A$3:$AH$4999,20,FALSE) -> SHV11
A10: ARRIVAL DATE: | B10: =VLOOKUP($B$4,DATA!$A$3:$AH$4999,17,FALSE) -> 45900 | C10: IMPORT CC DATE:
A11: DELIVERY DATE:
A12: BL No.: | B12: =VLOOKUP($B$4,DATA!$A$3:$AH$4999,2,FALSE)&" "&G12&" "&H12&" "&I12&" "&J12&" "&K12 -> TH25080681 | C12: INV/PKL: | D12: =VLOOKUP($B$4,DATA!$A$3:$AH$4999,8,FALSE) -> 139_2567 | G12: =IFERROR(VLOOKUP(G6,DATA!$A$3:$AH$4999,2,FALSE),"") | H12: =IFERROR(VLOOKUP(H6,DATA!$A$3:$AH$4999,2,FALSE),"") | I12: =IFERROR(VLOOKUP(I6,DATA!$A$3:$AH$4999,2,FALSE),"") | J12: =IFERROR(VLOOKUP(J6,DATA!$A$3:$AH$4999,2,FALSE),"") | K12: =IFERROR(VLOOKUP(K6,DATA!$A$3:$AH$4999,2,FALSE),"")
A13: CONTAINER No.: | B13: =VLOOKUP($B$4,DATA!$A$3:$AH$4999,28,FALSE)&" "&G13&" " &H13&" " &I13&" " &J13&" " &K13 -> 1.FFAU4696414-40HC, 2.NBYU9027180-40HC, 3.NBYU8114320-40HC, 4.NBYU8158334-40HC, 5.NBYU8170200-40HC | C13: SEAL No.: | G13: =IFERROR(VLOOKUP(G6,DATA!$A$3:$AH$4999,28,FALSE),"") | H13: =IFERROR(VLOOKUP(H6,DATA!$A$3:$AH$4999,28,FALSE),"") | I13: =IFERROR(VLOOKUP(I6,DATA!$A$3:$AH$4999,28,FALSE),"") | J13: =IFERROR(VLOOKUP(J6,DATA!$A$3:$AH$4999,28,FALSE),"") | K13: =IFERROR(VLOOKUP(K6,DATA!$A$3:$AH$4999,28,FALSE),"")
A14: VOLUME: | B14: =VLOOKUP($B$4,DATA!$A$3:$AH$4999,30,FALSE)&"x20', "&VLOOKUP($B$4,DATA!$A$3:$AH$4999,31,FALSE)&"x40'" -> 0x20', 5x40' | C14: VSSL NAME: | D14: =VLOOKUP($B$4,DATA!$A$3:$AH$4999,16,FALSE) -> XIN MING ZHOU 98 V.2511S
A15: TRUCK No.: | C15: COMMODITY: | D15: =VLOOKUP($B$4,DATA!$A$3:$AH$4999,23,FALSE)&", "&VLOOKUP($B$4,DATA!$A$3:$AH$4999,29,FALSE)&" "&G15&" "&H15&" "&I15 -> UTILITY PIPING SUPPLY FOR MACHINERY, MEP WORKS MATERIAL, 76 PACKAGES | G15: =IFERROR(VLOOKUP(G6,DATA!$A$3:$AH$4999,23,FALSE)&", "&VLOOKUP(G6,DATA!$A$3:$AH$4999,29,FALSE),"") | H15: =IFERROR(VLOOKUP(H6,DATA!$A$3:$AH$4999,23,FALSE)&", "&VLOOKUP(H6,DATA!$A$3:$AH$4999,29,FALSE),"") | I15: =IFERROR(VLOOKUP(I6,DATA!$A$3:$AH$4999,23,FALSE)&", "&VLOOKUP(I6,DATA!$A$3:$AH$4999,29,FALSE),"") | J15: =IFERROR(VLOOKUP(J6,DATA!$A$3:$AH$4999,23,FALSE)&", "&VLOOKUP(J6,DATA!$A$3:$AH$4999,29,FALSE),"") | K15: =IFERROR(VLOOKUP(K6,DATA!$A$3:$AH$4999,23,FALSE)&", "&VLOOKUP(K6,DATA!$A$3:$AH$4999,29,FALSE),"")
C17: SERVICE PROVIDE: | D17: =VLOOKUP($B$4,DATA!$A$3:$AH$4999,35,FALSE) -> #REF!
A19: Remark:

Sheet DATA
A1: SHIPMENT INFORMATION | C1: 3 | D1: 4 | E1: 5 | F1: 6 | G1: 7 | H1: 8 | I1: 9 | J1: 10 | K1: 11 | L1: 12 | M1: 13 | N1: 14 | O1: 15 | P1: 16 | Q1: 17 | R1: 18 | S1: 19 | T1: 20 | U1: 21 | V1: 22 | W1: 23 | X1: 24 | Y1: 25 | Z1: 26 | AA1: 27 | AB1: 28 | AC1: 29 | AD1: 30 | AE1: 31 | AF1: 32 | AG1: 33 | AH1: 34 | AI1: 35 | AJ1: ACTIVITIES
A2: Job | B2: B/L No | C2: B/L Date | D2: Imp/Exp | E2: Ship'm Mode | F2: Importer | G2: Client Name | H2: Inv | I2: PKL | J2: INV & PKL Date | K2: CO | L2: CO Date | M2: Rcv Date | N2: Shipping Line | O2: MBL # | P2: Vssl/Truck | Q2: ETA/ETD | R2: LOAD ON | S2: POL | T2: Transit Port | U2: SCAN STATION | V2: Final Destination | W2: Commodity | X2: NW | Y2: GW | Z2: CBM/CIF | AA2: FOB | AB2: Container No | AC2: Quantity | AD2: 20' | AE2: 40' | AF2: CONT SIZE | AG2: Shipper Name | AH2: Received Date | AI2: SR NAME | AJ2: TP | AK2: TP DATE | AL2: IM8 | AM2: IM8 DATE | AN2: GATE IN DP/BW/SEZ | AO2: IM7 | AP2: IM7 DATE | AQ2: SR | AR2: SR DATE | AS2: CV | AT2: CV DATE | AU2: CO | AV2: CO DATE | AW2: IM4 | AX2: IM4 DATE | AY2: EX3 | AZ2: EX3 DATE | BA2: GATE OUT DP/BW/SEZ | BB2: INV
A3: 060 | B3: EH19/0702 | D3: IMPORT | E3: Land | F3: Big C | H3: INV-SG01082562 | I3: EH19/0702 | M3: 43706 | R3: 43690 | S3: TH | U3: POP | V3: POP | W3: STAINLESS EQUIPMENT & ACC | AC3: 1 LOT = 302 PKGS | AF3: - Apply Permit: 02.09.2019, Received: 08.09.2019, 10.09.2019
A4: 052 | B4: EW19/0071 | D4: IMPORT | E4: Land | F4: Big C | H4: 300719 | I4: 300719 | M4: 43705 | S4: TH | U4: POP | V4: POP | W4: ICE MAKER 624KG/24H, 1000KG/24H, ICE CART, ICED SCOOP | AF4: - Apply Permit: 05.09.2019, Received: 06.09.2019, 06.09.2019
A5: 035 | B5: BKK20190904 | D5: IMPORT | E5: Land | F5: Big C | H5: ML-INV-60260011 | I5: ML-INV-60260011 | S5: TH | U5: POP | V5: POP | W5: SEWAGE PUMP | AF5: - Apply Permit: 04.09.2019, Received: 06.09.2019, 06.09.2019
A6: 061 | B6: TBL0190845 | D6: IMPORT | E6: Land | F6: Big C | H6: INV_HL/Q/19-0901 | I6: PL_HL/Q/19-0901 | R6: 43709 | S6: TH | U6: POP | V6: POP | W6: FRUIT RACK | AC6: 15PKG = 52SET | AF6: - Apply Permit: 02.09.2019, Received: 04.09.2019, 05.09.2019
A7: 057 | B7: EW19/0257 | D7: IMPORT | E7: Land | F7: Big C | H7: 20190801 | I7: 20190801 | M7: 43697 | R7: 43693 | S7: TH | U7: POP | V7: POP | W7: STEEL FIXTURE (GONDOLA) | AB7: EWTU8880009-40HC | AE7: 1 | AF7: - Apply Permit: 30.08.2019, Received: 02.09.2019, 04.09.2019
A8: 053 | B8: TWB1908011 | D8: IMPORT | E8: Land | F8: Big C | H8: IV-2019145 | I8: PL-2019145 | M8: 43706 | S8: TH | U8: POP | V8: POP | W8: EXTERIOR SIGNAGE, INTERIOR SIGNAGE | AF8: - Apply Permit: 05.09.2019, Received: 06.09.2019, 06.09.2019
A9: 062 | B9: M02355 | D9: IMPORT | E9: Land | F9: Big C | G9: MASS | H9: BC2019-002 | I9: BC2019-002 | M9: 43710 | R9: 43709 | S9: TH | U9: POP | V9: POP | W9: PLASTIC BASKET | AC9: 9 ITEM = 262 PKG | AF9: - Apply Permit: 10.09.2019, Received: 17.09.2019, 20.09.2019
A10: 064 | B10: M02402 | D10: IMPORT | E10: Land | F10: Big C | G10: MASS | H10: INV BC2019-003 | I10: INV BC2019-003 | S10: TH | U10: POP | V10: POP | W10: COMPRESSED AIR CYLINDERS 300 BAR FOR SCBA | AC10: 23 ITEMS = 53 PKGS | AF10: - Apply Permit: 16.09.2019, Received: 17.09.2019, 20.09.2019
A11: 063 | B11: GLSW937891 | D11: IMPORT | E11: Sea | F11: BJC | G11: GLS | H11: 20190905/VP-BJC-KH | I11: 20190905/VP-BJC-KH | M11: 43714 | P11: GLS 07 V.937W | Q11: 43724 | R11: 43715 | S11: VN | T11: PNH02 | U11: PNH02 | V11: SISEZ | W11: NPKIN TISSUE PAPER, TOILET TISSUE PAPER | AB11: DRYU9021795-(40') PKEU5026440-(40') SEGU5593994-(40') SEGU5593192-(40') SEGU5592998-(40') | AC11: 135 ROLL | AE11: 5 | AF11: - Apply & Received TP (020/19): 13.09.2019 - Transit Clearance (T459): 17.09.2019 - Delivery from PPAP and arrive at SISEZ (By PPAP): 18.09.2019 - Apply and Received Form D (017/19): 20.09.2019, Valuation (025/19): 20.09.2019 - Complete Clearance (I26): 20.09.2019 | AI11: 063
A12: 065 | B12: GLSW939903 | D12: IMPORT | E12: Sea | F12: BJC | G12: GLS | H12: 20190917/VP-BJC-KH | I12: 20190917/VP-BJC-KH | M12: 43726 | P12: GLS CUU LONG V.939W | Q12: 43744 | R12: 43728 | S12: VN | T12: PNH02 | U12: PNH02 | V12: SISEZ | W12: TOILET TISSUE PAPER | AB12: DRYU9980125-(40') DRYU9955122-(40') | AC12: 72 ROLL | AE12: 2 | AF12: - Apply & Received TP (021/19): 01.10.2019 - Transit Clearance (T480): 02.10.2019 - Delivery from PPAP to SISEZ (By PPAP): 02.10.2019 - Apply and Received Form D (018/19): 18.10.2019, Valuation (026/19): 18.10.2019 - Complete Clearance (I29): 19.10.2019 | AI12: 063
A13: 066 | B13: TW1934XG23/48 | D13: IMPORT | E13: Sea | F13: China Construction Fourth (Mr. Samsen) | H13: 1900820-CT/CCF | I13: 1900820-CT/CCF | M13: 43727 | P13: EVNIA 1931 | Q13: 43734 | R13: 43706 | S13: CN | T13: STH | U13: STH | V13: STH | W13: ALLOY DEFORMED REBAR (STEEL BAR) | AB13: BREAK BULK | AC13: 1117 BUNDLE = 2578.404MT | AF13: - Applied Form E: 02.10.2019 and received (11483): 26.09.2019 - Applied Invoice Valuation: 02.10.2019, Received (54325): 03.10.2019 - Import Clearance at Steung Hav (I395): 17.10.2019
A14: 067 | B14: OMPLCHKHOMP037-19 | D14: IMPORT | E14: Sea | F14: BJC | G14: OMP | H14: 023/2019 | I14: 023/2019 | M14: 43733 | P14: ANU BHUM V.0025S | Q14: 43732 | R14: 43730 | S14: TH | T14: SHV15 | U14: SHV15 | V14: SISEZ | W14: JUMBO ROLL NAPKIN TISSUE | AB14: TRIU9269776-(40') | AC14: 120 ROLL | AE14: 1 | AF14: - Apply & Received TP (022/19): 01.10.2019 - Cleared Transit T13: 02.10.2019, - Delivered from OMP on 06.10.2019 by OMP and arrived at SISEZ: 07.10.2019 -​ Invoice Valuation (030/19): 18.10.2019, Apply Form D (019/19): 18.10.2019 - Clear Imp (I30): 19.10.2019 | AI14: =A14 -> 067
A15: 068 | B15: OMPLCHKHOMP036-19 | D15: IMPORT | E15: Sea | F15: BJC | G15: OMP | H15: 024/2019 | I15: 024/2019 | M15: 43733 | P15: ANU BHUM V.0025S | Q15: 43732 | R15: 43730 | S15: TH | T15: SHV15 | U15: SHV15 | V15: SISEZ | W15: CARTON BOX, PLASTIC WRAPPER, STICKER, BELT, PAPER CORE | AB15: TTNU9518175-(40') | AC15: 24 PLTS | AE15: 1 | AF15: - Reqeusted & Received TP (023/19): 01.10.2019 - Cleared Transit T12 (OMP): 02.10.2019, - Delivered from OMP on 06.10.2019 by OMP and arrived at SISEZ: 07.10.2019 -​ Invoice Valuation (027/19): 18.10.2019 - Clear Imp (I27): 18.10.2019 | AI15: =A15 -> 068 | AJ15: 023/19 | AL15: T12 | AM15: 43740
A16: 069 | B16: TW1934XG25 | D16: IMPORT | E16: Sea | F16: Royal CCT PLC (Mr. Samsen) | H16: 1900920-CT/ZT | I16: 1900920-CT/ZT | M16: 43739 | P16: T/B RATTANAWANICH 4 | S16: CN | T16: STH | U16: STH | V16: STH | W16: ALLOY DEFORMED REBAR (STEEL BAR) | AB16: BREAK BULK | AC16: 2051 BD = 4693.222MT | AF16: - Applied Form E: 24.10.2019 and received (12769): 25.09.2019 - Applied Invoice Valuation: 28.10.2019, Received (59957): 30.10.2019 - Import Clearance at Steung Hav (I416): 08.11.2019
A17: 070 | B17: TW1934XG24 | D17: IMPORT | E17: Sea | F17: Shang Tang Investment Co., Ltd (Mr. Samsen) | H17: 1900920-CT/ST | I17: 1900920-CT/ST | M17: 43739 | P17: T/B RATTANAWANICH 4 | S17: CN | T17: STH | U17: STH | V17: STH | W17: ALLOY DEFORMED REBAR (STEEL BAR) | AB17: BREAK BULK | AC17: 435 BD = 1008.330MT | AF17: - Apply New Importer and Asycuda: 25.10.2019 and Received: 25.10.2019 - Applied Form E: 24.10.2019 and received (12777): 25.09.2019 - Applied Invoice Valuation: 28.10.2019, Received (59955): 30.10.2019 - Import Clearance at Steung Hav (I409): 30.10.2019
A18: 071 | B18: GLSW943932 | D18: IMPORT | E18: Sea | F18: BJC | G18: GLS | H18: 20191016/VP-BJC-KH | I18: 20191016/VP-BJC-KH | M18: 43760 | Q18: 43764 | S18: VN | T18: PNH02 | U18: PNH02 | V18: SISEZ | W18: NAPKIN TISSUE PAPER | AB18: GAOU6458563-40HC, GAOU6458563-40HC | AC18: 72 ROLL | AE18: 2 | AF18: - Apply & Received TP (026/19): 28.10.2019 - Transit Clearance (T546): 30.10.2019 - Delivery from PPAP and arrive at SISEZ (By PPAP): 30.10.2019 - Apply and Received Form D (020/19) & Valuation (030/19): 25.10.2019 - Complete Clearance (I32): 25.11.2019 | AI18: =A18 -> 071 | AL18: 13800000 | AS18: 43787
A19: 072 | B19: 7762 6825 0576 | D19: IMPORT | E19: Air-LCL | F19: BJC | G19: BJC | H19: 9197700031 | I19: 847986 | M19: 43741 | O19: 618-72653136 | S19: CN | T19: PNH01 | U19: PNH01 | V19: SISEZ | W19: PIN, WHEEL, PIN, BUSHING, CROWNED PULLEY D = 100MM | AB19: LCL | AC19: 12 PCS | AF19: - Apply and Received TP (024/19): 04.10.2019 - Transit Clearance (T5601): 07.10.2019 - Delivered from PNH AIRPORT and arrived SISEZ: 07.10.2019 - Apply & Received Invoice Valuation (028/19): 18.10.2019 - Import Clearance (I31): 19.10.2019 | AI19: =A19 -> 072
A20: 073 | B20: OMPLCHKHOMP044/19 | D20: IMPORT | E20: Sea | F20: BJC | G20: OMP | H20: 026/2019 | I20: 026/2019 | M20: 43746 | Q20: 43745 | S20: TH | T20: SHV15 | U20: SHV15 | V20: SISEZ | W20: CARTON BOX, PLASTIC WRAPPER, STICKER, PAPER CORE | AB20: TCKU9303523-40HC, TTNU9660301-40HC | AC20: 49 PLT | AE20: 2 | AF20: - Reqeusted TP (OMP-SISEZ) & Received (025/19): 08.10.2019 - Cleared Transit T14 (OMP): 11.10.2019, - Delivered from OMP on 10.2019 by OMP and arrived at SISEZ: 10.2019 -Invoice Valuation (029/19): 18.10.2019 - Clear Imp (I28): 18.10.2019 | AI20: =A20 -> 073
A21: 074 | B21: GLSW946955 | D21: IMPORT | E21: sea | F21: BJC | G21: GLS | H21: 20191105/VP-BJC-KH | I21: 20191105/VP-BJC-KH | M21: 43774 | N21: GLS | Q21: 43794 | S21: VN | T21: PNH02 | U21: PNH02 | V21: SISEZ | W21: NAPKIN TISSUE PAPER | AB21: DRYU9950455-40HC, DRYU9955122-40HC, DRYU9970410-40HC | AC21: 108 ROLL | AE21: 3 | AF21: - Apply & Received Transit Permit (028/19): 25.11.2019 - Transit Clearance (T610): 26.11.2019 - Delivery from PPAP to SISEZ (By PPAP): 27.11.2019 - Apply & Received Form D (023/19): 04.12.2019, Valuation (034/19): 04.12.2019 - Complete Clearance (I37): 04.12.2019 | AI21: =A21 -> 074
A22: 075 | B22: OMPLCHKHOMP053/19 | D22: IMPORT | E22: Sea | F22: BJC | G22: OMP | H22: 028/2019 | I22: 028/2019 | M22: 43775 | N22: OMP | Q22: 43775 | S22: TH | T22: SHV15 | U22: SHV15 | V22: SISEZ | W22: JUMBO ROLL NAPKIN TISSUE | AB22: OMPL9002014-40HC, OMPL9055698-40HC | AC22: 155 ROLL | AE22: 2 | AF22: - Reqeusted & Received TP (026/19): 14.11.2019 - Cleared Transit (T15): 15.11.2019, - Delivered from OMP on 17.11.2019 by OMP and arrived at SISEZ: 18.11.2019 - Apply & Received Invoice Valuation (032/19): 25.11.2019, Form D (021/19): 25.11.2019 - Clear Imp (I33 ): 25.11.20192 | AI22: =A22 -> 075 | AJ22: 027/19 | AL22: T15 | AM22: 43784 | AS22: 43787
A23: 076 | B23: XDIC000321 | D23: IMPORT | E23: Sea | F23: GREAT WALL (FULL WELL) | G23: CMA | M23: 43774 | N23: CMA | P23: TOKYO TOWER V.0077.010 | Q23: 43753 | S23: CN | U23: SHV01 | V23: SIDP | W23: FAW CAR | AB23: UESU5180963-40HC | AC23: 2 UNITS | AE23: 1 | AF23: - Applied TP (SHV-SIDP): 06.11.2019, Received (04132អគរ.រគ): 08.11.2019, 08.11.2019 | AL23: Reimbursement | AS23: not yet get money
A24: 077 | B24: ONEYDXBV07167900 | D24: IMPORT | E24: Sea | F24: YAT SOVANN (FULL WELL) | G24: ONE | M24: 43785 | N24: ONE | P24: BRIDGE V.0092N | Q24: 43730 | S24: JEBEL ALI | U24: SHV01 | V24: SIDP | W24: ROLLS ROYCE | AB24: AMFU8745626-40HC | AC24: 1 UNIT | AE24: 1 | AF24: - Applied TP (SHV-SIDP): 18.11.2019, Received (04257អគរ.រគ): 18.11.2019, 19.11.2019
A25: 078 | B25: GLSW947971 | D25: IMPORT | E25: Sea | F25: BJC | G25: GLS | H25: 20191114/VP-BJC-KH | I25: 20191114/VP-BJC-KH | M25: 43790 | N25: GLS | Q25: 43794 | S25: VN | T25: PNH02 | U25: PNH02 | V25: SISEZ | W25: NAPKIN TISSUE PAPER, TOILET TISSUE PAPER | AB25: DRYU9954759-40HC, DRYU9972602 -40HC | AC25: 42 ROLL | AE25: 2 | AF25: - Apply & Received Transit Permit (029/19): 25.11.2019 - Transit Clearance (T611): 26.11.2019 - Delivery from PPAP to SISEZ (By PPAP): 28.11.2019 - Apply & Received Form D (022/19): 04.12.2019, Valuation (033/19): 04.12.2019 - Complete Clearance (I36): 04.12.2019 | AI25: =A25 -> 078
A26: 079 | B26: SHAWD059070 | C26: 43787 | D26: IMPORT | E26: Sea | F26: TF MOTORS (CAMBODIA) CO., LTD | G26: SHENDA | H26: CAM20190912N | I26: CAM20190912N | M26: 43799 | N26: IAL | Q26: 43804 | S26: CN | T26: PNH02 | U26: PNH02 | V26: SIBW | W26: NEW CAR | AB26: IAAU1726760 (40'), TCNU4203824 (40') | AC26: 5 UNITS | AE26: 2 | AF26: - Request TP (PPAP-SIBW): 06.12.2019, Received (04518អគរ): 07.12.2019 - Request TP (SIBW-MG Showroom): 06.12.2019, Received (SDR): 10.12.2019 - Transit Clearance T632 (IM8: PPAP-SIBW): 09.12.2019, and deliver and arrive to SIBW: 10.12.2019 - Stock in SIBW I 38 (IM7): 10.12.2019 - Do Clearance I 39 (IM4) for 3 Cars: 16.12.2019 - Do Clearance I41 (IM4) for 2 Care: 25.1.2019
A27: 080 | B27: OMPLCHKHOMP066-19 | D27: IMPORT | E27: Sea | F27: BJC | G27: OMP | H27: 030/2019 | I27: 030/2019 | M27: 43810 | N27: OMP | P27: NP SAMUTSAKHON V.014S | Q27: 43807 | S27: TH | T27: SHV15 | U27: SHV15 | V27: SISEZ | W27: CARTON BOX, PLASTIC WRAPPER, BLADE/STEEL | AB27: TCKU9552470-40HC | AC27: 20 PLTS | AE27: 1 | AF27: - Reqeusted & Received (030/19): 11.12.2019 - Cleared Transit (T16): 12.12.2019, - Delivered from OMP on 12.12.2019 by OMP and arrived at SISEZ: 13.12.2019 - Invoice Valuation (035/19): 23.12.2019 - Clear Imp (I40): 23.12.2019 | AI27: =A27 -> 080
A28: 081 | B28: GLSW951006 | C28: 43813 | D28: IMPORT | E28: Sea | F28: BJC | G28: PPAP | H28: 20191213/VP-BJC-KH | I28: 20191213/VP-BJC-KH | J28: 43812 | K28: VN-KH 19/01/36201 | L28: 43816 | M28: 43815 | N28: GLS | P28: PHUC THAI V.023S-2 | Q28: 43820 | S28: VN | T28: PNH02 | U28: PNH02 | V28: SISEZ | W28: NAPKIN TISSUE PAPER, TOILET TISSUE PAPER | X28: 12,337.80 | Y28: 12,440.80 | Z28: 11,145.11 | AA28: 10,527.11 | AB28: GAOU6131396-40HC | AC28: 20 ROLLS | AE28: 1 | AF28: - Reqeusted TP (PPAP-SISEZ): 23.12.019, Received (031/19): 23.12.2019 - Cleared Transit T671 (PPAP): 24.12.2019, delivered by PPAP and arrived at SISEZ: 25.12.2019 | AI28: =A28 -> 081 | AJ28: ..\2 BJC\081 GLSW951006
A29: 082 | B29: GLSW951005 | C29: 43813 | D29: IMPORT | E29: Sea | F29: BJC | G29: PPAP | H29: 20191210/VP-BJC-KH | I29: 20191210/VP-BJC-KH | J29: 43809 | K29: VN-KH 19/01/36193 | L29: 43816 | M29: 43815 | N29: GLS | P29: PHUC THAI V.023S-2 | Q29: 43820 | S29: VN | T29: PNH02 | U29: PNH02 | V29: SISEZ | W29: NAPKIN TISSUE PAPER | X29: 44,982.20 | Y29: 45,295.40 | Z29: 39,359.43 | AA29: 37,505.43 | AB29: GAOU6458033-40HC, CAIU8602367-40HC, CAIU8449577 -40HC | AC29: 108 ROLLS | AE29: 3 | AF29: - Reqeusted TP (PPAP-SISEZ): 23.12.019, Received (032/19): 23.12.2019 - Cleared Transit T673 (PPAP): 24.12.2019, delivered by PPAP and arrive at SISEZ: 25.12.2019 | AI29: =A29 -> 082 | AJ29: ..\2 BJC\082 GLSW951005
A30: 083 | B30: OMPLCHKHOMP004-20 | C30: 43842 | D30: IMPORT | E30: Sea | F30: BJC | G30: OMP | H30: 001/2020 | I30: 001/2020 | J30: 43839 | M30: 43845 | N30: OMP | P30: NP SAMUTSAKHON V.202S | Q30: 43844 | S30: TH | T30: SHV15 | U30: SHV15 | V30: SISEZ | W30: CARTON BOX, KRAFT PAPER | X30: 13,693.00 | Y30: 14,036.00 | Z30: 10,470.83 | AA30: 8,970.06 | AB30: OMPL9573568-40HC | AC30: 29 PALLETS | AE30: 1 | AF30: - Requested TP (OMP-SISEZ): 15.01.2020, Received (001/20): 15.01.2020 | AI30: =A30 -> 083 | AJ30: 001/20 | AL30: T1 | AM30: 43836
A31: 084 | B31: GLSN0040049 | C31: 43848 | D31: IMPORT | E31: Sea | F31: BJC | G31: PPAP | H31: 20200115/VP-BJC-KH | I31: 20200115/VP-BJC-KH | J31: 43845 | K31: VN-KH 20/01/02746 | L31: 43880 | M31: 43847 | N31: PPAP | Q31: 43855 | S31: VN | T31: PNH02 | U31: PNH02 | V31: SISEZ | W31: NAPKIN TISSUE PAPER, TOILET TISSUE PAPER | X31: 58,690.10 | Y31: 59,109.20 | Z31: 52,173.68 | AA31: 49,780.68 | AB31: SEGU5593865-40HC, GAOU6131992-40HC, GAOU6458603-40HC, DRYU9954580-40HC | AC31: 129 ROLLS | AE31: 4 | AF31: - Reqeusted TP (PPAP-SISEZ): 27.01.2020, Received (002/20): 27.01.2020 - Clearance Transit T66 (PPAP-SISEZ): 28.02.2020, Delivered by PPAP and arrived SISEZ: 29.01.2020 | AI31: =A31 -> 084 | AJ31: ..\2 BJC\084 GLSN0040049
A32: 085 | B32: OMPLCHKHOMP018-20 | C32: 43868 | D32: IMPORT | E32: Sea | F32: BJC | G32: OMP | H32: 003/2020 | I32: 003/2020 | J32: 43864 | M32: 43872 | N32: OMP | P32: NP SAMUTSAKHON V.206S | Q32: 43871 | S32: TH | T32: SHV15 | U32: SHV15 | V32: SISEZ | W32: CARTON BOX, PLASTIC WRAPPER | X32: 5,541.00 | Y32: 5,630.00 | Z32: 14,740.10 | AA32: 13,256.46 | AB32: OMPL9826075-40HC | AC32: 16 PALLETS | AE32: 1 | AF32: - Requested TP (OMP-SISEZ): 11.02.2020, Received (003/20): 12.02.2020 | AI32: =A32 -> 085
A33: 086 | B33: OMPLCHKHOMP019-20 | C33: 43868 | D33: IMPORT | E33: Sea | F33: BJC | G33: OMP | H33: 004/2020 | I33: 004/2020 | J33: 43864 | K33: D2020-0033433 | L33: 43872 | M33: 43872 | N33: OMP | P33: NP SAMUTSAKHON V.206S | Q33: 43871 | S33: TH | T33: SHV15 | U33: SHV15 | V33: SISEZ | W33: JUMBO ROLL TISSUE PAPER | X33: 8,701.00 | Y33: 9,001.00 | Z33: 11415.61 | AA33: 10390.76 | AB33: OMPL5578405-40HC | AC33: 120 ROLLS | AE33: 1 | AF33: - Requested TP (OMP-SISEZ): 11.02.2020, Received (004/20): 12.02.2020 | AG33: BERLI JUCKER | AI33: =A33 -> 086
A34: 087 | B34: GMD20HPHPNH0011 | C34: 43877 | D34: IMPORT | E34: Sea | F34: BJC | G34: PPAP | H34: 20200213/VP-BJC-KH | I34: 20200213/VP-BJC-KH | J34: 43874 | K34: VN-KH 20/01/05598 | L34: 43880 | M34: 43878 | N34: PPAP | P34: MEKONG02 V.156W | Q34: 43882 | S34: VN | T34: PNH02 | U34: PNH02 | V34: SISEZ | W34: NAPKIN TISSUE PAPER, TOILET TISSUE PAPER | X34: 57,891.60 | Y34: 58,310.70 | Z34: 51,467.27 | AA34: 49,075.27 | AB34: GMDU8181905-40HC, GMDU8188664-40HC, GMDU8181124-40HC, GMDU8180555-40HC | AC34: 129 ROLLS | AE34: 4 | AI34: 087
A35: 088 | B35: COSU4512576787 | C35: 43736 | D35: IMPORT | E35: Sea | F35: YAT SOVANN (FULL WELL) | G35: COSCO | M35: 43902 | N35: COSCO | P35: BRIDGE V.0100N | Q35: 43787 | S35: RU | T35: SHV01 | U35: SHV01 | V35: SIDP | W35: TOYOTA ALPHARD & MERCEDES-BENZ | Y35: 4,350.00 | AB35: CCLU7155182-40HC | AC35: 2 UNITS | AE35: 1
A36: 089 | B36: COSU6254749374 | C36: 43864 | D36: IMPORT | E36: Sea | F36: C.V.E.T | G36: (FULLWEL: Mr. KHEMARA) | M36: 43902 | N36: COSCO | P36: BRIDGE V.0118N | Q36: 43912 | S36: RU | T36: SHV01 | U36: SHV01 | V36: SIDP | W36: MERCEDES-BENZ | Y36: 4,370.00 | AB36: CBHU6302946-40HC | AC36: 2 UNITS | AE36: 1
A37: 090 | B37: OOLU2633339140 | C37: 43872 | D37: IMPORT | E37: Sea | F37: C.V.E.T | G37: (FULLWEL: Mr. KHEMARA) | M37: 43902 | N37: OOCL | S37: US | T37: SHV01 | U37: SHV01 | V37: SIDP | W37: USED ROLL ROYCE GHOST | Y37: 3,500.00 | AB37: CCLU9940780-45HC | AC37: 1 UNIT | AE37: 1
A38: 091 | B38: OMPLCHKHOMP029-20 | C38: 43902 | D38: IMPORT | E38: Sea | F38: BJC | G38: OMP | H38: 006/2020 | I38: 006/2020 | J38: 43895 | M38: 43902 | N38: OMP | P38: NP SAMUTSAKHON V.209S | S38: TH | T38: SHV15 | U38: SHV15 | V38: SISEZ | W38: CARTON BOX, PLASTIC WRAPPER, USED MACHINERY | X38: 8,218.00 | Y38: 8,335.00 | Z38: 21793.48 | AA38: 20307.17 | AB38: TTNU9896365-40HC | AC38: 17 PALLETS | AE38: 1 | AJ38: 006/20 | AL38: T4 | AM38: 43907
A39: 092 | B39: SHAWDO59954 | C39: 43900 | D39: IMPORT | E39: Sea | F39: TF MOTORS (CAMBODIA) CO., LTD | G39: SHENDA | H39: CAM20191205S2 | I39: CAM20191205S2 | J39: 43850 | K39: E201322602501007 | L39: 43901 | M39: 43910 | N39: IAL | P39: NEWPORT CYPRESS 79 V.044W | Q39: 43911 | S39: CN | T39: PNH02 | U39: PNH02 | V39: SIBW | W39: NEW CAR MG ZS | X39: 15,168.00 | Y39: 15,168.00 | Z39: 158400 | AA39: 156000 | AB39: CAIU9709690-40'HQ IAAU1695139-40'HQ IAAU1730857-40'HQ IAAU1773329-40'HQ | AC39: 12 UNITS | AD39: 0 | AE39: 4
A40: 093 | B40: GMD20HPHPNH0027 | C40: 43912 | D40: IMPORT | E40: Sea | F40: BJC | G40: GMD | H40: 20200318/VP-BJC-KH | I40: 20200318/VP-BJC-KH | J40: 43908 | K40: VN-KH 20/01/10323 | L40: 43915 | M40: 43916 | N40: GMD | S40: VN | T40: PNH02 | U40: PNH02 | V40: SI SEZ | W40: TOILET TISSUE PAPER, NAPKIN TISSUE PAPER | X40: 84,523.70.70 | Y40: 85,155.70 | Z40: 74653.48 | AA40: 71065.48 | AB40: GMDU8180534-40HC,GMDU8183791-40HC,GMDU8180663-40HC,GMDU8184587-40HC,GMDU8187673-40HC,GMDU8181525-40HC | AC40: 171 ROLLS | AE40: 6
A41: 094 | B41: COAU7222562693 | C41: 43919 | D41: IMPORT | E41: Truck | F41: HE VAN CONSTRUCTION (SJ) | G41: SJ | S41: VN | T41: BAVET | U41: BAVET | V41: SIDP | W41: CERAMIC DISH CERAMIC SPOON ALUMINIUM POT ALUMINIUM PAN OFFICE FURNITURE (PLYWOOD) | Y41: 4347.07 | AB41: CCLU7312996-40'HQ | AC41: 730 P'KGS | AE41: 1 | AF41: TRANSIT PERMIT ONLY
A42: 095 | B42: SHAWD059992 | C42: 43914 | D42: IMPORT | E42: Sea | F42: TF MOTORS (CAMBODIA) CO., LTD | G42: SHENDA | H42: CAM20200114S1 | I42: CAM20200114S1 | J42: 43881 | K42: E201322602505010 | L42: 43920 | N42: AIL | P42: NEWPORT CYPRESS 02 V.K13W | Q42: 43927 | S42: CN | T42: PNH02 | U42: PNH02 | V42: SIBW | W42: NEW CAR MG | X42: 76551 | Y42: 76551 | Z42: 698700 | AC42: 51 UNITS | AD42: 0 | AE42: 17 | AF42: INSPECT 3 TIME 10.04.20 (CUSTOMS OT: TRUCK ARRIVE SISEZ 19H, 13.04.20, 15.04.20) IM4 (I171: 04.09.20) 10 UNITS IM4 (I182: 08.09.20) 5 UNITS
A43: 096 | B43: SHAWD060137 | C43: 43920 | D43: IMPORT | E43: Sea | F43: M H MOTOR | G43: SHENDA | H43: KH20200113S | I43: KH20200113S | J43: 43915 | Q43: 43933 | S43: CN | T43: PNH02 | U43: PNH02 | V43: PNH02 | W43: AUTO PARTS | Y43: 2381.8 | AB43: IAAU1784848-40HC | AC43: 20 PKGS=1930PCS | AE43: 1
A44: 097 | B44: TW2010XG31/33/35 | C44: 43900 | D44: IMPORT | E44: Sea | F44: China Construction Fourth (Mr. Samsen) | H44: 20200305CT/CCF | I44: 20200305CT/CCF | J44: 43895 | K44: E20101148580004 | L44: 43909 | Q44: 43936 | S44: CN | T44: STH | U44: STH | V44: STH | W44: ALLOY DEFORMED REBAR (STEEL BAR), COILS OF WIRE ROD | X44: 2801.034 | Y44: 2801.034 | Z44: 1545518.7 | AA44: 1405017 | AB44: BREAK BULK | AC44: 1218 PKGS
A45: 098 | B45: 596617713 | C45: 43933 | D45: IMPORT | E45: Truck | F45: HE VAN CONSTRUCTION (SJ) | G45: SJ | M45: 43935 | N45: SJ | S45: VN | T45: BAVET | U45: BAVET | V45: SIDP | W45: DC FAN, TOILET TISSUE (2PLY), CERAMIC DISH, CERAMIC SPOON | Y45: 5079 | AB45: HASU4035927-40HC | AC45: 1158 PKG | AE45: 1 | AF45: TP:, GATE IN: 18.04.20
A46: 099 | B46: OMPLCHKHOMP039-20 | C46: 43937 | D46: IMPORT | E46: Sea | F46: BJC | G46: OMP | H46: 008/2020 | I46: 008/2020 | J46: 43929 | K46: D2020-0094091 | L46: 43941 | M46: 43943 | Q46: 43939 | S46: TH | T46: SHV15 | U46: SHV15 | V46: SISEZ | W46: JUMBO ROLL TISSUE PAPER | X46: 8512 | Y46: 8812 | Z46: 11175.91 | AA46: 10172.57 | AB46: PMLU9008711-40HC | AC46: 120 ROLL(S) | AE46: 1 | AJ46: 008/20 | AL46: T5 | AM46: 43948
A47: 100 | B47: HDMUNXHM1353666 | C47: 43941 | D47: IMPORT | E47: Land | G47: SJ | Q47: 43945 | S47: VN | T47: BAVET | U47: BAVET | V47: SIDP | W47: DC FAN, LED BLUB, WALLPAPER, MATTRESS SUPPORT, ALUMINIUM PT, ALUMINIUM PAN | Y47: 15968 | AB47: TGBU5890319-40HC, EITU1171296-40HC | AC47: 572 P'KGS | AE47: 2 | AF47: GATE IN: 25.04.20, T1548, I18
A48: 101 | B48: BV-202012-04 | C48: 43933 | D48: IMPORT | E48: Land | F48: WELLER (MR. VITOU) | G48: SJ | Q48: 43945 | S48: VN | T48: BAVET | U48: BAVET | V48: SIDP | W48: PAPER ROLL (LESS THAN 100GSM) | Y48: 14500 | AB48: TEMU5343250-20DC, OCGU2012276-20DC | AC48: 564 CTNS | AD48: 2 | AF48: GATE IN: 01.05.20
A49: 102 | B49: HWX2004225 | C49: 43946 | D49: IMPORT | E49: Land | F49: WELLER (MR. VITOU) | G49: SJ | Q49: 43949 | S49: VN | T49: BAVET | U49: BAVET | V49: SIDP | W49: MIX MART GOODS | Y49: 7018 | AB49: KKFU9025564-45HC | AC49: 929 CTNS | AE49: 1 | AF49: GATE IN: 29.04.20
A50: 103 | B50: COAU7223469890 | C50: 43946 | D50: IMPORT | E50: Land | F50: WELLER (MR. VITOU) | G50: SJ | Q50: 43949 | S50: VN | T50: BAVET | U50: BAVET | V50: SIDP | W50: FITNESS EQUIPMENT | Y50: 5153 | AB50: CSNU6539725-40HC | AC50: 80 PKGS | AE50: 1 | AF50: GATE IN: 29.04.20
A51: 104 | B51: 024A517627 | C51: 43953 | D51: IMPORT | E51: Land | F51: WELLER (MR. VITOU) | G51: SJ | Q51: 43958 | S51: VN | T51: BAVET | U51: BAVET | V51: SIDP | W51: FOODSTUFF | Y51: 5988.4 | AB51: WHSU5055888-40HC | AC51: 1010 CTNS | AE51: 1 | AF51: GATE IN: 08.05.20
A52: 105 | B52: YMLUI228337677 | C52: 43953 | D52: IMPORT | E52: Land | F52: WELLER (MR. VITOU) | G52: SJ | Q52: 43958 | S52: VN | T52: BAVET | U52: BAVET | V52: SIDP | W52: FITNESS EQUIPMENTS | Y52: 2374 | AB52: TEMU0755996-20GP | AC52: 45 P'KGS | AD52: 1 | AF52: GATE IN: 08.05.20
A53: 106 | B53: 024A517331 | C53: 43954 | D53: IMPORT | E53: Land | F53: WELLER (MR. VITOU) | G53: SJ | Q53: 43958 | S53: CN | T53: BAVET | U53: BAVET | V53: SIDP | W53: CABINET, MATTRESS SUPPORT, WALLPAPER, PLASTIC TAP, SHELF | Y53: 4551.5 | AB53: TCNU5684940-40HC | AC53: 185 P'KGS | AE53: 1 | AF53: GATE IN: 10.05.20
A54: 107 | B54: EGLV157000052345 | C54: 43955 | D54: IMPORT | E54: Land | F54: WELLER (MR. VITOU) | G54: SJ | Q54: 43958 | S54: CN | T54: BAVET | U54: BAVET | V54: SIDP | W54: WALLPAPER, MATTRESS SUPPORT, SPEAKER, ALUMINIUM POT, ALUMINIUM PAN | Y54: 14494.1 | AB54: IMTU9049250-40HC, EISU9161156-40HC | AC54: 453 P'KGS | AE54: 2 | AF54: GATE IN: 09.05.20
A55: 108 | B55: 597785935 | C55: 43958 | D55: IMPORT | E55: Land | F55: WELLER (MR. VITOU) | G55: SJ | Q55: 43963 | S55: CN | T55: BAVET | U55: BAVET | V55: SIDP | Y55: 6870 | AB55: MSKU9411754-40HC | AC55: 196 P'KGS | AE55: 1 | AF55: GATE IN: 16.05.20
A56: 109 | B56: COAU7223441790 | C56: 43953 | D56: IMPORT | E56: Land | F56: WELLER (MR. VITOU) | G56: SJ | Q56: 43963 | S56: CN | T56: BAVET | U56: BAVET | V56: SIDP | W56: STEEL SQUARE TUBE | Y56: 16800 | AB56: BSIU9601416-40HC | AC56: 626 P'KGS | AE56: 1 | AF56: GATE IN: 16.05.20
A57: 110 | B57: 598513776 | C57: 43961 | D57: IMPORT | E57: Land | F57: WELLER (MR. VITOU) | G57: SJ | Q57: 43966 | S57: CN | T57: BAVET | U57: BAVET | V57: SIDP | W57: MIX MART GOODS | Y57: 14219.2 | AB57: MRSU3892988/ML-CN5269225/40'HC MRKU3751499/ML-CN5226621/40'HC | AC57: 1499 CTNS | AE57: 2 | AF57: GATE IN: 18.05.20
A58: 111 | B58: 024A518730 | C58: 43960 | D58: IMPORT | E58: Land | F58: WELLER (MR. VITOU) | G58: SJ | Q58: 43966 | S58: CN | T58: BAVET | U58: BAVET | V58: SIDP | W58: FOODSTUFF | Y58: 5988.4 | AB58: WHLU5510380/WHLD900367/40'HC | AC58: 1010 CTNS | AE58: 1 | AF58: GATE IN: 16.05.20
A59: 112 | B59: 597742587 | C59: 43960 | D59: IMPORT | E59: Land | F59: WELLER (MR. VITOU) | G59: SJ | Q59: 43967 | S59: CN | T59: BAVET | U59: BAVET | V59: SIDP | W59: SCAFFOLDING FASTERNER, PAPER ROLL, WALLPAPER, LED BULB, CERAMIC DISH, CERAMIC SPOON | Y59: 17468 | AB59: MSKU0715545/ML-CN5247564/40'HC MRKU4130921/ML-CN5247551/40'HC | AC59: 215 CTNS & 357 ROLLS | AE59: 2 | AF59: GATE IN: 18.05.20
A60: 113 | B60: YMLUI232176328 | C60: 43960 | D60: IMPORT | E60: Land | F60: WELLER (MR. VITOU) | G60: SJ | Q60: 43967 | S60: CN | T60: BAVET | U60: BAVET | V60: SIDP | W60: MATTRESS SUPPORT, DC FAN, SCAFFOLDING FASTERNER, ALUMINIUM PAN | Y60: 4239 | AB60: CAIU7846667/YMAG131406/40'HQ | AC60: 342 CTNS | AE60: 1 | AF60: GATE IN: 18.05.20
A61: 114 | B61: YMLUI228338315 | C61: 43964 | D61: IMPORT | E61: Land | F61: WELLER (MR. VITOU) | G61: SJ | Q61: 43971 | S61: CN | T61: BAVET | U61: BAVET | V61: SIDP | W61: FITNESS EQUIPMENTS | Y61: 4450 | AB61: TGBU6454264/YMAG625569/40'HQ | AC61: 65 CTNS | AE61: 1 | AF61: GATE IN: 21.05.20
A62: 115 | B62: ATCCA9080009 | C62: 43963 | D62: IMPORT | E62: Land | F62: WELLER (MR. VITOU) | G62: SJ | Q62: 43971 | S62: CN | T62: BAVET | U62: BAVET | V62: SIDP | W62: FOODSTUFF | Y62: 6137.56 | AB62: QATU4500024/K9730529/40'HC | AC62: 464 CTNS | AE62: 1 | AF62: GATE IN: 21.05.20
A63: 116 | B63: COAU7223798696 | C63: 43966 | D63: IMPORT | E63: Land | F63: WELLER (MR. VITOU) | G63: SJ | Q63: 43972 | S63: CN | T63: BAVET | U63: BAVET | V63: SIDP | W63: ALUMINIUM PAN, SCREW, LAMP, FURNITURE (PLYWOOD) | Y63: 3155.5 | AB63: CCLU7250370/CL136567/40'HQ | AC63: 201 CTNS | AE63: 1 | AF63: GATE IN: 22.05.20
A64: 117 | B64: 024A520508 | C64: 43973 | D64: IMPORT | E64: Land | F64: WELLER (MR. VITOU) | G64: SJ | Q64: 43977 | S64: CN | T64: BAVET | U64: BAVET | V64: SIDP | W64: MIXED CARGO | Y64: 10059.1 | AB64: BHCU4991093/WHLD912055/40'HC | AC64: 246 CTNS & 524 ROLLS | AE64: 1 | AF64: GATE IN: 26.05.20
A65: 118 | B65: NSASGNG17340 | C65: 43969 | D65: IMPORT | E65: Land | F65: WELLER (MR. VITOU) | G65: SJ | Q65: 43977 | S65: CN | T65: BAVET | U65: BAVET | V65: SIDP | W65: MIXED MART CARGO | Y65: 5681.5 | AB65: DFSU7676325/SITJ790819/40'HC | AC65: 271 CTNS | AE65: 1 | AF65: GATE IN: 27.05.20
A66: 119 | B66: COAU7223441793 | C66: 43972 | D66: IMPORT | E66: Land | F66: WELLER (MR. VITOU) | G66: SJ | Q66: 43978 | S66: CN | T66: BAVET | U66: BAVET | V66: SIDP | W66: HOTEL EQUIPMENT | Y66: 6286.3 | AB66: DFSU6604059/190228006/40'HC | AC66: 125 CTNS & 107 ROLLS | AE66: 1 | AF66: GATE IN: 01.06.20
A67: 120 | B67: COAU7223795490 | C67: 43971 | D67: IMPORT | E67: Land | F67: WELLER (MR. VITOU) | G67: SJ | Q67: 43978 | S67: CN | T67: BAVET | U67: BAVET | V67: SIDP | W67: STEEL SQUARE TUBE | Y67: 17300 | AB67: CCLU7971442/U346783/40'HQ | AC67: 670 BUNDLES | AE67: 1 | AF67: GATE IN: 29.05.20
A68: 121 | B68: NSASGNG17692 | C68: 43976 | D68: IMPORT | E68: Land | F68: WELLER (MR. VITOU) | G68: SJ | Q68: 43980 | S68: CN | T68: BAVET | U68: BAVET | V68: SIDP | W68: MIX MART GOODS | Y68: 9226 | AB68: TCKU7363170/SITJ787198/40'HC | AC68: 367CTNS & 100ROLLS | AE68: 1 | AF68: - Apply TP: 28.05.20, TP Ref: 01723 (29.05.20) - Entry DP Request: 01.06.20 - Offset: - Completed | AG68: SHENZHEN
A69: 122 | B69: COAU7223666872 | C69: 43976 | D69: IMPORT | E69: Land | F69: WELLER (MR. VITOU) | G69: SJ | Q69: 43980 | S69: CN | T69: BAVET | U69: BAVET | V69: SIDP | W69: CONSTRUCTION MATERIALS | Y69: 26882.5 | AB69: CCLU7883932/CK311078/40'HQ | AC69: 50BARRELS & 1250BAGS | AE69: 1 | AF69: - Apply TP: 28.05.20, TP Ref: 01723 (29.05.20) - Entry DP Request: 01.06.20 - Offset: - Completed | AG69: DONGGUAN
A70: 123 | B70: YMLUI232176924 | C70: 43974 | D70: IMPORT | E70: Land | F70: WELLER (MR. VITOU) | G70: SJ | Q70: 43985 | S70: CN | T70: BAVET | U70: BAVET | V70: SIDP | W70: FURNITURE | Y70: 130121.92 | AA70: 6 | AB70: BMOU6334060/YMAE657539/40'HQ MAGU5563906/YMAF737588/40'HQ TEMU8512293/YMAF737556/40'HQ YMLU8699990/YMAF737526/40'HQ YMLU8832530/YMAF772649/40'HQ YMMU6085194/YMAG122205/40'HQ | AC70: 2530 P'KGS | AD70: 0 | AE70: 6 | AF70: - Apply TP: 01.06.20, TP Ref: 01770 (02.06.20) - Entry DP Request: 04.06.20 - Offset: 05.06.20 - Complete
A71: 124 | B71: 031A516578 | C71: 43977 | D71: IMPORT | E71: Land | F71: WELLER (MR. VITOU) | G71: SJ | Q71: 43986 | S71: CN | T71: BAVET | U71: BAVET | V71: SIDP | W71: MIX MART GOODS | Y71: 11610 | AA71: 6 | AB71: WHSU5325140/WHLK253947/40'HC DFSU7759991/WHLK253839/40'HC | AC71: 400 CTNS | AD71: 0 | AE71: 2 | AF71: - Apply TP: 01.06.20, TP Ref: 01777 (02.06.20) - Entry DP Request: 06.06.20 - Offset: 05.06.20 - Completed
A72: 125 | B72: YMLUI232176943 | C72: 43980 | D72: IMPORT | E72: Land | F72: WELLER (MR. VITOU) | G72: SJ | Q72: 43986 | S72: CN | T72: BAVET | U72: BAVET | V72: SIDP | W72: CONSTRUCTION MATERIALS | Y72: 9444 | AA72: 6 | AB72: FSCU8054960/YMAF737490/40'HQ | AC72: 226 CTNS | AD72: 0 | AE72: 1 | AF72: - Apply TP: 01.06.20, TP Ref: 01778 (02.06.20) - Entry DP Request: 05.06.20 - Offset: 05.06.20 - Completed
A73: 126 | B73: HDMUQSHM8562901 | C73: 43972 | D73: IMPORT | E73: Land | F73: WELLER (MR. VITOU) | G73: SJ | Q73: 43986 | S73: CN | T73: BAVET | U73: BAVET | V73: SIDP | W73: FURNITURE | Y73: 20789.46 | AA73: 6 | AB73: SEGU5835043/19197976/40'HQ | AC73: 414 P'KGS | AD73: 0 | AE73: 1 | AF73: - Apply TP: 02.06.20, TP Ref: 01791 (03.06.20) - Entry DP Request: 05.06.20 - Offset: 05.06.20 - Completed
A74: 127 | B74: 024A522062 | C74: 43984 | D74: IMPORT | E74: Land | F74: WELLER (MR. VITOU) | G74: SJ | Q74: 43987 | S74: CN | T74: BAVET | U74: BAVET | V74: SIDP | W74: MIXED CARGO AND FURNITURE | Y74: 55455.86 | AA74: 6 | AB74: TCNU6677020/WHLD900321/40'HC TCNU3882253/WHLD907662/40'HC WHLU5645446/WHLD907654/40'HC | AC74: 2035CTNS & 100ROLLS | AD74: 0 | AE74: 3 | AF74: TP: 01806 (04.06.20) GATE IN: 06.06.20
A75: 128 | B75: NSASGNG18190 | C75: 43984 | D75: IMPORT | E75: Land | F75: WELLER (MR. VITOU) | G75: SJ | Q75: 43987 | S75: CN | T75: BAVET | U75: BAVET | V75: SIDP | W75: MIXED CARGO AND FURNITURE | Y75: 28639.86 | AA75: 6 | AB75: UETU5777340/SITJ838415/40'HC SEGU6847305/SITJ838423/40'HC FFAU1160665/SITJ838430/40'HC | AC75: 1025 CTNS | AD75: 0 | AE75: 3 | AF75: TP: 01807 (04.06.20) GATE IN: 08.06.20
A76: 129 | B76: YMLUI228339461 | C76: 43984 | D76: IMPORT | E76: Land | F76: WELLER (MR. VITOU) | G76: SJ | Q76: 43988 | S76: CN | T76: BAVET | U76: BAVET | V76: SIDP | W76: FITNESS EQUIPMENTS | Y76: 5361.5 | AA76: 6 | AB76: BEAU4586160/YAMG626790/40'HQ | AC76: 85 P'KGS | AD76: 0 | AE76: 1 | AF76: TP: 01827 (05.06.20) GATE IN: 08.06.20
A77: 130 | B77: 024A523566 | C77: 43984 | D77: IMPORT | E77: Land | F77: WELLER (MR. VITOU) | G77: SJ | Q77: 43988 | S77: CN | T77: BAVET | U77: BAVET | V77: SIDP | W77: MIIXED CARGO | Y77: 30581.75 | AA77: 6 | AB77: CAAU5155051/WHLF647099/40'HC WHLU5765457/WHLF647172/40'HC TCNU8887324/WHLF647066/40'HC | AC77: 1155CTNS & 215ROLLS | AD77: 0 | AE77: 3 | AF77: TP: 01829 (05.06.20) GATE IN: 12.06.20
A78: 131 | B78: 024A523584 | C78: 43984 | D78: IMPORT | E78: Land | F78: WELLER (MR. VITOU) | G78: SJ | Q78: 43988 | S78: CN | T78: BAVET | U78: BAVET | V78: SIDP | W78: MIIXED CARGO | Y78: 31375.5 | AA78: 6 | AB78: WHLU5710937/WHLD906912/40'HC WHLU5537992/WHLF647170/40'HC WHSU5093419/WHLC540629/40'HC | AC78: 613CTNS & 500ROLLS | AD78: 0 | AE78: 3 | AF78: TP: 01828 (05.06.20) GATE IN: 11.06.20
A79: 132 | B79: 024A523355 | C79: 43984 | D79: IMPORT | E79: Land | F79: WELLER (MR. VITOU) | G79: SJ | Q79: 43988 | S79: CN | T79: BAVET | U79: BAVET | V79: SIDP | W79: FOODSTUFF AND MIXED CARGO | Y79: 32045 | AA79: 6 | AB79: MAGU5478384/WHLF647194/40'HC DFSU7674301/WHLC540630/40'HC | AC79: 1811CTNS & 55P'KGS | AD79: 0 | AE79: 2 | AF79: TP: 01830 (05.06.20) GATE IN: 11.06.20
A80: 133 | B80: 599420902 | C80: 43983 | D80: IMPORT | E80: Land | F80: WELLER (MR. VITOU) | G80: SJ | Q80: 43991 | S80: CN | T80: BAVET | U80: BAVET | V80: SIDP | W80: MIXED CARGO | Y80: 11189.5 | AA80: 6 | AB80: MRKU3093340/ML-CN5229836/40'HC | AC80: 300CTNS & 120ROLLS | AD80: 0 | AE80: 1 | AF80: TP: 01855 (08.06.20) GATE IN: 10.06.20
A81: 134 | B81: COAU7882001280 | C81: 43981 | D81: IMPORT | E81: Land | F81: WELLER (MR. VITOU) | G81: SJ | Q81: 43991 | S81: CN | T81: BAVET | U81: BAVET | V81: SIDP | W81: CONSTRUCTION MATERIALS | Y81: 19700 | AA81: 6 | AB81: OOCU7152201/CL137995/40'HQ | AC81: 600 P'KGS | AD81: 0 | AE81: 1 | AF81: TP: 01854 (08.06.20) GATE IN: 12.06.20
A82: 135 | B82: COAU7224196912 | C82: 43987 | D82: IMPORT | E82: Land | F82: WELLER (MR. VITOU) | G82: SJ | Q82: 43993 | S82: CN | T82: BAVET | U82: BAVET | V82: SIDP | W82: MIXED CARGO | Y82: 18174 | AA82: 6 | AB82: CCLU7822881/CL138806/40'HQ UETU5108345/CL138889/40'HQ | AC82: 590CTNS &200ROLLS | AD82: 0 | AE82: 2 | AF82: TP: 01889 (10.06.20) GATE IN: 14.06.20
A83: 136 | B83: SHAWD060776 | C83: 43982 | D83: IMPORT | E83: Sea | F83: M H MOTOR | G83: SHENDA | H83: KH20200506S | I83: KH20200506S | J83: 44009 | P83: MEKONG 8 V.094W | Q83: 43991 | S83: CN | T83: PNH02 | U83: PNH02 | V83: PNH02 | W83: AUTO PARTS | Y83: 2030 | AA83: 67 | AB83: HMMU6083300-40'HQ | AC83: 15 PKGS | AD83: 0 | AE83: 1 | AF83: - Applied CV: 15.06.20, CV Ref: 25930 (17.06.20), - IM4: I6929 & I6930 (PART): 19.06.20, - Truck (Mr. Boramey): 19.06.20, Arrived: 19.06.20, Unloaded: 20.06.20 - Offset: 24.06.20 - Completed | AG83: SAIC MOTOR | AH83: 43992
A84: 137 | B84: 024A523565 | C84: 43988 | D84: IMPORT | E84: Land | F84: WELLER (MR. VITOU) | G84: SJ | Q84: 43995 | S84: CN | T84: BAVET | U84: BAVET | V84: SIDP | W84: MIXED CARGO | Y84: 3503.3 | AA84: 6 | AB84: PHRU2502446/NS2064884/20'DC | AC84: 25 CTNS & 107 ROLLS | AD84: 1 | AE84: 0 | AF84: TP: 01908 (12.06.20) GATE IN: 15.06.20
A85: 138 | B85: 024A523562 | C85: 43988 | D85: IMPORT | E85: Land | F85: WELLER (MR. VITOU) | G85: SJ | Q85: 43995 | S85: CN | T85: BAVET | U85: BAVET | V85: SIDP | W85: MIXED CARGO AND FURNITURE | Y85: 9864 | AA85: 6 | AB85: WHSU5475643/WHLF652840/40'HC | AC85: 360 CTNS & 90ROLLS | AD85: 0 | AE85: 1 | AF85: TP: 01907 (12.06.20) GATE IN: 14.06.20
A86: 139 | B86: NSASGNG18517 | C86: 43990 | D86: IMPORT | E86: Land | F86: WELLER (MR. VITOU) | G86: SJ | Q86: 43995 | S86: CN | T86: BAVET | U86: BAVET | V86: SIDP | W86: MIXED CARGO AND FOODSTUFF | Y86: 21249 | AA86: 6 | AB86: TCNU5294388/SITJ837466/40'HC BMOU6517440/SITJ836628/40'HC | AC86: 749 CTNS & 180 ROLLS | AD86: 0 | AE86: 2 | AF86: TP: 01996 (12.06.20) GATE IN: 16.06.20
A87: 140 | B87: YMLUI226021338 | C87: 43987 | D87: IMPORT | E87: Land | F87: WELLER (MR. VITOU) | G87: SJ | Q87: 43995 | S87: CN | T87: BAVET | U87: BAVET | V87: SIDP | W87: PLYWOOD, GYPSUM BOARD | Y87: 24500 | AA87: 6 | AB87: MAGU5672677/YMAG688749/40'HQ YMMU6141446/YMAH052069/40'HQ | AC87: 430 P'KGS | AD87: 0 | AE87: 2 | AF87: TP: 01905 (12.06.20) GATE IN: 15.06.20
A88: 141 | B88: 203157867 | C88: 43995 | D88: IMPORT | E88: SEA-LAND-FCL | F88: WELLER (MR. VITOU) | G88: SJ | Q88: 43997 | S88: CN | T88: BAVET | U88: BAVET | V88: SIDP | W88: MIXED CARGO | Y88: 14711.6 | AA88: 6 | AB88: MSKU4531680/ML-CN5219046/40'HC MSKU4606244/ML-CN4696287/40'HC | AC88: 315CTNS & 80ROLLS | AD88: 0 | AE88: 2 | AF88: TP: 01948 (15.06.20): GATE IN: 16.06.20 (CONT: 1680), 17.06.20 (CONT: 6244) | AG88: DONGGUAN | AH88: 43997
A89: 142 | B89: YMLUI235179868 | C89: 43993 | D89: IMPORT | E89: SEA-LAND-FCL | F89: WELLER (MR. VITOU) | G89: SJ | Q89: 44001 | S89: CN | T89: BAVET | U89: BAVET | V89: SIDP | W89: WALL PUTTY POWDER | Y89: 26500 | AA89: 6 | AB89: YMMU6067565/YMAH448026/40'HC | AC89: 1060 BAGS | AD89: 0 | AE89: 1 | AF89: TP: 01984 (17.06.20): GATE IN: 20.06.20 | AG89: HK RONGTIAN | AH89: 43999
A90: 143 | B90: YMLUI228339771 | C90: 43993 | D90: IMPORT | E90: SEA-LAND-FCL | F90: WELLER (MR. VITOU) | G90: SJ | Q90: 44001 | S90: CN | T90: BAVET | U90: BAVET | V90: SIDP | W90: CERAMIC TILES | Y90: 77390 | AA90: 6 | AB90: BMOU1143902/YMAG624465/20'DC BMOU1253140/YMAG624468/20'DC FTAU1143876/YMAG624462/20'DC YMLU3322107/YMAG624463/20'DC YMMU1207725/YMAG624469/20'DC | AC90: 3100 CTNS | AD90: 5 | AE90: 0 | AF90: TP: 01983 (17.06.20), GATE IN: 20.06.20 | AG90: HK RONGTIAN | AH90: 43999
A91: 144 | B91: EGLV149002350059 | C91: 43989 | D91: IMPORT | E91: SEA-LAND-FCL | F91: WELLER (MR. VITOU) | G91: SJ | Q91: 44001 | S91: CN | T91: BAVET | U91: BAVET | V91: SIDP | W91: STEEL SQUARE TUBE | Y91: 15600 | AA91: 6 | AB91: EITU1673967/EMCFWM7080/40'HC | AC91: 570 BUNDLES | AD91: 0 | AE91: 1 | AF91: TP: 01982 (17.06.20), GATE IN: 20.06.20 | AG91: DONGGUAN | AH91: 43999
A92: 145 | B92: EGLV157000075507 | C92: 43994 | D92: IMPORT | E92: SEA-LAND-FCL | F92: WELLER (MR. VITOU) | G92: SJ | Q92: 44001 | S92: CN | T92: BAVET | U92: BAVET | V92: SIDP | W92: MIXED CARGO AND FURNITURE | Y92: 12891.2 | AA92: 6 | AB92: EGHU9597939/EMCAYS2299/40'HC | AC92: 478 CTNS | AD92: 0 | AE92: 1 | AF92: TP: 01981 (17.06.20), GATE IN: 21.06.20 | AG92: GUANGZHOU | AH92: 43999
A93: 146 | B93: 024A524434 | C93: 43995 | D93: IMPORT | E93: SEA-LAND-FCL | F93: WELLER (MR. VITOU) | G93: SJ | Q93: 44003 | S93: CN | T93: BAVET | U93: BAVET | V93: SIDP | W93: MIXED CARGO | Y93: 12940.5 | AA93: 6 | AB93: WHSU5393801/WHLD900322/40'HC | AC93: 356 CTNS & 90 ROLLS | AD93: 0 | AE93: 1 | AF93: TP: 02010 (19.06.20), GATE IN: 21.06.20 | AG93: SHENZHEN | AH93: 44001
A94: 147 | B94: SSLHCM2004202 | C94: 43999 | D94: IMPORT | E94: SEA-LAND-FCL | F94: WELLER (MR. VITOU) | G94: SJ | Q94: 44004 | S94: CN | T94: BAVET | U94: BAVET | V94: SIDP | W94: APHALT ANTI-STRIPPING AGENT | Y94: 24000 | AA94: 6 | AB94: BSIU9305287/T745337/40'HC | AC94: 480 BARRELS | AD94: 0 | AE94: 1 | AF94: TP: 02009 (19.06.20), GATE IN: 24.06.20 | AG94: YIWU QIANGSHENG | AH94: 44001
A95: 148 | B95: 024A525986 | C95: 43999 | D95: IMPORT | E95: SEA-LAND-FCL | F95: WELLER (MR. VITOU) | G95: SJ | Q95: 44004 | S95: CN | T95: BAVET | U95: BAVET | V95: SIDP | W95: MIXED CARGO | Y95: 10460 | AA95: 6 | AB95: WHLU5696989/WHLD907105/40'HC | AC95: 271 CTNS | AD95: 0 | AE95: 1 | AF95: TP: 02026 (22.06.20), GATE IN: 23.06.20 | AG95: SHENZHEN | AH95: 44004
A96: 149 | B96: COAU7224172150 | C96: 44000 | D96: IMPORT | E96: SEA-LAND-FCL | F96: WELLER (MR. VITOU) | G96: SJ | Q96: 44005 | S96: CN | T96: BAVET | U96: BAVET | V96: SIDP | W96: TOILET TISSUE | Y96: 4050 | AA96: 6 | AB96: CSNU6257038/CJ770590/40'HQ | AC96: 960 CTNS | AD96: 0 | AE96: 1 | AF96: TP: 02036 (23.06.20), GATE IN: 24.06.20 | AG96: DONGGUAN | AH96: 44004
A97: 150 | B97: COAU7224193104 | C97: 44001 | D97: IMPORT | E97: SEA-LAND-FCL | F97: WELLER (MR. VITOU) | G97: SJ | Q97: 44006 | S97: CN | T97: BAVET | U97: BAVET | V97: SIDP | W97: MIXED CARGO | Y97: 14082.35 | AA97: 6 | AB97: CCLU7135890/CL492753/40'HQ | AC97: 489 CTNS | AD97: 0 | AE97: 1 | AF97: TP: 02060 (24.06.20, GATE IN: | AG97: SHENZHEN | AH97: 44005
A98: 151 | B98: YMLUI228340746 | C98: 44000 | D98: IMPORT | E98: SEA-LAND-FCL | F98: WELLER (MR. VITOU) | G98: SJ | Q98: 44006 | S98: CN | T98: BAVET | U98: BAVET | V98: SIDP | W98: CERAMIC TILES | Y98: 76159 | AA98: 6 | AB98: FCIU6263344/YMAG628507/20'DC SEGU2293946/YMAG628508/20'DC SEGU2809565/YMAG628504/20'DC TEMU0336562/YMAG628505/20'DC TEMU0967737/YMAG628506/20'DC | AC98: 3050 CTNS | AD98: 5 | AE98: 0 | AF98: TP: 02062 (24.06.20), GATE IN: | AG98: HK RONGTIAN | AH98: 44005
A99: 152 | B99: 024A526176 | C99: 44003 | D99: IMPORT | E99: SEA-LAND-FCL | F99: WELLER (MR. VITOU) | G99: SJ | Q99: 44007 | S99: CN | T99: BAVET | U99: BAVET | V99: SIDP | W99: MIXED CARGO | Y99: 13000 | AA99: 6 | AB99: WHSU5170264/WHL1689311/40'HC | AC99: 316 CTNS | AD99: 0 | AE99: 1 | AF99: TP: 02061 (24.06.20), GATE IN: | AG99: SHENZHEN | AH99: 44005
... A101: 154 | B101: YMLUI235179958 | C101: 43995 | D101: IMPORT | E101: SEA-LAND-FCL | F101: WELLER (MR. VITOU) | G101: SJ | Q101: 44008 | S101: CN | T101: BAVET | U101: BAVET | V101: SIDP | W101: MIXED CARGO | Y101: 6275 | AA101: 6 | AB101: TCKU1260894/YMAH449995/20'DC | AC101: 179 CTNS | AD101: 1 | AE101: 0 | AF101: TP: 02067 (24.06.20), GATE IN: | AG101: DONGGUAN | AH101: 44005
...

Sheet DATA INF
O1: ADDRESS FOR REQUEST LETTER | S1: FOR AUT | AB1: [$-12000453] dddd mmmm yyyy | AC1: [@ប្រតិទិនចន្ទគតិ១] &[@ប្រតិទិនចន្ទគតិ២]&[@ប្រតិទិនចន្ទគតិ៣]&[@ប្រតិទិនចន្ទគតិ៤]&[@ប្រតិទិនចន្ទគតិ៥] | AD1: [$-12000453]dd ខែ mmmm ឆ្នាំ yyyy") | AE1: [$-km-KH,1200] dddd
A2: PORT | B2: 2 | C2: SR CODE | D2: LOCATION SR 2 | E2: LINK SR | F2: INF-M 1 | H2: CNEE | I2: PIC | J2: FOR CO CV | O2: ADD NEW CNEE | P2: HEADER | Q2: LOLO | S2: NAME | T2: ID CARD | U2: CNEE | V2: VAT | W2: TEL | X2: NAME SI | Y2: ID CARD SI | Z2: TEL | AB2: Date | AC2: ប្រតិទិនចន្ទគតិ2023 | AD2: ប្រតិទិនចន្ទគតិ១ | AE2: ប្រតិទិនចន្ទគតិ២ | AF2: ប្រតិទិនចន្ទគតិ៣ | AG2: ប្រតិទិនចន្ទគតិ៤ | AH2: ប្រតិទិនចន្ទគតិ៥ | AK2: លេខរៀងខែ/ស័ក | AL2: ចន្ទគតិ | AM2: សុរិយាគតិ | AN2: ស័ក
A3: POI01 | B3: ការិយាល័យគយ និងរដ្ឋាករមាត់ច្រកអន្តរជាតិប៉ោយប៉ែត | C3: HHA | D3: ហេង ហ៊ុយ (Heng Huy Autocars) ដែលមានអាស័យដ្ឋាន #ដីឡូត៍ ១៥០៦៧ ផ្លូវ១១៤ សង្កាត់មនោរម្យ ខណ្ឌ៧មករា រាជធានីភ្នំពេញ | F3: ង៉ូវ ចាន់រស្មី | H3: TF MOTORS (CAMBODIA) CO., LTD | I3: ង៉ូវ ចាន់រស្មី | J3: PNH02 | K3: មាត់ច្រកកំពង់ផែអន្តរជាតិភ្នំពេញ | M3: DON THONGPRAPAI | N3: កាន់លិខិតឆ្លងដែនលេខ: AB4555337 ទូរសព្ទ័លេខ 095 777 975 ជំនួសប្រធានក្រុមហ៊ុន SUVANNAPHUM INVESTMENT CO., LTD អត្តសញ្ញាណកម្មសារពើពន្ធ (VAT) លេខៈ L001-901801901 ជានីតិបុគ្គលជើងសារគយដែលមានរូបវន្តបុគ្គលជើងសាគយតំណាងលោក/លោកស្រី ផេង សុវណ្ណា អត្តសញ្ញាណប័ណ្ណសញ្ជាតិខ្មែរលេខៈ 190228973 ទូរសព្ទ័លេខ 012 333 901 ប័ណ្ណសម្គាល់ជើងសាគយលេខ #699B ផុតសុពលភាពថ្ងៃទី 31 ខែ ធ្នូ ឆ្នាំ 2024 ។ | O3: TF MOTORS (CAMBODIA) CO., LTD | P3: NO. 174-175 (BLOCK 1C, 1D AND 2C, 2D) OF CALIFORNIA HOUSE, RUSSIAN FEDERATION BLVD, SANGKAT TEUK THLA, PHNOM PENH, CAMBODIA VAT: L001-104008598, TEL: +855 888 772 209 | Q3: NO. 174-175 (BLOCK 1C, 1D AND 2C, 2D) OF CALIFORNIA HOUSE, RUSSIAN FEDERATION BLVD, SANGKAT TEUK THLA, PHNOM PENH, CAMBODIA VAT: L001-104008598, TEL: +855 888 772 209 | R3: POIPET | S3: MO GUANKANG | T3: EG7009964 | U3: HUAN YA HE ZHONG (CAMBODIA) TRADING CO., LTD | V3: L001-901908165 | W3: 017 555924 | AB3: 45658 | AC3: ថ្ងៃពុធ ៣កើត ខែបុស្ស ឆ្នាំរោង ឆស័ក ព.ស.២៥៦៨ | AD3: ថ្ងៃចន្ទ | AE3: ៥ រោច | AF3: ខែមិគសិរ | AG3: ឆ្នាំថោះ | AH3: បញ្ចស័ក ពស. ២៥៦៧ | AK3: 1 | AL3: មិគសិរ | AM3: មករា | AN3: ឯកស័ក | AP3: 1
A4: POI02 | B4: សាខាគយ និងរដ្ឋាករដូង | C4: MG | D4: MORRIS GARAGES ដែលមានអាសយដ្ឋាន #អគារ ១៧៤-១៧៥ (ប្លុក ១C, ១D និង ២C, ២D) នៃកាលីហ្វ័រញ៉ា សូសលហៅស៍ ផ្លូវ សហព័ន្ធរុស្ស៊ី សង្កាត់ទឹកថ្លា ខណ្ឌសែនសុខ រាជធានីភ្នំពេញ ជាទីតាំងបង្ហាញ (SHOWROOM)របស់ក្រុមហ៊ុន TF MOTORS (CAMBODIA) CO., LTD។ | E4: https://goo.gl/maps/WuC6bokrk32WsiPf6 | F4: លាង សុភា | G4: ភេទប្រុស មានអត្តសញ្ញាណប័ណ្ណសញ្ជាតិខ្មែរលេខៈ0107001600(01) មានតួនាទីជាបុគ្គលិកផ្នែករដ្ឋាបាល TF MOTORS (CAMBODIA) CO., LTD អត្តសញ្ញាណកម្មសារពើពន្ធ (VAT)លេខៈ L001-104008598 ទូរសព្ទ័លេខៈ 010 483 668 | H4: TF MOTORS (CAMBODIA) CO., LTD | I4: លាង សុភា | J4: SHV11 | K4: កំពង់ផែអន្តរជាតិក្រុងព្រះសីហនុ | M4: WICHAI ON-SRI | N4: កាន់លិខិតឆ្លងដែនលេខ: AD0667637 ទូរសព្ទ័លេខ 089 890 324 ជាប្រធានក្រុមហ៊ុន SUVANNAPHUM INVESTMENT CO., LTD អត្តសញ្ញាណកម្មសារពើពន្ធ (VAT) លេខៈ L001-901801901 ជានីតិបុគ្គលជើងសារគយដែលមានរូបវន្តបុគ្គលជើងសាគយតំណាងលោក/លោកស្រី ផេង សុវណ្ណា អត្តសញ្ញាណប័ណ្ណសញ្ជាតិខ្មែរលេខៈ 190228973 ទូរសព្ទ័លេខ 012 333 901 ប័ណ្ណសម្គាល់ជើងសាគយលេខ #699B ផុតសុពលភាពថ្ងៃទី 31 ខែ ធ្នូ ឆ្នាំ 2026 ។ | O4: DHONNA JIA CHENG IMP EXP CO., LTD. | P4: #255,ST.351,PHUM TA NGOV KROM,SANGKAT NIROTH, KHAN CHBAR AMPOV,PHNOM PENH, CAMBODIA VAT No : K007-901903553 | Q4: #255,ST.351,PHUM TA NGOV KROM,SANGKAT NIROTH, KHAN CHBAR AMPOV,PHNOM PENH, CAMBODIA VAT No : K007-901903553 | R4: DOUNG | S4: ហ៊ាន សហមុន្នី | T4: 70296574 | U4: ZENITH MACHINERY LEASING CO.,LTD | V4: K009-902005913 | W4: 070 673 598 | X4: WICHAI ON-SRI | Y4: AD0667637 | Z4: 089 890 324 | AB4: 45659 | AC4: ថ្ងៃព្រហស្បតិ៍ ៤កើត ខែបុស្ស ឆ្នាំរោង ឆស័ក ព.ស.២៥៦៨ | AD4: ថ្ងៃអង្គារ | AE4: ៦ រោច | AF4: ខែមិគសិរ | AG4: ឆ្នាំថោះ | AH4: បញ្ចស័ក ពស. ២៥៦៧ | AK4: 2 | AL4: បុស្ស | AM4: កុម្ភៈ | AN4: ទោស័ក | AP4: 1
A5: PNH02 | B5: សាខាគយ និងរដ្ឋាករកំពង់ផែអន្តរជាតិភ្នំពេញ | C5: SSK | D5: SIN SOKEN (ស៊ិន សុខកេន) ដែលមានអាសយដ្ឋានឃ្លាំងលេខ ៥៩៧ ផ្លូវមុន្នីវង្ស សង្កាត់បឹងព្រលឹត ខណ្ឌ៧មករា រាជធានីភ្នំពេញ ។ | F5: DON THONGPRAPAI | G5: កាន់លិខិតឆ្លងដែនលេខ: AB4555337 ទូរសព្ទ័លេខ 095 777 975 ជាប្រធានក្រុមហ៊ុន SUVANNAPHUM INVESTMENT CO., LTD អត្តសញ្ញាណកម្មសារពើពន្ធ (VAT) លេខៈ L001-901801901 ជានីតិបុគ្គលជើងសារគយដែលមានរូបវន្តបុគ្គលជើងសាគយតំណាងលោក/លោកស្រី ផេង សុវណ្ណា អត្តសញ្ញាណប័ណ្ណសញ្ជាតិខ្មែរលេខៈ 190228973 ទូរសព្ទ័លេខ 012 333 901 ប័ណ្ណសម្គាល់ជើងសាគយលេខ #699B ផុតសុពលភាពថ្ងៃទី 31 ខែ ធ្នូ ឆ្នាំ 2026 ។ | H5: HUAN YA HE ZHONG (CAMBODIA) TRADING CO., LTD | I5: MO GUANKANG | J5: SIBW | K5: បញ្ចេញទំនិញនៅមាត់ច្រកភណ្ឌាគារគយមានដែនកំណត់សុវណ្ណភូមិ | M5: BOONNAM KULRAKAMPUSIRI | N5: កាន់លិខិតឆ្លងដែនលេខ: AC2134008 ទូរសព្ទ័លេខ 069 777 815 ជាប្រធានក្រុមហ៊ុន SUVANNAPHUM INVESTMENT CO., LTD អត្តសញ្ញាណកម្មសារពើពន្ធ (VAT) លេខៈ L001-901801901 ជានីតិបុគ្គលជើងសារគយដែលមានរូបវន្តបុគ្គលជើងសាគយតំណាងលោក/លោកស្រី ផេង សុវណ្ណា អត្តសញ្ញាណប័ណ្ណសញ្ជាតិខ្មែរលេខៈ 190228973 ទូរសព្ទ័លេខ 012 333 901 ប័ណ្ណសម្គាល់ជើងសាគយលេខ #699B ផុតសុពលភាពថ្ងៃទី 31 ខែ ធ្នូ ឆ្នាំ 2026 ។ | O5: SREY CHINDA IMPORT EXPORT CO., LTD | P5: #23N, St.2007, SANGKAT KAKAB, KHAN PORSENCHEY, PHNOM PENH, CAMBODIA. VAT No : K010-901902352 | Q5: #23N, St.2007, SANGKAT KAKAB, KHAN PORSENCHEY, PHNOM PENH, CAMBODIA. VAT No : K010-901902352 | R5: PHNOM PENH | S5: ZHU SHUAI | T5: E24411836 | U5: MINGYANG GUOJI TRADING CO.,LTD | V5: L001-902001625 | W5: 018 9159555 | X5: BOONNAM KULRAKAMPUSIRI | Y5: AC2134008 | Z5: 069 777 815 | AB5: 45660 | AC5: ថ្ងៃសុក្រ ៥កើត ខែបុស្ស ឆ្នាំរោង ឆស័ក ព.ស.២៥៦៨ | AD5: ថ្ងៃពុធ | AE5: ៧ រោច | AF5: ខែមិគសិរ | AG5: ឆ្នាំថោះ | AH5: បញ្ចស័ក ពស. ២៥៦៧ | AK5: 3 | AL5: មាឃ | AM5: មីនា | AN5: ត្រីស័ក
A6: SHV11 | B6: សាខាគយ និងរដ្ឋាករកំពង់ផែអន្តរជាតិក្រុងព្រះសីហនុ | C6: V99 | D6: V99 PLATINUM AUTO ដែលមានអាសយដ្ឋានឃ្លាំងលេខ 31-32 ផ្លូវ114 សង្កាត់មនោរម្យ ខណ្ឌ៧មករា រាជធានីភ្នំពេញ​ | E6: https://goo.gl/maps/gSiPqu5BXT1h24HJ6 | F6: MO GUANKANG | G6: ភេទប្រុស ដែលមានលិខិតឆ្លងដែនលេខៈ EG7009964 ជាប្រធានក្រុមហ៊ុន HUAN YA HE ZHONG (CAMBODIA) TRADING CO., LTD អត្តសញ្ញាណកម្មសារពើពន្ធ (VAT)លេខៈ L001-901908165 ទូរសព្ទ័លេខៈ 017 555924 | H6: N/A | I6: MA YUANQIANG | J6: SIDP | K6: បញ្ចេញទំនិញនៅមាត់ច្រកផែស្ងួតសុវណ្ណភូមិ | M6: WONGMONGKOL SRESTTAWIN | N6: កាន់លិខិតឆ្លងដែនលេខ: AC5014016 ទូរសព្ទ័លេខ 093 544 566 ជាប្រធានក្រុមហ៊ុន SUVANNAPHUM INVESTMENT CO., LTD អត្តសញ្ញាណកម្មសារពើពន្ធ (VAT) លេខៈ L001-901801901 ជានីតិបុគ្គលជើងសារគយដែលមានរូបវន្តបុគ្គលជើងសាគយតំណាងលោក/លោកស្រី ផេង សុវណ្ណា អត្តសញ្ញាណប័ណ្ណសញ្ជាតិខ្មែរលេខៈ 190228973 ទូរសព្ទ័លេខ 012 333 901 ប័ណ្ណសម្គាល់ជើងសាគយលេខ #699B ផុតសុពលភាពថ្ងៃទី 31 ខែ ធ្នូ ឆ្នាំ 2026 ។ | O6: DOUNG PUM AGRI IMPORT & EXPORT CO,.LTD | P6: អាស័យដ្ឋាន#1FEo​ ផ្លូវ ៩៣ ភូមិ ផ្សារតូច សង្កាត់ ទួលសង្កែទី១ ខណ្ឌ ឫស្សីកែវ រាជធានីភ្នំពេញ VAT No : K008-902005660 | Q6: អាស័យដ្ឋាន#1FEo​ ផ្លូវ ៩៣ ភូមិ ផ្សារតូច សង្កាត់ ទួលសង្កែទី១ ខណ្ឌ ឫស្សីកែវ រាជធានីភ្នំពេញ VAT No : K008-902005660 | R6: SIHANOUKVILLE | S6: ទ្រី ស៊ាងហេង | T6: 250012059 | U6: TRY SEANGHENG TRADING CO., LTD | V6: B124-902102170 | W6: 096 9266789 | X6: WONGMONGKOL SRESTTAWIN | Y6: AC5014016 | Z6: 093 544 566 | AB6: 45661 | AC6: ថ្ងៃសៅរ៍ ៦កើត ខែបុស្ស ឆ្នាំរោង ឆស័ក ព.ស.២៥៦៨ | AD6: ថ្ងៃព្រហស្បតិ៍ | AE6: ៨ រោច | AF6: ខែមិគសិរ | AG6: ឆ្នាំថោះ | AH6: បញ្ចស័ក ពស. ២៥៦៧ | AK6: 4 | AL6: ផល្គុន | AM6: មេសា | AN6: ចត្វាស័ក
A7: BAV01 | B7: សាខាគយ​ និងរដ្ឋាករស្វាយរៀង ការិយាល័យគយ និងរដ្ឋាករបាវិត | C7: BYD | D7: ឈ្មោះ BYD Sale & Service Center ដែលមានអាស័យដ្ឋាន#52 ផ្លូវជាតិលេខ 6A ភូមិដើមគរ សង្កាត់ជ្រោយចង្វារ ខណ្ឌជ្រោយចង្វារ រាជធានីភ្នំពេញ ជាទីតាំងបង្ហាញរថយន្ត (Showroom) របស់ក្រុមហ៊ុន HUAN YA HE ZHONG (CAMBODIA) TRADING CO., LTD | E7: https://www.google.com/maps/place/BYD+Cambodia/@11.592152,104.9271733,17z/data=!3m1!4b1!4m5!3m4!1s0x310953d2e3fa102f:0x97e2f0815633bd99!8m2!3d11.592152!4d104.929362 | F7: MA YUANQIANG | H7: N/A | I7: TANG XIUNING | J7: SISEZ | K7: បញ្ចេញទំនិញនៅតំបន់សេដ្ឋកិច្ចពិសេសសុវណ្ណភូមិ | O7: JI SHUN DA TRADING CO., LTD | P7: #B75, ST.B, PHUM KBAL DAMREY I, SANGKAT KAKAB I, KHAN PORSENCHEY, PHNOM PENH, CAMBODIA VAT : K010-901908667 | Q7: #B75, ST.B, PHUM KBAL DAMREY I, SANGKAT KAKAB I, KHAN PORSENCHEY, PHNOM PENH, CAMBODIA VAT : K010-901908667 | R7: BAVET | S7: BOONNAM KULRAKAMPUSIRI | T7: AC2134008 | U7: BJC CELLOX(CAMBODIA) CO., LTD | V7: L001-901639149 | W7: 069 777 815 | AB7: 45662 | AC7: ថ្ងៃអាទិត្យ ៧កើត ខែបុស្ស ឆ្នាំរោង ឆស័ក ព.ស.២៥៦៨ | AD7: ថ្ងៃសុក្រ | AE7: ៩ រោច | AF7: ខែមិគសិរ | AG7: ឆ្នាំថោះ | AH7: បញ្ចស័ក ពស. ២៥៦៧ | AK7: 5 | AL7: ចេត្រ | AM7: ឧសភា | AN7: ឆស័ក
A8: AIR01 | B8: សាខាគយ និងរដ្ឋាករអាកាសយាន្ដដ្ឋានអន្តរជាតិភ្នំពេញ | C8: RATANNAK | D8: រតនៈ ឡាក់សិរី ខា ត្រេដ័រ (RATANAK LUXURY CAR TRADER) ដែលមានអាស័យដ្ឋានផ្ទះលេខ #639KR ផ្លូវ 93 មហាវិថីព្រះមុន្នីវង្ស ភូមិ 7 សង្កាត់បឹងកេងកងទី 3 ខណ្ឌចំការមន រាជធានីភ្នំពេញ ។ | E8: https://goo.gl/maps/bnuc2F89m9JhgRMW7 | F8: LIAO KAILING | G8: ភេទប្រុស ដែលមានលិខិតឆ្លងដែនលេខៈ EG2412090 ជាប្រធានក្រុមហ៊ុន ONEROAD INDUSTRIAL (CAMBODIA) CO.,LTD អត្តសញ្ញាណកម្មសារពើពន្ធ (VAT)លេខៈ K002-902101770 | H8: ONEROAD INDUSTRIAL (CAMBODIA) CO.,LTD | I8: LIAO KAILING | J8: PNH01 | K8: បញ្ចេញទំនិញនៅមាត់ច្រកអាកាសយាន្តដ្ឋានអន្តរជាតិភ្នំពេញ | O8: HUAN YA HE ZHONG (CAMBODIA) TRADING CO., LTD | P8: 52 NATIONAL ROAD NO 6A RUSSEY KEO PHNOM PENH Contact Person: Marco Mok VAT: L001-901908165 ,Tel: +853 2882 2822 | Q8: 52 NATIONAL ROAD NO 6A RUSSEY KEO PHNOM PENH Contact Person: Marco Mok VAT: L001-901908165 ,Tel: +853 2882 2822 | R8: PHNOM PENH AIRPORT | S8: WICHAI ON-SRI | T8: AD0667637 | U8: BJC CELLOX(CAMBODIA) CO., LTD | V8: L001-901639149 | W8: 089 890 324 | AB8: 45663 | AC8: ថ្ងៃចន្ទ ៨កើត ខែបុស្ស ឆ្នាំរោង ឆស័ក ព.ស.២៥៦៨ | AD8: ថ្ងៃសៅរ៍ | AE8: ១០ រោច | AF8: ខែមិគសិរ | AG8: ឆ្នាំថោះ | AH8: បញ្ចស័ក ពស. ២៥៦៧ | AK8: 6 | AL8: ពិសាខ | AM8: មិថុនា | AN8: អដ្ឋស័ក
A9: BMC11 | B9: ការិយាល័យគយ និងរដ្ឋាករមាត់ច្រកអន្តរជាតិប៉ោយប៉ែត | C9: ORG | D9: ONE ROAD GROUP ​ដែលមានអាស័យដ្ឋាន No.288K,Street 598,Sangkat Toul Sangke 2,Khan Reusey Keo,Phnom Penh, Cambodia។ | E9: https://maps.google.com/maps?q=11.604460,104.898928&ll=11.604460,104.898928&z=16 | F9: ZHANG HUA | G9: ភេទប្រុស ដែលមានលិខិតឆ្លងដែនលេខៈ E37888060 ជាប្រធានក្រុមហ៊ុន H U A Y (CAMBODIA) INTERNATIONAL AUTO TRADE CO., LTD អត្តសញ្ញាណកម្មសារពើពន្ធ (VAT)លេខៈ L001-901909613 ទូរសព្ទ័លេខៈ +855 098881618​ | H9: H U A Y (CAMBODIA) INTERNATIONAL AUTO TRADE CO., LTD | I9: ZHANG HUA | J9: PNH19 | K9: បញ្ចេញទំនិញនៅមាត់ច្រកផែស្ងួតតិចស្រ៊ុន | O9: SAN FENG JIAN ZHU CO.,LTD. | P9: #C២៧ បុរីអាការសចរណ៍ ផ្លូវ ភូមិក្បាលដំរី១ សង្កាត់កាកាបទី១ ខណ្ឌពោធិ៍សែនជ័យ រាជធានីភ្នំពេញ ​Vat No : K010-902000030 | Q9: #C២៧ បុរីអាការសចរណ៍ ផ្លូវ ភូមិក្បាលដំរី១ សង្កាត់កាកាបទី១ ខណ្ឌពោធិ៍សែនជ័យ រាជធានីភ្នំពេញ ​Vat No : K010-902000030 | R9: TEC SRUN DRYPORT | S9: លាង សុភា | T9: 0107001600(01) | U9: TF MOTORS (CAMBODIA) CO., LTD | V9: L001-104008598 | W9: 088 8772 209 | AB9: 45664 | AC9: ថ្ងៃអង្គារ ៩កើត ខែបុស្ស ឆ្នាំរោង ឆស័ក ព.ស.២៥៦៨ | AD9: ថ្ងៃអាទិត្យ | AE9: ១១ រោច | AF9: ខែមិគសិរ | AG9: ឆ្នាំថោះ | AH9: បញ្ចស័ក ពស. ២៥៦៧ | AK9: 7 | AL9: ជេស្ឋ | AM9: កក្កដា | AN9: នព្វស័ក
A10: PVG15 | B10: ការិយាល័យគយ និងរដ្ឋាករមាត់ច្រកអន្តរជាតិម៉ឺនជ័យ | C10: MYGT | D10: ឈ្មោះ មីងយ៉ាងគួជីត្រេឌីង ឯ.ក ដែលមានទីតាំងអាគារ 174K សង្កាត់ទួលសង្កែ ខណ្ឌប្ញស្សីកែវ រាជធានីភ្នំពេញ របស់ក្រុមហ៊ុន MINGYANG GUOJI TRADING CO., LTD។ | E10: https://goo.gl/maps/GsWi5kemXdEiPexB8 | F10: ពឹង បូរិន | G10: ភេទប្រុស ដែលមានលិខិតឆ្លងដែនលេខៈ 011248801 ជាប្រធានក្រុមហ៊ុន RECOVERY COLLECTION CONSULTANT CO.,LTD.​ អត្តសញ្ញាណកម្មសារពើពន្ធ (VAT)លេខៈ K009-901902489 ទូរសព្ទ័លេខៈ +85595 242 721 | H10: RECOVERY COLLECTION CONSULTANT CO.,LTD | I10: ពឹង បូរិន | O10: ONEROAD INDUSTRIAL (CAMBODIA) CO.,LTD | P10: #N-៤០ ផ្លូវNewton Koh Pich, Mulberry Park ភូមិ ៤ សង្កាត់ ទន្លេបាសាក់ ខណ្ឌ ចំការមន រាជធានីភ្នំពេញ VAT No : K002-902101770 | Q10: #N-៤០ ផ្លូវNewton Koh Pich, Mulberry Park ភូមិ ៤ សង្កាត់ ទន្លេបាសាក់ ខណ្ឌ ចំការមន រាជធានីភ្នំពេញ VAT No : K002-902101770 | S10: ZHOU YOUYUAN | T10: EJ6181097 | U10: XST AUTO (CAMBODIA) INTERNATIONAL TRADE CO.,LTD | V10: L001-902101200 | W10: 0967100000 | AB10: 45665 | AC10: ថ្ងៃពុធ ១០កើត ខែបុស្ស ឆ្នាំរោង ឆស័ក ព.ស.២៥៦៨ | AD10: ថ្ងៃចន្ទ | AE10: ១២ រោច | AF10: ខែមិគសិរ | AG10: ឆ្នាំថោះ | AH10: បញ្ចស័ក ពស. ២៥៦៧ | AK10: 8 | AL10: អាសាធ | AM10: សីហា | AN10: សំរឹទ្វិស័ក
A11: PNH01 | B11: សាខាគយ និងរដ្ឋាករ អាកាសយាន្តដ្ឋានអន្តរជាតិ | C11: SOUEAST | D11: SOUEAST (សោតអៀសអូតូខា) ដែលមានអាស័យដ្ឋាន No.21-23 street 214,Phnum 2,Sangkat Boeng Rang,Khan Daun Penh,Phnom Penh,Cambodia។ | E11: https://goo.gl/maps/2NmY7hFBS2k9oh8Y7 | F11: សុន ដារ៉ា | G11: ភេទប្រុស ដែលមានលិខិតឆ្លងដែនលេខៈ 061527309 ជាប្រធានក្រុមហ៊ុន SON DARA IMEX CO.,LTD. អត្តសញ្ញាណកម្មសារពើពន្ធ (VAT)លេខៈ K006-902005865 ទូរសព្ទ័លេខៈ +85592 731118 | H11: SON DARA IMEX CO.,LTD | I11: សុន ដារ៉ា | O11: MINGYANG GUOJI TRADING CO.,LTD | P11: 174K STREET 105 SANGKAT TUAL SANGKAT KHAN RUSSET KEO PHOM PENH,THE KINGDOM OF CAMBODIA TEL:+855 0189159555 | Q11: 174K STREET 105 SANGKAT TUAL SANGKAT KHAN RUSSET KEO PHOM PENH,THE KINGDOM OF CAMBODIA TEL:+855 0189159555 | S11: ង៉ូវ ចាន់រស្មី | T11: 061434557 | U11: TF MOTORS (CAMBODIA) CO., LTD | V11: L001-104008598 | W11: 088 8772209 | AB11: 45666 | AC11: ថ្ងៃព្រហស្បតិ៍ ១១កើត ខែបុស្ស ឆ្នាំរោង ឆស័ក ព.ស.២៥៦៨ | AD11: ថ្ងៃអង្គារ | AE11: ១៣ រោច | AF11: ខែមិគសិរ | AG11: ឆ្នាំថោះ | AH11: បញ្ចស័ក ពស. ២៥៦៧ | AK11: 9 | AL11: ស្រាពណ៍ | AM11: កញ្ញា
A12: PNH19 | B12: ការិយាល័យគយនិងរដ្ឋាករផែស្ងួត តិច ស្រ៊ុន | C12: UMG | D12: ឈ្មោះ យូណាយធីត មើឃ្យូរី គ្រុប ដែលមានទីតាំង No.287 ផ្លូវជាតិលេខ3 សង្កាត់ចោមចៅ1 ខណ្ឌពោធិ៍សែនជ័យ រាជធានីភ្នំពេញ របស់ក្រុមហ៊ុន UNITED MERCURY GROUP CO., LTD។ | E12: https://goo.gl/maps/SqAr2vWr8cFYvyLK6 | F12: WICHAI ON-SRI | G12: ភេទប្រុស ដែលមានលិខិតឆ្លងដែនលេខៈ AD0667637 ជំនួសប្រធានចាត់ការទូទៅក្រុមហ៊ុន SUVANNAPHUM INVESTMENT CO., LTD អត្តសញ្ញាណកម្មសារពើពន្ធ (VAT)លេខៈ L001-901801901 ទូរសព្ទ័លេខៈ 089 890 324 | H12: NAL SRUN 62 IMPORT EXPORT CO.,LTD. | I12: ស៊្រុន ណាល់ | O12: H U A Y (CAMBODIA) INTERNATIONAL AUTO TRADE CO., LTD | P12: អាស័យដ្ឋាន:# ៤៥ ផ្លូវសហព័ន្ធរុស្ស៊ី សង្កាត់ថ្លា ខណ្ឌសែនសុខ រាជធានីភ្នំពេញ ទូរស័ព្ទលេខ : +855 098881618​ ។ | Q12: អាស័យដ្ឋាន:# ៤៥ ផ្លូវសហព័ន្ធរុស្ស៊ី សង្កាត់ថ្លា ខណ្ឌសែនសុខ រាជធានីភ្នំពេញ ទូរស័ព្ទលេខ : +855 098881618​ ។ | S12: ZHANG HUA | T12: E37888060 | U12: A N D Y (CAMBODIA) INTERNATIONAL AUTO TRADE CO.,LTD | V12: L001-902104222 | W12: 098881618​ | AB12: 45667 | AC12: ថ្ងៃសុក្រ ១២កើត ខែបុស្ស ឆ្នាំរោង ឆស័ក ព.ស.២៥៦៨ | AD12: ថ្ងៃពុធ | AE12: ១៤ រោច | AF12: ខែមិគសិរ | AG12: ឆ្នាំថោះ | AH12: បញ្ចស័ក ពស. ២៥៦៧ | AK12: 10 | AL12: ភទ្របទ | AM12: តុលា
C13: FAW | D13: ឈ្មោះ FAW ដែលមានអាស័យដ្ឋាន: No.98 Street 110 , Toek Lok 1 Commune , Toul Kork District , Phnom Penh ទីតាំងបង្ហាញរថយន្ត (Showroom) របស់ក្រុមហ៊ុន VICTOR MOTOR CO.,LTD។ | E13: https://goo.gl/maps/ZEhCkybUEZNWhaRu9 | F13: ស៊្រុន ណាល់ | H13: TRY SEANGHENG TRADING CO.,LTD | I13: ទ្រី ស៊ាងហេង | O13: SON DARA IMEX CO.,LTD. | P13: #បុរីពិភពថ្មីចំការដូង ផ្ទះលេខ 95A ផ្លូវ 19 ភូមិប្រការ សង្កាត់ព្រៃស ខណ្ឌដង្កោ រាជធានីភ្នំពេញ Vat No : K006-902005865 | Q13: #បុរីពិភពថ្មីចំការដូង ផ្ទះលេខ 95A ផ្លូវ 19 ភូមិប្រការ សង្កាត់ព្រៃស ខណ្ឌដង្កោ រាជធានីភ្នំពេញ Vat No : K006-902005865 | S13: ហម គឹមឡេង | T13: 160322461 | U13: MAHA SOK APHIVATH TRADING CO.,LTD | V13: K006-902102027 | W13: 0974121521 | AB13: 45668 | AC13: ថ្ងៃសៅរ៍ ១៣កើត ខែបុស្ស ឆ្នាំរោង ឆស័ក ព.ស.២៥៦៨ | AD13: ថ្ងៃព្រហស្បតិ៍ | AE13: ១ កើត | AF13: ខែបុស្ស | AG13: ឆ្នាំថោះ | AH13: បញ្ចស័ក ពស. ២៥៦៧ | AK13: 11 | AL13: អស្សុជ | AM13: វិច្ឆិកា
C14: SODO HUAY | D14: ឈ្មោះ SOUEAST DONGFENG ដែលមានទីតាំងផ្ទះលេខ1076 ផ្លូវ2004 ភូមិទឹកថ្លា សង្កាត់ទឹកថ្លា ខណ្ឌសែនសុខ រាជធានីភ្នំពេញ ទីតាំងបង្ហាញរថយន្ត (Showroom) របស់ក្រុមហ៊ុន HUAY (CAMBODIA) INTERNATIONAL AUTO TRADE CO., LTD។ | E14: https://goo.gl/maps/ouoZkPz82XjHmWDGA | F14: ទ្រី ស៊ាងហេង | G14: ភេទប្រុស មានអត្តសញ្ញាណប័ណ្ណសញ្ជាតិខ្មែរលេខៈ 250012059 ជាប្រធានក្រុមហ៊ុន TRY SEANGHENG TRADING CO., LTD. អត្តសញ្ញាណកម្មសារពើពន្ធ (VAT)លេខៈ B124-902102170 ទូរសព្ទ័លេខៈ 0969266789 | H14: MILLION FARM AGRICULTURE CO.,LTD | I14: តាំង ហុង | O14: EVERSAILING SUPPLY CHAIN (CAMBODIA) CO.,LTD | P14: #១០G ផ្លូវ ២៣០ ភូមិ ៨ សង្កាត់ បឹងសាឡាង ខណ្ឌ ទួលគោក រាជធានីភ្នំពេញ Vat No : K005-902101776 | Q14: #១០G ផ្លូវ ២៣០ ភូមិ ៨ សង្កាត់ បឹងសាឡាង ខណ្ឌ ទួលគោក រាជធានីភ្នំពេញ Vat No : K005-902101776 | S14: MO GUANKANG | T14: EG7009964 | U14: HUAN YA HE ZHONG (CAMBODIA) TRADING CO., LTD | V14: L001-901908165 | W14: 017 555924 | AB14: 45669 | AC14: ថ្ងៃអាទិត្យ ១៤កើត ខែបុស្ស ឆ្នាំរោង ឆស័ក ព.ស.២៥៦៨ | AD14: ថ្ងៃសុក្រ | AE14: ២ កើត | AF14: ខែបុស្ស | AG14: ឆ្នាំថោះ | AH14: បញ្ចស័ក ពស. ២៥៦៧ | AK14: 12 | AL14: កត្តិក | AM14: ធ្នូ
C15: JMC AUTO | D15: ឈ្មោះ JMC AUTO ដែលមានអាស័យដ្ឋានផ្ទះលេខ #521, ផ្លូវជាតិលេខ 6A, ភូមិគៀនឃ្លាំង សង្កាត់ជ្រោយចង្វារ ខណ្ឌជ្រោយជង្វារ រាជធានីភ្នំពេញ ជាទីតាំងបង្ហាញរថយន្ត (Showroom) របស់ក្រុមហ៊ុន XST AUTO (CAMBODIA) INTERNATIONAL TRADE CO., LTD។ | E15: https://goo.gl/maps/AVkupG886tzbLokn9 | F15: តាំង ហុង | H15: XST AUTO (CAMBODIA) INTERNATIONAL TRADE CO.,LTD | I15: ZHOU YOUYUAN | O15: RECOVERY COLLECTION CONSULTANT CO.,LTD. | P15: ទីតាំងនៅផ្ទះ #C២៩ ផ្លូវ Maha-C ក្នុងបុរី មហាសែនសុខ ភូមិវិមានទ្រង់ សង្កាត់ក្រាំងធ្នង់ ខណ្ឌសែនសុខ រាជធានីភ្នំពេញ VAT: K009-901902489 | Q15: ទីតាំងនៅផ្ទះ #C២៩ ផ្លូវ Maha-C ក្នុងបុរី មហាសែនសុខ ភូមិវិមានទ្រង់ សង្កាត់ក្រាំងធ្នង់ ខណ្ឌសែនសុខ រាជធានីភ្នំពេញ VAT: K009-901902489 | S15: LI XINHUA | T15: E16409716 | U15: YUEKA ONE-STOP AUTO SERVICE CO. LTD | V15: L001-901804963 | W15: 078 890 777 | AB15: 45670 | AC15: ថ្ងៃចន្ទ ១៥កើត ខែបុស្ស ឆ្នាំរោង ឆស័ក ព.ស.២៥៦៨ | AD15: ថ្ងៃសៅរ៍ | AE15: ៣ កើត | AF15: ខែបុស្ស | AG15: ឆ្នាំថោះ | AH15: បញ្ចស័ក ពស. ២៥៦៧
C16: MUMG | D16: MATADOR UMG CAMBODIA ដែលមានអាស័យដ្ឋាន ស្ទឹងព្រែកត្នោត, ផ្លូវជាតិលេខ 4, ភូមិស្ទឹង ឃុំត្រពាំងគង ស្រុកសំរោងទង ខេត្តកំពង់ស្ពឺ។ | E16: https://goo.gl/maps/bnuc2F89m9JhgRMW7 | F16: ធន់ មករា | H16: FIR PLANNED CO.,LTD | I16: ខាន់ លីណា | O16: NAL SRUN 62 IMPORT EXPORT CO.,LTD. | P16: #២៣ ផ្លូវ២០ សង្កាត់ស្ទឹងមានជ័យទី៣ ខណ្ឌមានជ័យ រាជធានីភ្នំពេញ VAT: K007-9020022874 | Q16: #២៣ ផ្លូវ២០ សង្កាត់ស្ទឹងមានជ័យទី៣ ខណ្ឌមានជ័យ រាជធានីភ្នំពេញ VAT: K007-9020022874 | S16: គង់​ គិនណារី | T16: 010852466 | U16: AUTOMOTIVE ASIA (CAMBODIA) LIMITED | V16: L001-107030985 | W16: 023 222 204 | AB16: 45671 | AC16: ថ្ងៃអង្គារ ១រោច ខែបុស្ស ឆ្នាំរោង ឆស័ក ព.ស.២៥៦៨ | AD16: ថ្ងៃអាទិត្យ | AE16: ៤ កើត | AF16: ខែបុស្ស | AG16: ឆ្នាំថោះ | AH16: បញ្ចស័ក ពស. ២៥៦៧ | AK16: ១ រោច | AL16: ១ កើត
C17: FT | D17: ឈ្មោះ FORTHING ដែលមានទីតាំង #166 ផ្លូវជាតិលេខ 6 ភូមិគៀនឃ្លាំង សង្កាត់ជ្រោយចង្វារ ខណ្ឌជ្រោយចង្វារ រាជធានីភ្នំពេញ ជាទីតាំងបង្ហាញរថយន្ត (Showroom) របស់ក្រុមហ៊ុន YUEKA ONE-STOP AUTO SERVICE CO. LTD ទូរស័ព្ទលេខ: 087 866 762 ។ | E17: https://maps.app.goo.gl/WwG1EZtfFrMAoght5 | F17: ZHOU YOUYUAN | G17: ភេទប្រុស ដែលមានលិខិតឆ្លងដែនលេខៈ EJ6181097 ជាប្រធានក្រុមហ៊ុន XST AUTO (CAMBODIA) INTERNATIONAL TRADE CO.,LTD អត្តសញ្ញាណកម្មសារពើពន្ធ (VAT)លេខៈ L001-902101200 ទូរសព្ទ័លេខៈ 0967100000 | H17: UNITED MERCURY GROUP CO.,LTD | I17: ALFRED KASUMA ALIWARGA | O17: TRY SEANGHENG TRADING CO.,LTD | P17: ភូមិ ជើងឡង ឃុំ សួង ស្រុក សួង ខេត្ត ត្បូងឃ្មុំ VAT: B124-902102170 | Q17: ភូមិ ជើងឡង ឃុំ សួង ស្រុក សួង ខេត្ត ត្បូងឃ្មុំ VAT: B124-902102170 | S17: ស៊្រុន ណាល់ | T17: 061815277 | U17: NAL SRUN 62 IMPORT EXPORT CO.,LTD | V17: K007-902002874 | AB17: 45672 | AC17: ថ្ងៃពុធ ២រោច ខែបុស្ស ឆ្នាំរោង ឆស័ក ព.ស.២៥៦៨ | AD17: ថ្ងៃចន្ទ | AE17: ៥ កើត | AF17: ខែបុស្ស | AG17: ឆ្នាំថោះ | AH17: បញ្ចស័ក ពស. ២៥៦៧ | AK17: ២ រោច | AL17: ២ កើត
C18: MAX | D18: MAXUS ដែលមានអាសយដ្ឋាន #អគារ ១៧៤-១៧៥ (ប្លុក ១C, ១D និង ២C, ២D) នៃកាលីហ្វ័រញ៉ា សូសលហៅស៍ ផ្លូវ សហព័ន្ធរុស្ស៊ី សង្កាត់ទឹកថ្លា ខណ្ឌសែនសុខ រាជធានីភ្នំពេញ ជាទីតាំងបង្ហាញ (SHOWROOM)របស់ក្រុមហ៊ុន TF MOTORS (CAMBODIA) CO., LTD។ | E18: https://goo.gl/maps/WuC6bokrk32WsiPf6 | F18: ខាន់ លីណា | H18: MINGYANG GUOJI TRADING CO.,LTD | I18: ZHU SHUAI | O18: MILLION FARM AGRICULTURE CO.,LTD | P18: #Q២១ ជាន់ទី៣ ផ្លូវ Q ភូមិ ១៤ សង្កាត់ ទន្លេបាសាក់ ខណ្ឌ ចំការមន រាជធានីភ្នំពេញ VAT: K002-902102193 | Q18: #Q២១ ជាន់ទី៣ ផ្លូវ Q ភូមិ ១៤ សង្កាត់ ទន្លេបាសាក់ ខណ្ឌ ចំការមន រាជធានីភ្នំពេញ VAT: K002-902102193 | S18: YU YIXIANG | T18: EA3791641 | U18: VICTOR MOTOR CO.,LTD | V18: K005-901906510 | W18: 0968456666 | AB18: 45673 | AC18: ថ្ងៃព្រហស្បតិ៍ ៣រោច ខែបុស្ស ឆ្នាំរោង ឆស័ក ព.ស.២៥៦៨ | AD18: ថ្ងៃអង្គារ | AE18: ៦ កើត | AF18: ខែបុស្ស | AG18: ឆ្នាំថោះ | AH18: បញ្ចស័ក ពស. ២៥៦៧ | AK18: ៣ រោច | AL18: ៣ កើត
C19: SODO ANDY | D19: ឈ្មោះ SOUEAST DONGFENG ដែលមានទីតាំងផ្ទះលេខ1076 ផ្លូវ2004 ភូមិទឹកថ្លា សង្កាត់ទឹកថ្លា ខណ្ឌសែនសុខ រាជធានីភ្នំពេញ ទីតាំងបង្ហាញរថយន្ត (Showroom) របស់ក្រុមហ៊ុន A N D Y (CAMBODIA) INTERNATIONAL AUTO TRADE CO., LTD។ | E19: https://goo.gl/maps/ouoZkPz82XjHmWDGA | F19: ALFRED KASUMA ALIWARGA | G19: ភេទប្រុស ដែលមានលិខិតឆ្លងដែនលេខៈ C7615365 ជាប្រធានក្រុមហ៊ុន UNITED MERCURY GROUP CO.,LTD អត្តសញ្ញាណកម្មសារពើពន្ធ (VAT)លេខៈ L001-108001873 ទូរសព្ទ័លេខៈ 070 873235 | H19: SCD | I19: SREY CHINDA | O19: XST AUTO (CAMBODIA) INTERNATIONAL TRADE CO.,LTD | P19: #វិញ្ញាបនបត្រសម្គាល់ម្ចាស់អចលនវត្ថុលេខ ១២០៨០១០៤-០៥៥៨ ផ្លូវ ភូមិបាយ៉ាប សង្កាត់ភ្នំពេញថ្មី ខណ្ឌសែនសុខ រាជធានីភ្នំពេញ។ VAT: L001-902101200 | Q19: #វិញ្ញាបនបត្រសម្គាល់ម្ចាស់អចលនវត្ថុលេខ ១២០៨០១០៤-០៥៥៨ ផ្លូវ ភូមិបាយ៉ាប សង្កាត់ភ្នំពេញថ្មី ខណ្ឌសែនសុខ រាជធានីភ្នំពេញ។ VAT: L001-902101200 | S19: SAY SREYMOM | T19: 110597540 | U19: SAY SREYMOM IMPORT & EXPORT CO.,LTD | V19: K006-902106071 | W19: 011 303 425 | AB19: 45674 | AC19: ថ្ងៃសុក្រ ៤រោច ខែបុស្ស ឆ្នាំរោង ឆស័ក ព.ស.២៥៦៨ | AD19: ថ្ងៃពុធ | AE19: ៧ កើត | AF19: ខែបុស្ស | AG19: ឆ្នាំថោះ | AH19: បញ្ចស័ក ពស. ២៥៦៧ | AK19: ៤ រោច | AL19: ៤ កើត
C20: ATMT | D20: ឈ្មោះ Audi Phnom Penh ដែលមានអាសយដ្ឋាន#15Z ផ្លូវព្រះមុនីវង្ស កែងផ្លូវ 422 សង្កាត់ទន្លេបាសាក់ ខណ្ឌចំការមន រាជធានីភ្នំពេញ ទីតាំងបង្ហាញរថយន្ត (Showroom) របស់ក្រុមហ៊ុន AUTOMOTIVE ASIA (CAMBODIA) LIMITED។ | E20: https://maps.app.goo.gl/WDK2AHt4NY2gJxNs8 | F20: ZHU SHUAI | G20: ភេទស្រី ដែលមានលិខិតឆ្លងដែនលេខៈ E24411836 ជាប្រធានក្រុមហ៊ុន MINGYANG GUOJI TRADING CO., LTD អត្តសញ្ញាណកម្មសារពើពន្ធ (VAT)លេខៈ L001-1901801901​ | H20: TF MOTORS (CAMBODIA) CO., LTD | I20: ហូម៉េន សេនតូនី តាន់ឌីហ្សូណូ | O20: FIR PLANNED CO.,LTD | P20: ភូមិ អង្គសុគន្ធា ឃុំ មហាឫស្សី ស្រុក គងពិសី ខេត្ត កំពង់ស្ពឺ VAT: B105-901704100 | Q20: ភូមិ អង្គសុគន្ធា ឃុំ មហាឫស្សី ស្រុក គងពិសី ខេត្ត កំពង់ស្ពឺ VAT: B105-901704100 | S20: CHHOEM SAMBOK | T20: 030587652 | U20: AGRIMILE TRADING CO.,LTD | V20: K008-902103926 | W20: 017 537 443 | AB20: 45675 | AC20: ថ្ងៃសៅរ៍ ៥រោច ខែបុស្ស ឆ្នាំរោង ឆស័ក ព.ស.២៥៦៨ | AD20: ថ្ងៃព្រហស្បតិ៍ | AE20: ៨ កើត | AF20: ខែបុស្ស | AG20: ឆ្នាំថោះ | AH20: បញ្ចស័ក ពស. ២៥៦៧ | AK20: ៥ រោច | AL20: ៥ កើត
C21: CGC | D21: ឈ្មោះ ឆាយណាខា ដែលមានទីតាំងឃ្លាំងលេខ ៩-១០ ផ្លូវ ភូមិ ៧ សង្កាត់ ទឹកល្អក់ទី១ ខណ្ឌ ទួលគោក រាជធានីភ្នំពេញ ទីតាំងបង្ហាញរថយន្ត (Showroom) របស់ក្រុមហ៊ុន CHINA GOOD CAR INVESTMENT (CAMBODIA) CO.,LTD។ | E21: https://goo.gl/maps/TAd2yAmn6EJfHT3z8 | F21: SREY CHINDA | G21: ភេទស្រី មានអត្តសញ្ញាណប័ណ្ណសញ្ជាតិខ្មែរលេខៈ010432848(01) ជាប្រធានក្រុមហ៊ុន SREY CHINDA IMPORT EXPORT CO.,LTD អត្តសញ្ញាណកម្មសារពើពន្ធ (VAT)លេខៈ K010-901902352 ទូរសព្ទ័លេខៈ 098 700 350 | H21: VICTOR MOTOR CO.,LTD | I21: YU YIXIANG | O21: UNITED MERCURY GROUP CO.,LTD | P21: #៤៨ ផ្លូវ ជាតិលេខ៤ ភូមិ ព្រៃព្រីងខាងជើង សង្កាត់ ចោមចៅ ខណ្ឌ ពោធិ៍សែនជ័យ រាជធានីភ្នំពេញ VAT: L001-108001873 | Q21: #៤៨ ផ្លូវ ជាតិលេខ៤ ភូមិ ព្រៃព្រីងខាងជើង សង្កាត់ ចោមចៅ ខណ្ឌ ពោធិ៍សែនជ័យ រាជធានីភ្នំពេញ VAT: L001-108001873 | S21: PAIBOON LAOCHAN | T21: AB4916750 | U21: BJC CELLOX(CAMBODIA) CO., LTD | V21: L001-901639149 | W21: 092 784 079 | AB21: 45676 | AC21: ថ្ងៃអាទិត្យ ៦រោច ខែបុស្ស ឆ្នាំរោង ឆស័ក ព.ស.២៥៦៨ | AD21: ថ្ងៃសុក្រ | AE21: ៩ កើត | AF21: ខែបុស្ស | AG21: ឆ្នាំថោះ | AH21: បញ្ចស័ក ពស. ២៥៦៧ | AK21: ៦ រោច | AL21: ៦ កើត
C22: JETOUR | D22: ឈ្មោះ JETOUR ដែលមានទីតាំង#315,ផ្លូវជាតិ 6A,សង្កាត់ ព្រែកលៀប, ខណ្ឌ ជ្រោយចង្វារ, រាជធានីភ្នំពេញ ទីតាំងបង្ហាញរថយន្ត (Showroom) របស់ក្រុមហ៊ុន CHINA GOOD CAR INVESTMENT (CAMBODIA) CO.,LTD។ | E22: https://goo.gl/maps/z8V4So5cupHNnQ9f7 | F22: ហូម៉េន សេនតូនី តាន់ឌីហ្សូណូ | G22: ភេទប្រុស មានអត្តសញ្ញាណប័ណ្ណសញ្ជាតិខ្មែរលេខៈ010464617 ជាប្រធានក្រុមហ៊ុន TF MORTORS (CAMBODIA) CO.,LTD អត្តសញ្ញាណកម្មសារពើពន្ធ (VAT)លេខៈ L001-104008598 ទូរសព្ទ័លេខៈ 088 8772209 | H22: MOUSTAFA MT | I22: SET MOUSTAFA | O22: YUEKA ONE-STOP AUTO SERVICE CO. LTD | P22: 166#,NATIONAL ROAD NO.6, GROUP 4, PHUM KEAN KLAING, SANGKAT CHROY CHONG VA, KHAN CHROY CHONG VA, PHNOM PENH, CAMBODIA VAT: L001-901804963 | Q22: 166#,NATIONAL ROAD NO.6, GROUP 4, PHUM KEAN KLAING, SANGKAT CHROY CHONG VA, KHAN CHROY CHONG VA, PHNOM PENH, CAMBODIA VAT: L001-901804963 | S22: LIAO KAILING | T22: EG2412090 | U22: ONEROAD INDUSTRIAL (CAMBODIA) CO.,LTD | V22: K002-902101770 | AB22: 45677 | AC22: ថ្ងៃចន្ទ ៧រោច ខែបុស្ស ឆ្នាំរោង ឆស័ក ព.ស.២៥៦៨ | AD22: ថ្ងៃសៅរ៍ | AE22: ១០ កើត | AF22: ខែបុស្ស | AG22: ឆ្នាំថោះ | AH22: បញ្ចស័ក ពស. ២៥៦៧ | AK22: ៧ រោច | AL22: ៧ កើត
C23: DFSK | D23: ឈ្មោះ (DFSK) XST AUTO ដែលមានទីតាំង# 319,Hanoi Friendship Blvd（1019）សង្កាត់ភ្នំពេញថ្មី , ខណ្ឌសែនសុខ ,រាជធានីភ្នំពេញ ទីតាំងបង្ហាញរថយន្ត (Showroom) របស់ក្រុមហ៊ុន XST AUTO (CAMBODIA) INTERNATIONAL CO., LTD | E23: https://goo.gl/maps/xW9ZSXgkPh82TjKdA | F23: YU YIXIANG | G23: ភេទប្រុស ដែលមានលិខិតឆ្លងដែនលេខៈ EA3791641 ជាប្រធានក្រុមហ៊ុន VICTOR MOTOR CO.,LTD. អត្តសញ្ញាណកម្មសារពើពន្ធ (VAT)លេខៈ K005-901906510 ទូរសព្ទ័លេខៈ 099 255 500 | H23: JSD | I23: ហម គឹមឡេង | O23: VICTOR MOTOR CO.,LTD | P23: #៩៨ ផ្លូវ ១១០ សង្កាត់ ទឹកល្អក់ទី ១ ខណ្ឌ ទួលគោក រាជធានីភ្នំពេញ TEL: K005-901906510 | Q23: #៩៨ ផ្លូវ ១១០ សង្កាត់ ទឹកល្អក់ទី ១ ខណ្ឌ ទួលគោក រាជធានីភ្នំពេញ TEL: K005-901906510 | S23: ZHANG HUA | T23: E37888060 | U23: H U A Y (CAMBODIA) INTERNATIONAL AUTO TRADE CO., LTD | V23: L001-901909613 | W23: 098881618 | AB23: 45678 | AC23: ថ្ងៃអង្គារ ៨រោច ខែបុស្ស ឆ្នាំរោង ឆស័ក ព.ស.២៥៦៨ | AD23: ថ្ងៃអាទិត្យ | AE23: ១១ កើត | AF23: ខែបុស្ស | AG23: ឆ្នាំថោះ | AH23: បញ្ចស័ក ពស. ២៥៦៧ | AK23: ៨ រោច | AL23: ៨ កើត
C24: TUNING | D24: ឈ្មោះ AUTO TUNING ដែលមានទីតាំង NO 84-90, Street 214 Beoung Proluet, Khan 7 Meakara ទីតាំងបង្ហាញរថយន្ត (Showroom) របស់ក្រុមហ៊ុន O C D M TRADING CO., LTD ទូរស័ព្ទលេខ: 093 82 23 23។ | E24: https://goo.gl/maps/jLNButnqVMBP8jjv7 | F24: SET MOUSTAFA | G24: ភេទប្រុស ដែលមានលិខិតឆ្លងដែនលេខៈ 011053628 ជាប្រធានក្រុមហ៊ុន MOUSTAFA MT(CAMBODIA) CO.,LTD អត្តសញ្ញាណកម្មសារពើពន្ធ (VAT)លេខៈ K010-902103109 ទូរសព្ទ័លេខៈ 099 255 500 | H24: N/A | I24: WICHAI ON-SRI | O24: MAHA SOK APHIVATH TRADING CO.,LTD | P24: #បុរីពិភពថ្មីចំការដូងផ្ទះលេខ ០៦ ផ្លូវ ០៥ ភូមិ ប្រការ សង្កាត់ ព្រៃស ខណ្ឌ ដង្កោ រាជធានីភ្នំពេញ VAT: K006-902102027 | Q24: #បុរីពិភពថ្មីចំការដូងផ្ទះលេខ ០៦ ផ្លូវ ០៥ ភូមិ ប្រការ សង្កាត់ ព្រៃស ខណ្ឌ ដង្កោ រាជធានីភ្នំពេញ VAT: K006-902102027 | S24: PAV PHEA RUM | T24: 061675682 | U24: BURIRUM TECHNICIAN CO.,LTD | V24: K007-902201280 | W24: 012 400 152 | AB24: 45679 | AC24: ថ្ងៃពុធ ៩រោច ខែបុស្ស ឆ្នាំរោង ឆស័ក ព.ស.២៥៦៨ | AD24: ថ្ងៃចន្ទ | AE24: ១២ កើត | AF24: ខែបុស្ស | AG24: ឆ្នាំថោះ | AH24: បញ្ចស័ក ពស. ២៥៦៧ | AK24: ៩ រោច | AL24: ៩ កើត
C25: KIM SRUN | D25: ឈ្មោះ គឹមស្រ៊ុនព្រីមៀមអូតូ (KIM SRUN PREMIUM AUTO) ដែលមានទីតាំង អាគារ 168 មហាវិថីព្រះមុន្នីវង្ស (93),សង្កាត់ ស្រះចក,ខណ្ឌដូនពេញ រាជធានីភ្នំពេញ ទូរស័ព្ទលេខ 012 985 555។ | E25: 11.578325314877558, 104.91689997184871 | F25: ហម គឹមឡេង | H25: N/A | I25: DON THONGPRAPAI | O25: ZENITH MACHINERY LEASING CO., LTD | P25: #១៥H ផ្លូវបេតុង ភូមិទឹកថ្លា សង្កាត់ទឹកថ្លា ខណ្ឌសែនសុខ រាជធានីភ្នំពេញ VAT: K009-902005913 | Q25: #១៥H ផ្លូវបេតុង ភូមិទឹកថ្លា សង្កាត់ទឹកថ្លា ខណ្ឌសែនសុខ រាជធានីភ្នំពេញ VAT: K009-902005913 | S25: BAI JIUZHI | T25: EE3035125 | U25: CHINA GOOD CAR INVESTMENT (CAMBODIA) CO.,LTD | V25: K005-901907714 | W25: 092 778 859 | AB25: 45680 | AC25: ថ្ងៃព្រហស្បតិ៍ ១០រោច ខែបុស្ស ឆ្នាំរោង ឆស័ក ព.ស.២៥៦៨ | AD25: ថ្ងៃអង្គារ | AE25: ១៣ កើត | AF25: ខែបុស្ស | AG25: ឆ្នាំថោះ | AH25: បញ្ចស័ក ពស. ២៥៦៧ | AK25: ១០ រោច | AL25: ១០ កើត
C26: FAW-V | D26: ឈ្មោះ FAW-VOLKSWAGEN ដែលមានទីតាំងNo.98 Street 110 , Toek Lok 1 Commune , Toul Kork District , Phnom Penh ទីតាំងបង្ហាញរថយន្ត (Showroom) របស់ក្រុមហ៊ុន របស់ក្រុមហ៊ុន HS MOTOR CO.,LTD ទូរស័ព្ទលេខ:095 999 82។ | E26: https://goo.gl/maps/8kzFf2rzbnV62TrP9 | F26: BOONNAM KULRAKAMPUSIRI | G26: ភេទប្រុស ដែលមានលិខិតឆ្លងដែនលេខៈAC2134008 អគ្គនាយករងនៃក្រុមហ៊ុន BJC CELLOX(CAMBODIA) CO., LTD អត្តសញ្ញាណកម្មសារពើពន្ធ (VAT)លេខៈ L001-901639149 ទូរសព្ទ័លេខៈ 069 777 815 ទីតាំងនៅផ្លូវជាតិលេខ ១ គីឡូម៉ែតលេខ ៤៦ ភូមិ សំរោងក្អែរ ឃុំ សំរោងធំ ស្រុកកៀនស្វាយ ខេត្តកណ្តាល ។ | H26: N/A | I26: WICHAI ON-SRI | O26: A N D Y (CAMBODIA) INTERNATIONAL AUTO TRADE CO., LTD | P26: អាស័យដ្ឋាន:# ១០៧៦ ផ្លូវម៉ៃដា(២០០៤) ភូមិ ទឹកថ្លា សង្កាត់ ទឹកថ្លា ខណ្ឌសែនសុខ រាជធានីភ្នំពេញ VAT: L001-902104222 | Q26: អាស័យដ្ឋាន:# ១០៧៦ ផ្លូវម៉ៃដា(២០០៤) ភូមិ ទឹកថ្លា សង្កាត់ ទឹកថ្លា ខណ្ឌសែនសុខ រាជធានីភ្នំពេញ VAT: L001-902104222 | S26: CHOEM PICHIT | T26: 100746252 | U26: CHOEM PICHIT IMPORT EXPORT CO.,LTD | V26: L009-902202339 | W26: 093 453 081 | AB26: 45681 | AC26: ថ្ងៃសុក្រ ១១រោច ខែបុស្ស ឆ្នាំរោង ឆស័ក ព.ស.២៥៦៨ | AD26: ថ្ងៃពុធ | AE26: ១៤ កើត | AF26: ខែបុស្ស | AG26: ឆ្នាំថោះ | AH26: បញ្ចស័ក ពស. ២៥៦៧ | AK26: ១១ រោច | AL26: ១១ កើត
C27: GTV | D27: ឈ្មោះ GTV MOTOR ដែលមានអាស័យដ្ឋាន: National Road 2, Srok Thom Village, Cheung Keb Commune, Kandal Steung District, Kandal Province. Cambodia. ទីតាំងបង្ហាញរថយន្ត (Showroom) របស់ក្រុមហ៊ុន HS MOTOR CO.,LTD ទូរស័ព្ទលេខ:095 999 82។ | E27: https://goo.gl/maps/xjSR154zc2fC58Jp7 | F27: BAI JIUZHI | G27: ភេទប្រុស កាន់លិខិតឆ្លងដែនលេខ: EE3035125 ជាប្រធានក្រុមហ៊ុន CHINA GOOD CAR INVESTMENT (CAMBODIA) CO.,LTD អត្តសញ្ញាណកម្មសារពើពន្ធ (VAT)លេខៈ K005-901907714 ទូរសព្ទ័លេខៈ 092 778 859 | H27: CHINA GOOD CAR INVESTMENT (CAMBODIA) CO.,LTD | I27: BAI JIUZHI | O27: AUTOMOTIVE ASIA (CAMBODIA) LIMITED | P27: អាសយដ្ឋាន#15Z ផ្លូវព្រះមុនីវង្ស កែងផ្លូវ 422 សង្កាត់ទន្លេបាសាក់ ខណ្ឌចំការមន រាជធានីភ្នំពេញ VAT: L001-107030985 | Q27: អាសយដ្ឋាន#15Z ផ្លូវព្រះមុនីវង្ស កែងផ្លូវ 422 សង្កាត់ទន្លេបាសាក់ ខណ្ឌចំការមន រាជធានីភ្នំពេញ VAT: L001-107030985 | S27: JIANG ZHIPING | T27: E85954264 | U27: EVERSAILING SUPPLY CHAIN (CAMBODIA) CO.,LTD | V27: K005-902101776 | W27: 071 792 7651 | AB27: 45682 | AC27: ថ្ងៃសៅរ៍ ១២រោច ខែបុស្ស ឆ្នាំរោង ឆស័ក ព.ស.២៥៦៨ | AD27: ថ្ងៃព្រហស្បតិ៍ | AE27: ១៥ កើត | AF27: ខែបុស្ស | AG27: ឆ្នាំថោះ | AH27: បញ្ចស័ក ពស. ២៥៦៧ | AK27: ១២ រោច | AL27: ១២ កើត
C28: WUL | D28: ឈ្មោះ WULING ដែលមានទីតាំងលេខ ២៧៨H ផ្លូវជាតិលេខ៦អា ភូមិគៀនឃ្លាំង សង្កាត់ព្រែកលៀប ខណ្ឌជ្រោយចង្វារ រាជធានីភ្នំពេញ លេខទំនាក់ទំនង៖ 096 34 95 302 ជាទីតាំងបង្ហាញរថយន្ត (SHOWROOM) របស់ក្រុមហ៊ុន FD AUTO (CAMBODIA) INTERNATIONAL TRADE CO., LTD។ | E28: https://maps.app.goo.gl/8FzUWyHaxFMwdmLG8 | F28: ហ៊ាន សហមុន្នី | G28: ភេទប្រុស មានអត្តសញ្ញាណប័ណ្ណសញ្ជាតិខ្មែរលេខៈ 070296574 ជាប្រធានក្រុមហ៊ុន ZENITH MACHINERY LEASING CO.,LTD អត្តសញ្ញាណកម្មសារពើពន្ធ (VAT)លេខៈ K009-902005913 | H28: DHONNA JIA CHENG IMP EXP CO.,LTD | I28: សំ សុផល | O28: SAY SREYMOM IMPORT & EXPORT CO.,LTD | P28: អាសយដ្ឋាន#1A ផ្លូវ56D9 ភូមិម័ល សង្កាត់ដង្កោ ខណ្ឌដង្កោ រាជធានីភ្នំពេញ VAT: K006-902106071 | Q28: អាសយដ្ឋាន#1A ផ្លូវ56D9 ភូមិម័ល សង្កាត់ដង្កោ ខណ្ឌដង្កោ រាជធានីភ្នំពេញ VAT: K006-902106071 | S28: ALFRED KASUMA ALIWARGA | T28: C7615365 | U28: UNITED MERCURY GROUP CO.,LTD | V28: L001-108001873 | W28: 070 873235 | AB28: 45683 | AC28: ថ្ងៃអាទិត្យ ១៣រោច ខែបុស្ស ឆ្នាំរោង ឆស័ក ព.ស.២៥៦៨ | AD28: ថ្ងៃសុក្រ | AE28: ១ រោច | AF28: ខែបុស្ស | AG28: ឆ្នាំថោះ | AH28: បញ្ចស័ក ពស. ២៥៦៧ | AK28: ១៣ រោច | AL28: ១៣ កើត
C29: FAW TRUCKS | D29: ឈ្មោះ FAW TRUCKS ដែលមានអាស័យដ្ឋាន: No.51A ផ្លូវ ហាណូយ, ខណ្ឌសែនសុខ , រាជធានីភ្នំពេញ ទីតាំងបង្ហាញរថយន្ត (Showroom) របស់ក្រុមហ៊ុន JF MOTOR CO., LTD។ | E29: https://maps.app.goo.gl/2tvM1nyFbV613EuVA | F29: សំ សុផល | G29: ភេទស្រី មានអត្តសញ្ញាណប័ណ្ណសញ្ជាតិខ្មែរលេខៈ 061845188 ជាប្រធានក្រុមហ៊ុន DHONNA JIA CHENG IMP EXP CO.,LTD អត្តសញ្ញាណកម្មសារពើពន្ធ (VAT)លេខៈ K007-901903554 | H29: YUEKA ONE-STOP AUTO SERVICE CO. LTD | I29: LI XINHUA | O29: L U SEA TRADING SERVICE CO., LTD | P29: ផ្លូវជាតិលេខ៥ ភូមិដួង សង្កាត់ព្រែកព្នៅ ខណ្ឌរាជធានី ភ្នំពេញ VAT : K009-901905395 | Q29: ផ្លូវជាតិលេខ៥ ភូមិដួង សង្កាត់ព្រែកព្នៅ ខណ្ឌរាជធានី ភ្នំពេញ VAT : K009-901905395 | S29: OEURN CHANDET | T29: 150901855 | U29: O C D M TRADING CO., LTD | V29: K007-902104377 | W29: 011746031 | AB29: 45684 | AC29: ថ្ងៃចន្ទ ១៤រោច ខែបុស្ស ឆ្នាំរោង ឆស័ក ព.ស.២៥៦៨ | AD29: ថ្ងៃសៅរ៍ | AE29: ២ រោច | AF29: ខែបុស្ស | AG29: ឆ្នាំថោះ | AH29: បញ្ចស័ក ពស. ២៥៦៧ | AK29: ១៤ រោច | AL29: ១៤ កើត
C30: MG 60M | D30: MORRIS GARAGES ដែលមានទីតាំង #179-185 ផ្លូវ ឧកញ្ញ៉ាមហាភក្ដី ហ៊ុននាង, សង្កាត់ចាក់អង្រែក្រោម, ភ្នំពេញ ជាទីតាំងបង្ហាញ (SHOWROOM)របស់ក្រុមហ៊ុន TF MOTORS (CAMBODIA) CO., LTD។ | E30: https://maps.app.goo.gl/ABRHiNiopnSau79k7?g_st=ic | F30: LI XINHUA | G30: ភេទប្រុស ដែលមានលិខិតឆ្លងដែនលេខៈ E16409716 ជាប្រធានក្រុមហ៊ុន YUEKA ONE-STOP AUTO SERVICE CO. LTD អត្តសញ្ញាណកម្មសារពើពន្ធ (VAT)លេខៈ L001-901804963 ទូរសព្ទ័លេខៈ 078 890 777 | H30: ZENITH MACHINERY LEASING CO., LTD | I30: ហ៊ាន សហមុន្នី | O30: BURIRUM TECHNICIAN CO., LTD | P30: #C-09 និង C-10 ផ្លូវ លំ ភូមិ ដំណាក់ធំ សង្កាត់ ស្ទឹងមានជ័យទី២ ខណ្ឌ មានជ័យ រាជធានីភ្នំពេញ VAT : K007-902201280 | Q30: #C-09 និង C-10 ផ្លូវ លំ ភូមិ ដំណាក់ធំ សង្កាត់ ស្ទឹងមានជ័យទី២ ខណ្ឌ មានជ័យ រាជធានីភ្នំពេញ VAT : K007-902201280 | S30: DEAB SIYET | T30: 030598691 | U30: HUA RONG SENG INTERNATIONAL MINING CO.,LTD | V30: K009-902204536 | W30: 097 7978 632 | AB30: 45685 | AC30: ថ្ងៃអង្គារ ១៥រោច ខែបុស្ស ឆ្នាំរោង ឆស័ក ព.ស.២៥៦៨ | AD30: ថ្ងៃអាទិត្យ | AE30: ៣ រោច | AF30: ខែបុស្ស | AG30: ឆ្នាំថោះ | AH30: បញ្ចស័ក ពស. ២៥៦៧ | AK30: ១៥ រោច | AL30: ១៥ កើត
C31: MG SR | D31: MORRIS GARAGES ដែលមានទីតាំង #ផ្លូវ ភូមិ គោកត្នោត ឃុំ កណ្ដែក ស្រុក ប្រាសាទបាគង ខេត្តសៀមរាប ជាទីតាំងបង្ហាញ (SHOWROOM)របស់ក្រុមហ៊ុន TF MOTORS (CAMBODIA) CO., LTD។ | E31: https://maps.app.goo.gl/qWxmFSEBYSm1igPZ6?g_st=ic | F31: អូច ពៅ | G31: ភេទប្រុស មានអត្តសញ្ញាណប័ណ្ណសញ្ជាតិខ្មែរលេខៈ 051559119 ជាប្រធានក្រុមហ៊ុន DGML IMPORT EXPORT CO.,LTD អត្តសញ្ញាណកម្មសារពើពន្ធ (VAT)លេខៈ K006-902105683 | H31: BJC CELLOX (CAMBODIA) CO., LTD | I31: BOONNAM KULRAKAMPUSIRI | O31: CHINA GOOD CAR INVESTMENT (CAMBODIA) CO.,LTD | P31: #ឃ្លាំងលេខ ៩-១០ ផ្លូវ ភូមិ ៧ សង្កាត់ ទឹកល្អក់ទី១ ខណ្ឌ ទួលគោក រាជធានីភ្នំពេញ VAT : K005-901907714 | Q31: #ឃ្លាំងលេខ ៩-១០ ផ្លូវ ភូមិ ៧ សង្កាត់ ទឹកល្អក់ទី១ ខណ្ឌ ទួលគោក រាជធានីភ្នំពេញ VAT : K005-901907714 | S31: SORN HORNG | T31: 101205869 | U31: SORN HORNG ENTERPRISE CO.,LTD | V31: K010 902204642 | W31: 096 291 7646 | AB31: 45686 | AC31: ថ្ងៃពុធ ១កើត ខែមាឃ ឆ្នាំរោង ឆស័ក ព.ស.២៥៦៨ | AD31: ថ្ងៃចន្ទ | AE31: ៤ រោច | AF31: ខែបុស្ស | AG31: ឆ្នាំថោះ | AH31: បញ្ចស័ក ពស. ២៥៦៧
C32: AUTOHOME | D32: AUTOHOME ដែលមានអាសយដ្ឋាន #៨៥៦ ផ្លូវ សហព័ន្ធរុស្សី (១១០), ក្រុមទី៥ ភូមិ ទឹកថ្លា សង្កាត់ ទឹកថ្លា ខណ្ឌ សែនសុខ , ភ្នំពេញ ជាទីតាំងបង្ហាញ (SHOWROOM)របស់ក្រុមហ៊ុន AUTOHOME(CAMBODIA) IMPORT EXPORT CO.,LTD។ | E32: https://maps.app.goo.gl/2AHTffvCQvkcsz717?g_st=iw | F32: ជួន រ៉ូ | G32: ភេទប្រុស មានអត្តសញ្ញាណប័ណ្ណសញ្ជាតិខ្មែរលេខៈ 040430759 ជាប្រធានក្រុមហ៊ុន FEEDS UP CO.,LTD អត្តសញ្ញាណកម្មសារពើពន្ធ (VAT)លេខៈ K006-902105453 | H32: AUTOMOTIVE ASIA (CAMBODIA) LIMITED | I32: គង់​ គិនណារី | O32: CHOEM PICHIT IMPORT EXPORT CO.,LTD | P32: #គ្មាន ផ្លូវ ឩកញ៉ាម៉ុងឫទ្ធី(១៩២៨) ភូមិ ច្រេស សង្កាត់ គោកឃ្លាង ខណ្ឌ សែនសុខ រាជធានីភ្នំពេញ VAT : L009-902202339 | Q32: #គ្មាន ផ្លូវ ឩកញ៉ាម៉ុងឫទ្ធី(១៩២៨) ភូមិ ច្រេស សង្កាត់ គោកឃ្លាង ខណ្ឌ សែនសុខ រាជធានីភ្នំពេញ VAT : L009-902202339 | S32: DO MARYNOEL | T32: 011199507 | U32: HS MOTOR CO.,LTD | V32: K005 902205145 | W32: 015 707 091 | AB32: 45687 | AC32: ថ្ងៃព្រហស្បតិ៍ ២កើត ខែមាឃ ឆ្នាំរោង ឆស័ក ព.ស.២៥៦៨ | AD32: ថ្ងៃអង្គារ | AE32: ៥ រោច | AF32: ខែបុស្ស | AG32: ឆ្នាំថោះ | AH32: បញ្ចស័ក ពស. ២៥៦៧
C33: KAUTO | D33: ឈ្មោះ ខេអូតូ(K AUTO) ដែលមានទីតាំង អាគារ 168 មហាវិថីព្រះមុន្នីវង្ស (93),សង្កាត់ ស្រះចក,ខណ្ឌដូនពេញ រាជធានីភ្នំពេញ ទូរស័ព្ទលេខ 012 985 555។ | E33: 11.578325314877558, 104.91689997184871 | F33: គង់​ គិនណារី | G33: ភេទស្រី មានអត្តសញ្ញាណប័ណ្ណសញ្ជាតិខ្មែរលេខៈ010852466 មានតួនាទី ប្រធានក្រុមហ៊ុន AUTOMOTIVE ASIA (CAMBODIA) LIMITED អត្តសញ្ញាណកម្មសារពើពន្ធ (VAT)លេខៈ L001-107030985 | H33: N/A | I33: ស្រ៊ុន ណាល់ | O33: EVERSAILING SUPPLY CHAIN (CAMBODIA) CO.,LTD | P33: N0.10G,ST230 PHUM4 SANGKAT BOE UNG SALANG KHAN TUOL KOUK - PHNOM PENH VAT :K005-902101776 | Q33: N0.10G,ST230 PHUM4 SANGKAT BOE UNG SALANG KHAN TUOL KOUK - PHNOM PENH VAT :K005-902101776 | S33: CHENG JIUSI | T33: EE1326007 | U33: GTV MOTOR CO.,LTD | V33: L001-902203582 | W33: 015 707 091 | AB33: 45688 | AC33: ថ្ងៃសុក្រ ៣កើត ខែមាឃ ឆ្នាំរោង ឆស័ក ព.ស.២៥៦៨ | AD33: ថ្ងៃពុធ | AE33: ៦ រោច | AF33: ខែបុស្ស | AG33: ឆ្នាំថោះ | AH33: បញ្ចស័ក ពស. ២៥៦៧
C34: JMC | D34: ឈ្មោះ​ JMC ដែលមានទីតាំង #643 មហាវិថីមិត្តភាពហាណូយ (1019), សង្កាត់ភ្នំពេញថ្មី, ខណ្ឌសែនសុខ, រាជធានីភ្នំពេញ ជាទីតាំងបង្ហាញរថយន្ត (Showroom) របស់ក្រុមហ៊ុន XST AUTO (CAMBODIA) INTERNATIONAL TRADE CO., LTD។ | E34: https://goo.gl/maps/C4z9v8FtuqgFFec99 | F34: ស្រ៊ុន ណាល់ | G34: ភេទប្រុស មានអត្តសញ្ញាណប័ណ្ណសញ្ជាតិខ្មែរលេខៈ 061815277 ជាប្រធានក្រុមហ៊ុន NAL SRUN 62 IMPORT EXPORT CO.,LTD អត្តសញ្ញាណកម្មសារពើពន្ធ (VAT)លេខៈ K007-9020022874 | H34: JSD | I34: TANG XIUNING | O34: O C D M TRADING CO., LTD | P34: #31 ផ្លូវ P25 ភូមិ បឹងឈូក សង្កាត់ និរោធ ខណ្ឌ ច្បារអំពៅ រាជធានីភ្នំពេញ VAT :K007-902104377 | Q34: #31 ផ្លូវ P25 ភូមិ បឹងឈូក សង្កាត់ និរោធ ខណ្ឌ ច្បារអំពៅ រាជធានីភ្នំពេញ VAT :K007-902104377 | S34: HANN SINATH | T34: ​020921342 | U34: GLOBAL GREEN (CAMBODIA) ENERGY DEVELOPMENT CO.,LTD | V34: L001-107029847 | W34: 098 425 713 | AB34: 45689 | AC34: ថ្ងៃសៅរ៍ ៤កើត ខែមាឃ ឆ្នាំរោង ឆស័ក ព.ស.២៥៦៨ | AD34: ថ្ងៃព្រហស្បតិ៍ | AE34: ៧ រោច | AF34: ខែបុស្ស | AG34: ឆ្នាំថោះ | AH34: បញ្ចស័ក ពស. ២៥៦៧
C35: ANKEN | D35: ឈ្មោះ ANKEN AUTO ដែលមានទីតាំងទី១នៅ ផ្លូវ 78 សង្កាត់ទន្លេបាសាក ខណ្ឌចំការមន រាជធានីភ្នំពេញ ទូរស័ព្ទលេខ 017 760 671 នឹងទីតាំងទី២ ផ្ទះលេខ១៦០ ផ្លូវជាតិលេខ១ ភូមិបឹងឈូក ​សង្កាត់និរោធ ខណ្ឌច្បារអំពៅ រាជធានីភ្នំពេញ ទូរស័ព្ទលេខ 081 337 933។ | E35: https://maps.app.goo.gl/XwfSQjLuqGuvYayo7 | F35: ZHANG HUA | G35: ភេទស្រី ដែលមានលិខិតឆ្លងដែនលេខៈ E37888060 ជាប្រធានក្រុមហ៊ុន A N D Y (CAMBODIA) INTERNATIONAL AUTO TRADE CO.,LTD អត្តសញ្ញាណកម្មសារពើពន្ធ (VAT)លេខៈ L001-902104222 ទូរសព្ទ័លេខៈ +855 098881618​ | H35: JSD | I35: TANG XIUNING | O35: HUA RONG SENG INTERNATIONAL MINING CO.,LTD | P35: #14C2 ផ្លូវ លំ ភូមិ ព្រៃមូល សង្កាត់ ក្រាំងធ្នង់ ខណ្ឌ សែនសុខ រាជធានីភ្នំពេញ VAT :K009-902204536 | S35: POL SAVRY | T35: 171011534 | U35: SNCO (CAMBODIA) CO., LTD | V35: K008 902202776 | W35: 093 749 248 | AB35: 45690 | AC35: ថ្ងៃអាទិត្យ ៥កើត ខែមាឃ ឆ្នាំរោង ឆស័ក ព.ស.២៥៦៨ | AD35: ថ្ងៃសុក្រ | AE35: ៨ រោច | AF35: ខែបុស្ស | AG35: ឆ្នាំថោះ | AH35: បញ្ចស័ក ពស. ២៥៦៧
C36: DFSK2 | D36: ឈ្មោះ DFSK ដែលមានទីតាំង# 319,Hanoi Friendship Blvd（1019）សង្កាត់ភ្នំពេញថ្មី , ខណ្ឌសែនសុខ ,រាជធានីភ្នំពេញ ទីតាំងបង្ហាញរថយន្ត (Showroom) របស់ក្រុមហ៊ុន ONE PLUS AUTO TRADING (CAMBODIA) CO., LTD ទូរស័ព្ទលេខ 096910000 , 096710000 ។ | E36: https://maps.app.goo.gl/dkmB55bm1iVRYJq18 | F36: TANG XIUNING | G36: ភេទប្រុស ដែលមានលិខិតឆ្លងដែនលេខៈ ED9067769 ជាប្រធានក្រុមហ៊ុន JI SHUN DA DTADING CO.,LTD អត្តសញ្ញាណកម្មសារពើពន្ធ (VAT)លេខៈ K010-901908667 ទូរសព្ទ័លេខៈ | H36: HUAN YA HE ZHONG (CAMBODIA) TRADING CO., LTD | I36: MO GUANKANG | O36: DGML IMPORT EXPORT CO.,LTD | P36: អាស័យដ្ឋាន:# បុរីពិភពថ្មីកួរស្រូវទី២ ផ្ទះលេខ៣២អា ជាន់ផ្ទាល់ដី ផ្លូវ១៩ ភូមិ ស្រីស្នំ សង្កាត់ ព្រែកកំពឹស ខណ្ឌ ដង្កោ រាជធានីភ្នំពេញ VAT: L006-902105683 | S36: CHOEM SIRATH | T36: 110571200 | U36: CHOEM SIRATH IMPORT & EXPORT CO,LTD | V36: K008-902300821 | W36: 087 452 029 | AB36: 45691 | AC36: ថ្ងៃចន្ទ ៦កើត ខែមាឃ ឆ្នាំរោង ឆស័ក ព.ស.២៥៦៨ | AD36: ថ្ងៃសៅរ៍ | AE36: ៩ រោច | AF36: ខែបុស្ស | AG36: ឆ្នាំថោះ | AH36: បញ្ចស័ក ពស. ២៥៦៧
C37: NHAUTO | D37: ឈ្មោះ NH Auto ដែលមានទីតាំង# ផ្ទះលេខ៣៣ ផ្លូវ៦០៨ ភូមិ១២ សង្កាត់បឹងកក់ទី២ ខណ្ឌទួលគោក រាជធានីភ្នំពេញ ទីតាំងបង្ហាញរថយន្ត (Showroom) របស់ក្រុមហ៊ុន TWO RCP ASIA CO., LTD ទូរស័ព្ទលេខ 016988234 ។ | E37: https://maps.app.goo.gl/hCthUNhcGJ2oueUo9 | F37: SAY SREYMOM | G37: ភេទស្រី មានអត្តសញ្ញាណប័ណ្ណសញ្ជាតិខ្មែរលេខៈ 110597540 មានតួនាទី ប្រធានក្រុមហ៊ុន SAY SREYMOM IMPORT & EXPORT CO.,LTD អត្តសញ្ញាណកម្មសារពើពន្ធ (VAT)លេខៈ K006-902106071 | H37: SAY SREYMOM IMPORT & EXPORT CO.,LTD | I37: SAY SREYMOM | O37: SORN HORNG ENTERPRISE CO.,LTD | P37: #G5A1 ផ្លូវ បេតុង ភូមិ ទួលពង្រ សង្កាត់ ចោមចៅទី១ ខណ្ឌ ពោធិ៍សែនជ័យ រាជធានីភ្នំពេញ VAT: K010 902204642 | Q37: #G5A1 ផ្លូវ បេតុង ភូមិ ទួលពង្រ សង្កាត់ ចោមចៅទី១ ខណ្ឌ ពោធិ៍សែនជ័យ រាជធានីភ្នំពេញ VAT: K010 902204642 | S37: TAING CHENG OING | T37: 010954723 | U37: TAING CHENG OING CONSTRUCTION &IMPORT EXPORT CO.,LTD | V37: L001-180001159 | W37: ០68 666 868 | AB37: 45692 | AC37: ថ្ងៃអង្គារ ៧កើត ខែមាឃ ឆ្នាំរោង ឆស័ក ព.ស.២៥៦៨ | AD37: ថ្ងៃអាទិត្យ | AE37: ១០ រោច | AF37: ខែបុស្ស | AG37: ឆ្នាំថោះ | AH37: បញ្ចស័ក ពស. ២៥៦៧
C38: OCH/EAC | D38: ឈ្មោះ ONE CAR HOME / EV AUTO CLUB ដែលមានទីតាំង# ផ្ទះលេខ 12AB ផ្លូវ 2004 ខណ្ឌសែនសុខ រាជធានីភ្នំពេញ ទូរស័ព្ទលេខ 0968975776 ។ | E38: https://maps.app.goo.gl/to7J1sGd39dUyS2S6?g_st=atm | F38: CHHOEM SAMBOK | G38: ភេទស្រី មានអត្តសញ្ញាណប័ណ្ណសញ្ជាតិខ្មែរលេខៈ 030587652 មានតួនាទី ប្រធានក្រុមហ៊ុន AGRIMILE TRADING CO.,LTD អត្តសញ្ញាណកម្មសារពើពន្ធ (VAT)លេខៈ K008-902103926 | H38: BJC CELLOX (CAMBODIA) CO., LTD | I38: PAIBOON LAOCHAN | O38: HS MOTOR CO.,LTD | P38: #98 ផ្លូវ 110 ភូមិ 6 សង្កាត់ ទឹកល្អក់ទី១ ខណ្ឌ ទួលគោក រាជធានីភ្នំពេញ VAT: K005 902205145 | Q38: #98 ផ្លូវ 110 ភូមិ 6 សង្កាត់ ទឹកល្អក់ទី១ ខណ្ឌ ទួលគោក រាជធានីភ្នំពេញ VAT: K005 902205145 | S38: ZHANG HONGJUN | T38: EJ1364662 | U38: SHENG DE BAO INVESTMENT CO., LTD | V38: K008-902303036 | W38: 097 728 7988 | AB38: 45693 | AC38: ថ្ងៃពុធ ៨កើត ខែមាឃ ឆ្នាំរោង ឆស័ក ព.ស.២៥៦៨ | AD38: ថ្ងៃចន្ទ | AE38: ១១ រោច | AF38: ខែបុស្ស | AG38: ឆ្នាំថោះ | AH38: បញ្ចស័ក ពស. ២៥៦៧
C39: SDB | D39: ឈ្មោះ SDB MOTORS ដែលមានទីតាំង# ឃ្លាំងលេខ២ ផ្លូវមហាវិថីសហព័ន្ធរុស្សី ភូមិប៉ប្រកខាងជើង សង្កាត់កាកាបទី១ ខណ្ឌពោធិ៍សែនជ័យ រាជធានីភ្នំពេញ ទូរស័ព្ទលេខ 010399123 ។ | E39: https://maps.app.goo.gl/BZAQoUEDz9qhgL6r5?g_st=com.google.maps.preview.copy | F39: CAO SHANG | G39: ភេទស្រី ដែលមានលិខិតឆ្លងដែនលេខៈ EFI654952 មានតួនាទី ប្រធានក្រុមហ៊ុន L U SEA TRADING SERVICE CO., LTD អត្តសញ្ញាណកម្មសារពើពន្ធ (VAT)លេខៈ K009-901905395 | H39: BJC CELLOX (CAMBODIA) CO., LTD | I39: WICHAI ON-SRI | O39: GTV MOTOR CO.,LTD | P39: ផ្លូវជាតិលេខ២ ភូមិស្រុកធំ ឃុំជើងកើប ស្រុកកណ្ដាលស្ទឹង ខេត្តកណ្ដាល VAT: L001-902203582 | Q39: ផ្លូវជាតិលេខ២ ភូមិស្រុកធំ ឃុំជើងកើប ស្រុកកណ្ដាលស្ទឹង ខេត្តកណ្ដាល VAT: L001-902203582 | S39: MEAS THOM | T39: 020907113(1) | U39: KLP.T TRANSPORTATION CO.,LTD | V39: B105-902203319 | W39: 096 505 9504 | AB39: 45694 | AC39: ថ្ងៃព្រហស្បតិ៍ ៩កើត ខែមាឃ ឆ្នាំរោង ឆស័ក ព.ស.២៥៦៨ | AD39: ថ្ងៃអង្គារ | AE39: ១២ រោច | AF39: ខែបុស្ស | AG39: ឆ្នាំថោះ | AH39: បញ្ចស័ក ពស. ២៥៦៧
C40: SHUN DA AUTO | D40: ឈ្មោះ SHUN DA AUTO ដែលមានទីតាំង#143 ផ្លូវ ទន្លេសាប ភូមិ ៣ សង្កាត់ ជ្រោយចង្វារ រាជធានីភ្នំពេញ ទូរស័ព្ទលេខ 070 557 817 ។ | E40: 11.5882787, 104.9277179 | F40: WICHAI ON-SRI.. | G40: ភេទប្រុស ដែលមានលិខិតឆ្លងដែនលេខៈ AB2484839 អគ្គនាយករងនៃក្រុមហ៊ុន BJC CELLOX(CAMBODIA) CO., LTD អត្តសញ្ញាណកម្មសារពើពន្ធ (VAT)លេខៈ L001-901639149 ទូរសព្ទ័លេខៈ 089 890 324 ទីតាំងនៅផ្លូវជាតិលេខ ១ គីឡូម៉ែតលេខ ៤៦ ភូមិ សំរោងក្អែរ ឃុំ សំរោងធំ ស្រុកកៀនស្វាយ ខេត្តកណ្តាល ។ | H40: L U SEA TRADING SERVICE CO., LTD | I40: CAO SHANG | O40: GLOBAL GREEN (CAMBODIA) ENERGY DEVELOPMENT CO.,LTD | P40: #205BC ផ្លូវ 51 សង្កាត់ បឹងកេងកងទី1 ខណ្ឌ ចំការមន រាជធានីភ្នំពេញ VAT: L001-107029847 | Q40: #205BC ផ្លូវ 51 សង្កាត់ បឹងកេងកងទី1 ខណ្ឌ ចំការមន រាជធានីភ្នំពេញ VAT: L001-107029847 | S40: LUO PENG | T40: EJ3905555 | U40: FD AUTO (CAMBODIA) INTERNATIONAL TRADE CO., LTD | V40: K001-902202691 | W40: 097 728 7988 | AB40: 45695 | AC40: ថ្ងៃសុក្រ ១០កើត ខែមាឃ ឆ្នាំរោង ឆស័ក ព.ស.២៥៦៨ | AD40: ថ្ងៃពុធ | AE40: ១៣ រោច | AF40: ខែបុស្ស | AG40: ឆ្នាំថោះ | AH40: បញ្ចស័ក ពស. ២៥៦៧
C41: HYDRA | D41: ឈ្មោះ HYDRA ដែលមានទីតាំង CHH IV0235, Russian Federation Blvd, Kbal Damrey I Village, Sangkat Kakap 1, Khann Por Senchey, Phnom Penh រាជធានីភ្នំពេញ ទូរស័ព្ទលេខ 017924492 ។ | E41: https://maps.app.goo.gl/GxewmX7TLuHwQp4J7 | F41: CHOEM PICHIT | G41: ភេទប្រុស មានអត្តសញ្ញាណប័ណ្ណសញ្ជាតិខ្មែរលេខៈ 100746252 ជាប្រធានក្រុមហ៊ុន CHOEM PICHIT IMPORT EXPORT CO.,LTD អត្តសញ្ញាណកម្មសារពើពន្ធ (VAT)លេខៈ L009-902202339 | H41: BURIRUM TECHNICIAN CO., LTD | I41: PAV PHEA RUM | O41: SNCO (CAMBODIA) CO., LTD | P41: #បុរីហេង ហៀងស៊ីធី C ២៩ ផ្លូវ ៦A ភូមិ ខ្ទរ សង្កាត់ ព្រែកលៀប ខណ្ឌ ជ្រោយចង្វារ រាជធានីភ្នំពេញ VAT: K008 902202776 | Q41: #បុរីហេង ហៀងស៊ីធី C ២៩ ផ្លូវ ៦A ភូមិ ខ្ទរ សង្កាត់ ព្រែកលៀប ខណ្ឌ ជ្រោយចង្វារ រាជធានីភ្នំពេញ VAT: K008 902202776 | S41: LI TAO | T41: EE9756253 | U41: AUTOHOME(CAMBODIA) IMPORT EXPORT CO.,LTD. | V41: K009-902303928 | AB41: 45696 | AC41: ថ្ងៃសៅរ៍ ១១កើត ខែមាឃ ឆ្នាំរោង ឆស័ក ព.ស.២៥៦៨ | AD41: ថ្ងៃព្រហស្បតិ៍ | AE41: ១៤ រោច | AF41: ខែបុស្ស | AG41: ឆ្នាំថោះ | AH41: បញ្ចស័ក ពស. ២៥៦៧
C42: ZDG | D42: ឈ្មោះ Z D G (CAMBODIA) CO.,LTD ដែលមានទីតាំង #ឃ្លាំងលេខ៣ ផ្លូវ មហាវិថីសហព័ន្ធរុស្សី ភូមិ ប៉ប្រកខាងជើង សង្កាត់ កាកាបទី១ ខណ្ឌពោធិសែនជ័យ រាជធានីភ្នំពេញ ទូរស័ព្ទលេខ 010 399 123 ។ | E42: https://maps.app.goo.gl/mwwdRx38mvW6sEPr9?g_st=it | F42: JIANG ZHIPING | G42: ភេទប្រុស ដែលមានលិខិតឆ្លងដែនលេខៈ E85954264 ជាប្រធានក្រុមហ៊ុន EVERSAILING SUPPLY CHAIN (CAMBODIA) CO.,LTD អត្តសញ្ញាណកម្មសារពើពន្ធ (VAT)លេខៈ K005-902101776 ទូរសព្ទ័លេខៈ 071 792 7651 | H42: DHONNA JIA CHENG IMP EXP CO.,LTD | I42: SAM SOPHAL | O42: CHOEM SIRATH IMPORT & EXPORT CO,LTD | P42: ក្បាលដីលេខ ៨៦៨ ផ្លូវ ៥៩៨ ភូមិ ពោងពាយ សង្កាត់ ទួលសង្កែទី២ ខណ្ឌ ឫស្សីកែវ រាជធានីភ្នំពេញ VAT: K008-902300821 | Q42: ក្បាលដីលេខ ៨៦៨ ផ្លូវ ៥៩៨ ភូមិ ពោងពាយ សង្កាត់ ទួលសង្កែទី២ ខណ្ឌ ឫស្សីកែវ រាជធានីភ្នំពេញ VAT: K008-902300821 | S42: POV VUTHA | T42: 020537376(01) | U42: Y.U.A.S (CAMBODIA) CO., LTD. | V42: K008-902302426 | W42: ០87 326 711 | AB42: 45697 | AC42: ថ្ងៃអាទិត្យ ១២កើត ខែមាឃ ឆ្នាំរោង ឆស័ក ព.ស.២៥៦៨ | AD42: ថ្ងៃសុក្រ | AE42: ១៥ រោច | AF42: ខែបុស្ស | AG42: ឆ្នាំថោះ | AH42: បញ្ចស័ក ពស. ២៥៦៧
C43: BORUI | D43: ឈ្មោះ BORUI ដែលមានទីតាំង #គ្មាន ផ្លូវសម្ដេចតេជោហ៊ុនសែន60ម ភូមិព្រែកតានូ សង្កាត់ចាក់អង្រែលើ ខណ្ឌមានជ័យ រាជធានីភ្នំពេញ ទូរស័ព្ទលេខ 070 816 755 ។ | E43: https://maps.app.goo.gl/E37xdAE6zNHZAV8N6 | F43: LAY SOLIN | G43: ភេទប្រុស មានអត្តសញ្ញាណប័ណ្ណសញ្ជាតិខ្មែរលេខៈ 110549258 ជាប្រធានក្រុមហ៊ុន A.S.C.T (CAMBODIA) CO.,LTD អត្តសញ្ញាណកម្មសារពើពន្ធ (VAT)លេខៈ K007-902102757 | H43: A N D Y (CAMBODIA) INTERNATIONAL AUTO TRADE CO.,LTD | I43: ZHANG HUA | O43: TAING CHENG OING CONSTRUCTION &IMPORT EXPORT CO.,LTD | P43: #B២-០៤៥ អគារ The Elysee កោះពេជ្រ ផ្លូវបាសាក់ សង្កាត់ទន្លេបាសាក់ ខណ្ឌចំការមន រាជធានីភ្នំពេញ VAT: L001-180001159 | Q43: #B២-០៤៥ អគារ The Elysee កោះពេជ្រ ផ្លូវបាសាក់ សង្កាត់ទន្លេបាសាក់ ខណ្ឌចំការមន រាជធានីភ្នំពេញ VAT: L001-180001159 | S43: XU TAOHONG | T43: E42900722 | U43: ONE PLUS AUTO TRADING (CAMBODIA) CO., LTD | V43: L001-902302529 | W43: 098 891 618 | AB43: 45698 | AC43: ថ្ងៃចន្ទ ១៣កើត ខែមាឃ ឆ្នាំរោង ឆស័ក ព.ស.២៥៦៨ | AD43: ថ្ងៃសៅរ៍ | AE43: ១ កើត | AF43: ខែមាឃ | AG43: ឆ្នាំថោះ | AH43: បញ្ចស័ក ពស. ២៥៦៧
F44: PAIBOON LAOCHAN | G44: ភេទប្រុស ដែលមានលិខិតឆ្លងដែនលេខៈAB4916750 អ្នកគ្រប់គ្រងហិរញ្ញវត្ថុ គណនីយ និងរដ្ឋាបាលនៃក្រុមហ៊ុន BJC CELLOX(CAMBODIA) CO., LTD អត្តសញ្ញាណកម្មសារពើពន្ធ (VAT)លេខៈ L001-901639149 ទូរសព្ទ័លេខៈ 092 784 079 ទីតាំងនៅផ្លូវជាតិលេខ ១ គីឡូម៉ែតលេខ ៤៦ ភូមិ សំរោងក្អែរ ឃុំ សំរោងធំ ស្រុកកៀនស្វាយ ខេត្តកណ្តាល ។ | H44: CHOEM PICHIT IMPORT EXPORT CO.,LTD | I44: CHOEM PICHIT | O44: SHENG DE BAO INVESTMENT CO., LTD | P44: #បុរីរុងរឿង ផ្ទះលេខG៣៧០០-១៩ ជាន់ទី២ បន្ទប់ R១៩០៣ ផ្លូវ Gប្លុកR៣ ភូមិ គៀនឃ្លាំង សង្កាត់ ព្រែកលៀប ខណ្ឌជ្រោយចង្វារ រាជធានីភ្ណំពេញ VAT: K008-902303036 | Q44: #បុរីរុងរឿង ផ្ទះលេខG៣៧០០-១៩ ជាន់ទី២ បន្ទប់ R១៩០៣ ផ្លូវ Gប្លុកR៣ ភូមិ គៀនឃ្លាំង សង្កាត់ ព្រែកលៀប ខណ្ឌជ្រោយចង្វារ រាជធានីភ្ណំពេញ VAT: K008-902303036 | S44: ហ៊ល​ សំណាង | T44: 020524916(01) | U44: TWO RCP ASIA CO., LTD | V44: B108-902003919 | W44: 016988234 | AB44: 45699 | AC44: ថ្ងៃអង្គារ ១៤កើត ខែមាឃ ឆ្នាំរោង ឆស័ក ព.ស.២៥៦៨ | AD44: ថ្ងៃអាទិត្យ | AE44: ២ កើត | AF44: ខែមាឃ | AG44: ឆ្នាំថោះ | AH44: បញ្ចស័ក ពស. ២៥៦៧
F45: OEURN CHANDET | G45: ភេទស្រី មានអត្តសញ្ញាណប័ណ្ណសញ្ជាតិខ្មែរលេខៈ 150901855 មានតួនាទី ប្រធានក្រុមហ៊ុន O C D M TRADING CO., LTDអត្តសញ្ញាណកម្មសារពើពន្ធ (VAT)លេខៈ K007-902104377 | H45: EVERSAILING SUPPLY CHAIN (CAMBODIA) CO.,LTD | I45: JIANG ZHIPING | O45: KLP.T TRANSPORTATION CO.,LTD | P45: #​ ផ្លូវ ៥១ ភូមិ រោងដំរី ឃុំ ភ្នំតូច ស្រុក ឧដុង្គ ខេត្ត កំពង់ស្ពឺ VAT: B105-902203319 | Q45: #​ ផ្លូវ ៥១ ភូមិ រោងដំរី ឃុំ ភ្នំតូច ស្រុក ឧដុង្គ ខេត្ត កំពង់ស្ពឺ VAT: B105-902203319 | S45: DANG THI HUYEN | T45: C5097432 | U45: ONE CAR HOME CO., LTD | V45: K010-902304374 | W45: 096 8975776 | AB45: 45700 | AC45: ថ្ងៃពុធ ១៥កើត ខែមាឃ ឆ្នាំរោង ឆស័ក ព.ស.២៥៦៨ | AD45: ថ្ងៃចន្ទ | AE45: ៣ កើត | AF45: ខែមាឃ | AG45: ឆ្នាំថោះ | AH45: បញ្ចស័ក ពស. ២៥៦៧
F46: DEAB SIYET | G46: ភេទប្រុស មានអត្តសញ្ញាណប័ណ្ណសញ្ជាតិខ្មែរលេខៈ 030598691 ជាប្រធានក្រុមហ៊ុន HUA RONG SENG INTERNATIONAL MINING CO.,LTD អត្តសញ្ញាណកម្មសារពើពន្ធ (VAT)លេខៈ K009-902204536 ទូរសព្ទ័លេខៈ 097 7978 632 | H46: A.S.C.T (CAMBODIA) CO., LTD | I46: LAY SOLIN | O46: FD AUTO (CAMBODIA) INTERNATIONAL TRADE CO., LTD | P46: #២៧៨H ផ្លូវជាតិលេខ៦អា ភូមិគៀនឃ្លាំង សង្កាត់ព្រែកលៀប ខណ្ឌជ្រោយចង្វារ រាជធានីភ្នំពេញ VAT: B105-902203319 | Q46: #២៧៨H ផ្លូវជាតិលេខ៦អា ភូមិគៀនឃ្លាំង សង្កាត់ព្រែកលៀប ខណ្ឌជ្រោយចង្វារ រាជធានីភ្នំពេញ VAT: B105-902203319 | S46: ខៀវ គា | T46: 11454872 | U46: KHIEV KEA INVESTMENT CO.,LTD | V46: K009-902302973 | W46: 068 235200 | AB46: 45701 | AC46: ថ្ងៃព្រហស្បតិ៍ ១រោច ខែមាឃ ឆ្នាំរោង ឆស័ក ព.ស.២៥៦៨ | AD46: ថ្ងៃអង្គារ | AE46: ៤ កើត | AF46: ខែមាឃ | AG46: ឆ្នាំថោះ | AH46: បញ្ចស័ក ពស. ២៥៦៧
F47: SORN HORNG | G47: ភេទស្រី មានអត្តសញ្ញាណប័ណ្ណសញ្ជាតិខ្មែរលេខៈ 101205869 មានតួនាទី ប្រធានក្រុមហ៊ុន SORN HORNG ENTERPRISE CO.,LTD អត្តសញ្ញាណកម្មសារពើពន្ធ (VAT)លេខៈ K010 902204642 | H47: O C D M TRADING CO., LTD | I47: OEURN CHANDET | O47: JF MOTOR CO., LTD | P47: #ឃ្លាំងលេខ ៥១A ផ្លូវ ហាណូយ ភូមិ បាយ៉ាប សង្កាត់ ភ្នំពេញថ្មី ខណ្ឌ សែនសុខ រាជធានីភ្នំពេញ VAT: K009-902202715 | Q47: #ឃ្លាំងលេខ ៥១A ផ្លូវ ហាណូយ ភូមិ បាយ៉ាប សង្កាត់ ភ្នំពេញថ្មី ខណ្ឌ សែនសុខ រាជធានីភ្នំពេញ VAT: K009-902202715 | S47: WONGMONGKOL SRESTTAWIN | T47: AC5014016 | U47: SUVANNAPHUM INVESTMENT CO.,LTD | V47: L001-100114229 | W47: 093 544 566 | AB47: 45702 | AC47: ថ្ងៃសុក្រ ២រោច ខែមាឃ ឆ្នាំរោង ឆស័ក ព.ស.២៥៦៨ | AD47: ថ្ងៃពុធ | AE47: ៥ កើត | AF47: ខែមាឃ | AG47: ឆ្នាំថោះ | AH47: បញ្ចស័ក ពស. ២៥៦៧
F48: DO MARYNOEL | G48: ភេទស្រី មានអត្តសញ្ញាណប័ណ្ណសញ្ជាតិខ្មែរលេខៈ 011199507 មានតួនាទី ប្រធានក្រុមហ៊ុន HS MOTOR CO.,LTD អត្តសញ្ញាណកម្មសារពើពន្ធ (VAT)លេខៈ K005 902205145 | H48: HUA RONG SENG INTERNATIONAL MINING CO.,LTD | I48: DEAB SIYET | O48: AUTOHOME (CAMBODIA) IMPORT EXPORT CO.,LTD. | P48: #៨៥៦ ផ្លូវ សហព័ប្ធរុស្ស៊ី (១១០), ក្រុមទី៥ ភូមិ ទឹកថ្លា សង្កាត់ ទឹកថ្លា ខណ្ឌ សែនសុខ រាជធានីភ្នំពេញ VAT: K009-902303928 | Q48: #៨៥៦ ផ្លូវ សហព័ប្ធរុស្ស៊ី (១១០), ក្រុមទី៥ ភូមិ ទឹកថ្លា សង្កាត់ ទឹកថ្លា ខណ្ឌ សែនសុខ រាជធានីភ្នំពេញ VAT: K009-902303928 | S48: CUI BAO | T48: E68588012 | U48: LIXIANG SDB AUTO SALES CO.LTD | V48: K010-902405547 | W48: 010 399 123 | AB48: 45703 | AC48: ថ្ងៃសៅរ៍ ៣រោច ខែមាឃ ឆ្នាំរោង ឆស័ក ព.ស.២៥៦៨ | AD48: ថ្ងៃព្រហស្បតិ៍ | AE48: ៦ កើត | AF48: ខែមាឃ | AG48: ឆ្នាំថោះ | AH48: បញ្ចស័ក ពស. ២៥៦៧
F49: CHENG JIUSI | G49: ភេទប្រុស ដែលមានលិខិតឆ្លងដែនលេខៈ EE1326007 ជាប្រធានក្រុមហ៊ុន GTV MOTOR CO.,LTD អត្តសញ្ញាណកម្មសារពើពន្ធ (VAT)លេខៈ L001-902203582 | H49: DGML IMPORT EXPORT CO.,LTD | I49: អូច ពៅ | O49: Y.U.A.S (CAMBODIA) CO., LTD. | P49: #២០ ផ្លូវ ២០៩ CW ភូមិព្រែកតាគង់ សង្កាត់ព្រែកតាសេក ខណ្ឌជ្រោយចង្វារ រាជធានីភ្នំពេញ VAT: K008-902302426 | Q49: #២០ ផ្លូវ ២០៩ CW ភូមិព្រែកតាគង់ សង្កាត់ព្រែកតាសេក ខណ្ឌជ្រោយចង្វារ រាជធានីភ្នំពេញ VAT: K008-902302426 | S49: WICHAI ON-SRI. | T49: AD0667637 | U49: F&N FOODS (CAMBODIA) CO., LTD | V49: L001-902400750 | W49: 089 890 324 | AB49: 45704 | AC49: ថ្ងៃអាទិត្យ ៤រោច ខែមាឃ ឆ្នាំរោង ឆស័ក ព.ស.២៥៦៨ | AD49: ថ្ងៃសុក្រ | AE49: ៧ កើត | AF49: ខែមាឃ | AG49: ឆ្នាំថោះ | AH49: បញ្ចស័ក ពស. ២៥៦៧
F50: HANN SINATH | G50: ភេទប្រុស មានអត្តសញ្ញាណប័ណ្ណសញ្ជាតិខ្មែរលេខៈ 020921342 ជាប្រធានក្រុមហ៊ុន GLOBAL GREEN (CAMBODIA) ENERGY DEVELOPMENT CO.,LTD អត្តសញ្ញាណកម្មសារពើពន្ធ (VAT)លេខៈ L001-107029847 ទូរសព្ទ័លេខៈ 098 425 713 | H50: SORN HORNG ENTERPRISE CO.,LTD | I50: SORN HORNG | O50: ONE PLUS AUTO TRADING (CAMBODIA) CO., LTD | P50: # ឃ្លាំងលេខ២ ផ្លូវ សហព័ន្ធរុស្ស៊ី ភូមិ ប៉ប្រកខាងជើង សង្កាត់ កាកាបទី១ ខណ្ឌ ពោធិ៍សែនជ័យ រាជធានីភ្នំពេញ VAT: L001-902302529 | Q50: # ឃ្លាំងលេខ២ ផ្លូវ សហព័ន្ធរុស្ស៊ី ភូមិ ប៉ប្រកខាងជើង សង្កាត់ កាកាបទី១ ខណ្ឌ ពោធិ៍សែនជ័យ រាជធានីភ្នំពេញ VAT: L001-902302529 | S50: សឿង ឌីណា | T50: 010514479(01) | U50: OISHI F&B (CAMBODIA) CO.,LTD | V50: L001-902006587 | W50: 017 892 891 | AB50: 45705 | AC50: ថ្ងៃចន្ទ ៥រោច ខែមាឃ ឆ្នាំរោង ឆស័ក ព.ស.២៥៦៨ | AD50: ថ្ងៃសៅរ៍ | AE50: ៨ កើត | AF50: ខែមាឃ | AG50: ឆ្នាំថោះ | AH50: បញ្ចស័ក ពស. ២៥៦៧
F51: POL SAVRY | G51: ភេទស្រី មានអត្តសញ្ញាណប័ណ្ណសញ្ជាតិខ្មែរលេខៈ 171011534 មានតួនាទី ប្រធានក្រុមហ៊ុន SNCO (CAMBODIA) CO., LTD អត្តសញ្ញាណកម្មសារពើពន្ធ (VAT)លេខៈ K008 902202776 | H51: HS MOTOR CO.,LTD | I51: DO MARYNOEL | O51: TWO RCP ASIA CO., LTD | P51: #09 ផ្លូវលំ ភូមិព្រែករាំង សង្កាត់កំពង់សំណាញ់ ក្រុងតាខ្មៅ ខេត្តកណ្តាល VAT: B108-902003919 | Q51: #09 ផ្លូវលំ ភូមិព្រែករាំង សង្កាត់កំពង់សំណាញ់ ក្រុងតាខ្មៅ ខេត្តកណ្តាល VAT: B108-902003919 | S51: DONG HUAIGUI | T51: EK4993418 | U51: Z D G(CAMBODIA) CO., LTD | V51: K010-902404193 | W51: 010 399 123 | AB51: 45706 | AC51: ថ្ងៃអង្គារ ៦រោច ខែមាឃ ឆ្នាំរោង ឆស័ក ព.ស.២៥៦៨ | AD51: ថ្ងៃអាទិត្យ | AE51: ៩ កើត | AF51: ខែមាឃ | AG51: ឆ្នាំថោះ | AH51: បញ្ចស័ក ពស. ២៥៦៧
F52: CHOEM SIRATH | G52: ភេទប្រុស មានអត្តសញ្ញាណប័ណ្ណសញ្ជាតិខ្មែរលេខៈ 110571200 ជាប្រធានក្រុមហ៊ុន CHOEM SIRATH IMPORT & EXPORT CO,LTD អត្តសញ្ញាណកម្មសារពើពន្ធ (VAT)លេខៈ K008-902300821 ទូរសព្ទ័លេខៈ 087 452 029 | H52: GTV MOTOR CO.,LTD | I52: CHENG JIUSI | O52: ONE CAR HOME CO., LTD | P52: #១៦ ផ្លូវ ២០០៤ ភូមិ តាងួន១ សង្កាត់ កាកាបទី១ ខណ្ឌ ពោធិសែនជ័យ រាជធានីភ្នំពេញ VAT: K010-902304374 | Q52: #១៦ ផ្លូវ ២០០៤ ភូមិ តាងួន១ សង្កាត់ កាកាបទី១ ខណ្ឌ ពោធិសែនជ័យ រាជធានីភ្នំពេញ VAT: K010-902304374 | S52: មាស ធំ | T52: 020907113(01) | U52: KAMPOT LOGISTICS AND PORT COMPANY LIMITED | V52: L001-902101494 | W52: 096 505 9504 | AB52: 45707 | AC52: ថ្ងៃពុធ ៧រោច ខែមាឃ ឆ្នាំរោង ឆស័ក ព.ស.២៥៦៨ | AD52: ថ្ងៃចន្ទ | AE52: ១០ កើត | AF52: ខែមាឃ | AG52: ឆ្នាំថោះ | AH52: បញ្ចស័ក ពស. ២៥៦៧
F53: TAING CHENG OING | G53: ភេទប្រុស មានអត្តសញ្ញាណប័ណ្ណសញ្ជាតិខ្មែរលេខៈ 010954723 ជាប្រធានក្រុមហ៊ុន TAING CHENG OING CONSTRUCTION &IMPORT EXPORT CO.,LTD អត្តសញ្ញាណកម្មសារពើពន្ធ (VAT)លេខៈ L001-180001159 ទូរសព្ទ័លេខៈ 068 666 868 | H53: GLOBAL GREEN (CAMBODIA) ENERGY DEVELOPMENT CO.,LTD | I53: HANN SINATH | O53: BJC CELLOX (CAMBODIA) CO., LTD | P53: ទីតាំងនៅផ្លូវជាតិលេខ ១ គីឡូម៉ែតលេខ ៤៦ ភូមិ សំរោងក្អែរ ឃុំ សំរោងធំ ស្រុកកៀនស្វាយ ខេត្តកណ្តាល (VAT)លេខៈ L001-901639149 ទូរសព្ទ័លេខៈ 069 777 815 | Q53: ទីតាំងនៅផ្លូវជាតិលេខ ១ គីឡូម៉ែតលេខ ៤៦ ភូមិ សំរោងក្អែរ ឃុំ សំរោងធំ ស្រុកកៀនស្វាយ ខេត្តកណ្តាល (VAT)លេខៈ L001-901639149 ទូរសព្ទ័លេខៈ 069 777 815 | S53: ប៊ូ ប៊ុនធឿន | T53: 11204667 | U53: ZJC IMPORT EXPORT CO., LTD | V53: K006-902405308 | W53: 010 684 888 | AB53: 45708 | AC53: ថ្ងៃព្រហស្បតិ៍ ៨រោច ខែមាឃ ឆ្នាំរោង ឆស័ក ព.ស.២៥៦៨ | AD53: ថ្ងៃអង្គារ | AE53: ១១ កើត | AF53: ខែមាឃ | AG53: ឆ្នាំថោះ | AH53: បញ្ចស័ក ពស. ២៥៦៧
F54: ZHANG HONGJUN | G54: ភេទប្រុស ដែលមានលិខិតឆ្លងដែនលេខៈ EJ1364662 ជាប្រធានក្រុមហ៊ុន SHENG DE BAO INVESTMENT CO., LTD អត្តសញ្ញាណកម្មសារពើពន្ធ (VAT)លេខៈ K008-902303036 ទូរសព្ទ័លេខៈ 097 728 7988 | H54: SNCO (CAMBODIA) CO., LTD | I54: POL SAVRY | O54: KHIEV KEA INVESTMENT CO.,LTD | P54: #ក្បាលដីលេខ ៨៥៩ ផ្លូវ លំ ភូមិ ត្រពាំងសំព័រ សង្កាត់ គោករកា ខណ្ឌ ព្រែកព្នៅ រាជធានីភ្នំពេញ (VAT)លេខៈ K009-902302973 ទូរសព្ទ័លេខៈ 068 235200 | Q54: #ក្បាលដីលេខ ៨៥៩ ផ្លូវ លំ ភូមិ ត្រពាំងសំព័រ សង្កាត់ គោករកា ខណ្ឌ ព្រែកព្នៅ រាជធានីភ្នំពេញ (VAT)លេខៈ K009-902302973 ទូរសព្ទ័លេខៈ 068 235200 | S54: CUI BAO | T54: E68588012 | U54: ONE PLUS AUTO TRADING (CAMBODIA) CO., LTD | V54: L001-902302529 | W54: 098 891 618 | AB54: 45709 | AC54: ថ្ងៃសុក្រ ៩រោច ខែមាឃ ឆ្នាំរោង ឆស័ក ព.ស.២៥៦៨ | AD54: ថ្ងៃពុធ | AE54: ១២ កើត | AF54: ខែមាឃ | AG54: ឆ្នាំថោះ | AH54: បញ្ចស័ក ពស. ២៥៦៧
F55: MEAS THOM | G55: ភេទប្រុស ដែលមានលិខិតឆ្លងដែនលេខៈ 020907113(1) ជាប្រធានក្រុមហ៊ុន KLP.T TRANSPORTATION CO.,LTD អត្តសញ្ញាណកម្មសារពើពន្ធ (VAT)លេខៈ B105-902203319 ទូរសព្ទ័លេខៈ 098 425 713 | H55: CHOEM SIRATH IMPORT & EXPORT CO,LTD | I55: CHOEM SIRATH | O55: SUVANNAPHUM INVESTMENT CO.,LTD | P55: #៥២ ផ្លូវ ៥៩៨ សង្កាត់ បឹងកក់ទី២ ខណ្ឌ ទួលគោក រាជធានីភ្នំពេញ (VAT)លេខៈ L001-100114229 | Q55: #៥២ ផ្លូវ ៥៩៨ សង្កាត់ បឹងកក់ទី២ ខណ្ឌ ទួលគោក រាជធានីភ្នំពេញ (VAT)លេខៈ L001-100114229 | S55: ZHANG CHENLEI | T55: EK9770281 | U55: GDB AUTOMOBILE IMPORT & EXPORT CO.,LTD | V55: K010-902500316 | W55: 088 907 1666 | AB55: 45710 | AC55: ថ្ងៃសៅរ៍ ១០រោច ខែមាឃ ឆ្នាំរោង ឆស័ក ព.ស.២៥៦៨ | AD55: ថ្ងៃព្រហស្បតិ៍ | AE55: ១៣ កើត | AF55: ខែមាឃ | AG55: ឆ្នាំថោះ | AH55: បញ្ចស័ក ពស. ២៥៦៧
F56: LUO PENG | G56: ភេទប្រុស ដែលមានលិខិតឆ្លងដែនលេខៈ EJ3905555 ជាប្រធានក្រុមហ៊ុន FD AUTO (CAMBODIA) INTERNATIONAL TRADE CO., LTD អត្តសញ្ញាណកម្មសារពើពន្ធ (VAT)លេខៈ K001-902202691 ទូរសព្ទ័លេខៈ 097 728 7988 | H56: TAING CHENG OING CONSTRUCTION &IMPORT EXPORT CO.,LTD | I56: TAING CHENG OING | O56: LIXIANG SDB AUTO SALES CO.LTD | P56: ឃ្លាំងលេខ២ ផ្លូវមហាវិថីសហព័ន្ធរុស្សី ភូមិប៉ប្រកខាងជើង សង្កាត់កាកាបទី១ ខណ្ឌពោធិ៍សែនជ័យ រាជធានីភ្នំពេញ (VAT)លេខៈ K010-902405547 | Q56: ឃ្លាំងលេខ២ ផ្លូវមហាវិថីសហព័ន្ធរុស្សី ភូមិប៉ប្រកខាងជើង សង្កាត់កាកាបទី១ ខណ្ឌពោធិ៍សែនជ័យ រាជធានីភ្នំពេញ (VAT)លេខៈ K010-902405547 | S56: ZHAO PENG | T56: EGI569605 | U56: SHENG DE BAO INVESTMENT CO., LTD | V56: K010-902303036 | W56: 096 280 3521 | AB56: 45711 | AC56: ថ្ងៃអាទិត្យ ១១រោច ខែមាឃ ឆ្នាំរោង ឆស័ក ព.ស.២៥៦៨ | AD56: ថ្ងៃសុក្រ | AE56: ១៤ កើត | AF56: ខែមាឃ | AG56: ឆ្នាំថោះ | AH56: បញ្ចស័ក ពស. ២៥៦៧
F57: LI TAO | G57: ភេទប្រុស ដែលមានលិខិតឆ្លងដែនលេខៈ EE9756253 ជាប្រធានក្រុមហ៊ុន AUTOHOME(CAMBODIA) IMPORT EXPORT CO.,LTD. អត្តសញ្ញាណកម្មសារពើពន្ធ (VAT)លេខៈ K009-902303928 ទូរសព្ទ័លេខៈ 097 728 7988 | H57: SHENG DE BAO INVESTMENT CO., LTD | I57: ZHANG HONGJUN | O57: F&N FOODS (CAMBODIA) CO., LTD | P57: ផ្ទះលេខ ៥២ ផ្លូវ ៥៩៨ ភូមិ ៥ សង្កាត់បឹងកក់ ២ ខណ្ឌទួលគោគ រាជធានីភ្នំពេញ VAT: L001-902400750 | Q57: ផ្ទះលេខ ៥២ ផ្លូវ ៥៩៨ ភូមិ ៥ សង្កាត់បឹងកក់ ២ ខណ្ឌទួលគោគ រាជធានីភ្នំពេញ VAT: L001-902400750 | AB57: 45712 | AC57: ថ្ងៃចន្ទ ១២រោច ខែមាឃ ឆ្នាំរោង ឆស័ក ព.ស.២៥៦៨ | AD57: ថ្ងៃសៅរ៍ | AE57: ១៥ កើត | AF57: ខែមាឃ | AG57: ឆ្នាំថោះ | AH57: បញ្ចស័ក ពស. ២៥៦៧
F58: POV VUTHA | G58: ភេទប្រុស មានអត្តសញ្ញាណប័ណ្ណសញ្ជាតិខ្មែរលេខៈ 020537376(01) ជាប្រធានក្រុមហ៊ុន Y.U.A.S (CAMBODIA) CO., LTD អត្តសញ្ញាណកម្មសារពើពន្ធ (VAT)លេខៈ K008-902302426 ទូរសព្ទ័លេខៈ 087 326 711 | H58: KLP.T TRANSPORTATION CO.,LTD | I58: MEAS THOM | O58: OISHI F&B (CAMBODIA) CO.,LTD | P58: #២ ផ្លូវ១៣៤ ភូមិ ១២ សង្កាត់ វាលវង់ ខណ្ឌ ៧មករា រាជធានីភ្នំពេញ VAT: L001-902006587 | Q58: #២ ផ្លូវ១៣៤ ភូមិ ១២ សង្កាត់ វាលវង់ ខណ្ឌ ៧មករា រាជធានីភ្នំពេញ VAT: L001-902006587 | AB58: 45713 | AC58: ថ្ងៃអង្គារ ១៣រោច ខែមាឃ ឆ្នាំរោង ឆស័ក ព.ស.២៥៦៨ | AD58: ថ្ងៃអាទិត្យ | AE58: ១ រោច | AF58: ខែមាឃ | AG58: ឆ្នាំថោះ | AH58: បញ្ចស័ក ពស. ២៥៦៧
F59: XU TAOHONG | G59: ភេទស្រី ដែលមានលិខិតឆ្លងដែនលេខៈ E42900722 ជាប្រធានក្រុមហ៊ុន ONE PLUS AUTO TRADING (CAMBODIA) CO., LTD. អត្តសញ្ញាណកម្មសារពើពន្ធ (VAT)លេខៈ L001-902302529 ទូរសព្ទ័លេខៈ 098 891 618 | H59: FD AUTO (CAMBODIA) INTERNATIONAL TRADE CO., LTD | I59: LUO PENG | O59: Z D G(CAMBODIA) CO., LTD | P59: #ឃ្លាំងលេខ៣ ផ្លូវ មហាវិថីសហព័ន្ធរុស្សី ភូមិ ប៉ប្រកខាងជើង សង្កាត់ កាកាបទី១ ខណ្ឌពោធិសែនជ័យ រាជធានីភ្នំពេញ VAT: K010-902404193 | Q59: #ឃ្លាំងលេខ៣ ផ្លូវ មហាវិថីសហព័ន្ធរុស្សី ភូមិ ប៉ប្រកខាងជើង សង្កាត់ កាកាបទី១ ខណ្ឌពោធិសែនជ័យ រាជធានីភ្នំពេញ VAT: K010-902404193 | AB59: 45714 | AC59: ថ្ងៃពុធ ១៤រោច ខែមាឃ ឆ្នាំរោង ឆស័ក ព.ស.២៥៦៨ | AD59: ថ្ងៃចន្ទ | AE59: ២ រោច | AF59: ខែមាឃ | AG59: ឆ្នាំថោះ | AH59: បញ្ចស័ក ពស. ២៥៦៧
F60: ហ៊ល​ សំណាង | G60: ភេទប្រុស ដែលមានអត្តសញ្ញាណបណ្ណលេខៈ 020524916(01) ជាប្រធានក្រុមហ៊ុន TWO RCP ASIA CO., LTD អត្តសញ្ញាណកម្មសារពើពន្ធ (VAT)លេខៈ B108-902003919 ទូរសព្ទ័លេខៈ 066 888551 | H60: JF MOTOR CO., LTD | I60: ZHANG XINLEI | O60: KAMPOT LOGISTICS AND PORT COMPANY LIMITED | P60: #១៤-១៥ ផ្លូវ ៣៣៥ ភូមិ ២ សង្កាត់ បឹងកក់ទី ២ ខណ្ឌ ទួលគោក រាជធានីភ្នំពេញ VAT: L001-902101494 | Q60: #១៤-១៥ ផ្លូវ ៣៣៥ ភូមិ ២ សង្កាត់ បឹងកក់ទី ២ ខណ្ឌ ទួលគោក រាជធានីភ្នំពេញ VAT: L001-902101494 | AB60: 45715 | AC60: ថ្ងៃព្រហស្បតិ៍ ១កើត ខែផល្គុន ឆ្នាំរោង ឆស័ក ព.ស.២៥៦៨ | AD60: ថ្ងៃអង្គារ | AE60: ៣ រោច | AF60: ខែមាឃ | AG60: ឆ្នាំថោះ | AH60: បញ្ចស័ក ពស. ២៥៦៧
F61: DANG THI HUYEN | G61: ភេទស្រី ដែលមានលិខិតឆ្លងដែនលេខៈ C5097432 ជាប្រធានក្រុមហ៊ុន ONE CAR HOME CO., LTD អត្តសញ្ញាណកម្មសារពើពន្ធ (VAT)លេខៈ K010-902304374 ទូរសព្ទ័លេខៈ 096 8975776 | H61: AUTOHOME (CAMBODIA) IMPORT EXPORT CO.,LTD. | I61: LI TAO | O61: ZJC IMPORT EXPORT CO., LTD | P61: #ដីឡូត៍លេខ ៣N, ៤N ផ្លូវ៥៦ D៧ ភូមិម័ល សង្កាត់ដង្កោ ខណ្ឌដង្កោ រាជធានីភ្នំពេញ VAT: K006-902405308 | Q61: #ដីឡូត៍លេខ ៣N, ៤N ផ្លូវ៥៦ D៧ ភូមិម័ល សង្កាត់ដង្កោ ខណ្ឌដង្កោ រាជធានីភ្នំពេញ VAT: K006-902405308 | AB61: 45716 | AC61: ថ្ងៃសុក្រ ២កើត ខែផល្គុន ឆ្នាំរោង ឆស័ក ព.ស.២៥៦៨ | AD61: ថ្ងៃពុធ | AE61: ៤ រោច | AF61: ខែមាឃ | AG61: ឆ្នាំថោះ | AH61: បញ្ចស័ក ពស. ២៥៦៧
F62: ខៀវ គា | G62: ភេទប្រុស ដែលមានអត្តសញ្ញាណបណ្ណលេខៈ 011454872 ជាប្រធានក្រុមហ៊ុន KHIEV KEA INVESTMENT CO.,LTD អត្តសញ្ញាណកម្មសារពើពន្ធ (VAT)លេខៈ K009-902302973 ទូរសព្ទ័លេខៈ 068 235200 | H62: Y.U.A.S (CAMBODIA) CO., LTD. | I62: POV VUTHA | O62: GDB AUTOMOBILE IMPORT & EXPORT CO.,LTD | P62: #ឃ្លាំងលេខ៣ ផ្លូវមហាវិថីសហព័ន្ធរុស្សី ភូមិប៉ប្រកខាងជើង សង្កាត់កាកាបទី១ ខណ្ឌពោធិ៍សែនជ័យ រាជធានីភ្នំពេញ VAT: K010-902500316 | Q62: #ឃ្លាំងលេខ៣ ផ្លូវមហាវិថីសហព័ន្ធរុស្សី ភូមិប៉ប្រកខាងជើង សង្កាត់កាកាបទី១ ខណ្ឌពោធិ៍សែនជ័យ រាជធានីភ្នំពេញ VAT: K010-902500316 | AB62: 45717 | AC62: ថ្ងៃសៅរ៍ ៣កើត ខែផល្គុន ឆ្នាំរោង ឆស័ក ព.ស.២៥៦៨ | AD62: ថ្ងៃព្រហស្បតិ៍ | AE62: ៥ រោច | AF62: ខែមាឃ | AG62: ឆ្នាំថោះ | AH62: បញ្ចស័ក ពស. ២៥៦៧
F63: WONGMONGKOL SRESTTAWIN | G63: កាន់លិខិតឆ្លងដែនលេខ: AC5014016 ទូរសព្ទ័លេខ 093 544 566 ជាប្រធានក្រុមហ៊ុន SUVANNAPHUM INVESTMENT CO., LTD អត្តសញ្ញាណកម្មសារពើពន្ធ (VAT) លេខៈ L001-100114229 ជានីតិបុគ្គលជើងសារគយដែលមានរូបវន្តបុគ្គលជើងសាគយតំណាងលោក/លោកស្រី ផេង សុវណ្ណា អត្តសញ្ញាណប័ណ្ណសញ្ជាតិខ្មែរលេខៈ 190228973 ទូរសព្ទ័លេខ 012 333 901 ប័ណ្ណសម្គាល់ជើងសាគយលេខ #699B ផុតសុពលភាពថ្ងៃទី 31 ខែ ធ្នូ ឆ្នាំ 2026 ។ | H63: ONE PLUS AUTO TRADING (CAMBODIA) CO., LTD | I63: XU TAOHONG | O63: SHENG DE BAO INVESTMENT CO., LTD | P63: #ដីឡូត៍លេខ៩៣៩២ ឃ្លាំងលេខ១ ជាន់ទី១ បន្ទប់លេខ២០១ ផ្លូវសហព័ន្ធរុស្សី ភូមិប៉ប្រកខាងជើងសង្កាត់កាកាបទី១ ខណ្ឌពោធិ៍សែនជ័យ រាជធានីភ្នំពេញ​​​​ VAT: K010-902303036 | Q63: #ដីឡូត៍លេខ៩៣៩២ ឃ្លាំងលេខ១ ជាន់ទី១ បន្ទប់លេខ២០១ ផ្លូវសហព័ន្ធរុស្សី ភូមិប៉ប្រកខាងជើងសង្កាត់កាកាបទី១ ខណ្ឌពោធិ៍សែនជ័យ រាជធានីភ្នំពេញ​​​​ VAT: K010-902303036 | AB63: 45718 | AC63: ថ្ងៃអាទិត្យ ៤កើត ខែផល្គុន ឆ្នាំរោង ឆស័ក ព.ស.២៥៦៨ | AD63: ថ្ងៃសុក្រ | AE63: ៦ រោច | AF63: ខែមាឃ | AG63: ឆ្នាំថោះ | AH63: បញ្ចស័ក ពស. ២៥៦៧
F64: CUI BAO | G64: ភេទប្រុស ដែលមានលិខិតឆ្លងដែនលេខៈ E68588012 ជាប្រធានក្រុមហ៊ុន LIXIANG SDB AUTO SALES CO.LTD. អត្តសញ្ញាណកម្មសារពើពន្ធ (VAT)លេខៈ K010-902405547 ទូរសព្ទ័លេខៈ 010 399 123 | H64: TWO RCP ASIA CO., LTD | I64: ហ៊ល​ សំណាង | AB64: 45719 | AC64: ថ្ងៃចន្ទ ៥កើត ខែផល្គុន ឆ្នាំរោង ឆស័ក ព.ស.២៥៦៨ | AD64: ថ្ងៃសៅរ៍ | AE64: ៧ រោច | AF64: ខែមាឃ | AG64: ឆ្នាំថោះ | AH64: បញ្ចស័ក ពស. ២៥៦៧
F65: WICHAI ON-SRI. | G65: ភេទប្រុស ដែលមានលិខិតឆ្លងដែនលេខៈ AB2484839 នាយករដ្ឋាបាលនៃក្រុមហ៊ុន F&N FOODS(CAMBODIA) CO., LTD អត្តសញ្ញាណកម្មសារពើពន្ធ (VAT)លេខៈ L001-902400750 ទូរសព្ទ័លេខៈ 089 890 324 ទីតាំងនៅផ្ទះលេខ ៥២ ផ្លូវ ៥៩៨ ភូមិ ៥ សង្កាត់បឹងកក់ ២ ខណ្ឌទួលគោគ រាជធានីភ្នំពេញ ។ | H65: ONE CAR HOME CO., LTD | I65: DANG THI HUYEN | AB65: 45720 | AC65: ថ្ងៃអង្គារ ៦កើត ខែផល្គុន ឆ្នាំរោង ឆស័ក ព.ស.២៥៦៨ | AD65: ថ្ងៃអាទិត្យ | AE65: ៨ រោច | AF65: ខែមាឃ | AG65: ឆ្នាំថោះ | AH65: បញ្ចស័ក ពស. ២៥៦៧
F66: សឿង ឌីណា | G66: ភេទស្រី មានអត្តសញ្ញាណប័ណ្ណសញ្ជាតិខ្មែរលេខៈ 010514479(01) មានតួនាទី Head of Procurement នៃក្រុមហ៊ុន OISHI F&B (CAMBODIA) CO.,LTD អត្តសញ្ញាណកម្មសារពើពន្ធ (VAT)លេខៈ L001-902006587 | H66: KHIEV KEA INVESTMENT CO.,LTD | I66: ខៀវ គា | AB66: 45721 | AC66: ថ្ងៃពុធ ៧កើត ខែផល្គុន ឆ្នាំរោង ឆស័ក ព.ស.២៥៦៨ | AD66: ថ្ងៃចន្ទ | AE66: ៩ រោច | AF66: ខែមាឃ | AG66: ឆ្នាំថោះ | AH66: បញ្ចស័ក ពស. ២៥៦៧
F67: DONG HUAIGUI | G67: ភេទប្រុស ដែលមានលិខិតឆ្លងដែនលេខៈ EK4993418 នាយករដ្ឋាបាលនៃក្រុមហ៊ុន Z D G(CAMBODIA) CO., LTD អត្តសញ្ញាណកម្មសារពើពន្ធ (VAT)លេខៈ K010-902404193 ទូរសព្ទ័លេខៈ 010 399 123។ | H67: SUVANNAPHUM INVESTMENT CO.,LTD | I67: WONGMONGKOL SRESTTAWIN | AB67: 45722 | AC67: ថ្ងៃព្រហស្បតិ៍ ៨កើត ខែផល្គុន ឆ្នាំរោង ឆស័ក ព.ស.២៥៦៨ | AD67: ថ្ងៃអង្គារ | AE67: ១០ រោច | AF67: ខែមាឃ | AG67: ឆ្នាំថោះ | AH67: បញ្ចស័ក ពស. ២៥៦៧
F68: មាស ធំ | G68: ភេទប្រុស ដែលមានអត្តសញ្ញាណបណ្ណលេខៈ 020907113(01) ជាប្រធានក្រុមហ៊ុន KAMPOT LOGISTICS AND PORT COMPANY LIMITED អត្តសញ្ញាណកម្មសារពើពន្ធ (VAT)លេខៈ L001-902101494 ទូរសព្ទ័លេខៈ 096 505 9504 | H68: LIXIANG SDB AUTO SALES CO.LTD | I68: CUI BAO | AB68: 45723 | AC68: ថ្ងៃសុក្រ ៩កើត ខែផល្គុន ឆ្នាំរោង ឆស័ក ព.ស.២៥៦៨ | AD68: ថ្ងៃពុធ | AE68: ១១ រោច | AF68: ខែមាឃ | AG68: ឆ្នាំថោះ | AH68: បញ្ចស័ក ពស. ២៥៦៧
F69: ប៊ូ ប៊ុនធឿន | G69: ភេទប្រុស ដែលមានអត្តសញ្ញាណបណ្ណលេខៈ 011204667 ជាប្រធានក្រុមហ៊ុន ZJC IMPORT EXPORT CO., LTD អត្តសញ្ញាណកម្មសារពើពន្ធ (VAT)លេខៈ K006-902405308 ទូរសព្ទ័លេខៈ 010 684 888 | H69: F&N FOODS (CAMBODIA) CO., LTD | I69: WICHAI ON-SRI. | AB69: 45724 | AC69: ថ្ងៃសៅរ៍ ១០កើត ខែផល្គុន ឆ្នាំរោង ឆស័ក ព.ស.២៥៦៨ | AD69: ថ្ងៃព្រហស្បតិ៍ | AE69: ១២ រោច | AF69: ខែមាឃ | AG69: ឆ្នាំថោះ | AH69: បញ្ចស័ក ពស. ២៥៦៧
F70: CUI BAO | G70: ភេទប្រុស ដែលមានលិខិតឆ្លងដែនលេខៈ E68588012 ជាប្រធានក្រុមហ៊ុន ONE PLUS AUTO TRADING (CAMBODIA) CO., LTD. អត្តសញ្ញាណកម្មសារពើពន្ធ (VAT)លេខៈ K001-902302529 ទូរសព្ទ័លេខៈ 098 891 618 | H70: OISHI F&B (CAMBODIA) CO.,LTD | I70: សឿង ឌីណា | AB70: 45725 | AC70: ថ្ងៃអាទិត្យ ១១កើត ខែផល្គុន ឆ្នាំរោង ឆស័ក ព.ស.២៥៦៨ | AD70: ថ្ងៃសុក្រ | AE70: ១៣ រោច | AF70: ខែមាឃ | AG70: ឆ្នាំថោះ | AH70: បញ្ចស័ក ពស. ២៥៦៧
F71: ZHANG CHENLEI | G71: ភេទប្រុស ដែលមានលិខិតឆ្លងដែនលេខៈ EK9770281 ជាប្រធានក្រុមហ៊ុន GDB AUTOMOBILE IMPORT & EXPORT CO.,LTD អត្តសញ្ញាណកម្មសារពើពន្ធ (VAT)លេខៈ K010-902500316 ទូរសព្ទ័លេខៈ 0889071666 | H71: Z D G(CAMBODIA) CO., LTD | I71: DONG HUAIGUI | AB71: 45726 | AC71: ថ្ងៃចន្ទ ១២កើត ខែផល្គុន ឆ្នាំរោង ឆស័ក ព.ស.២៥៦៨ | AD71: ថ្ងៃសៅរ៍ | AE71: ១៤ រោច | AF71: ខែមាឃ | AG71: ឆ្នាំថោះ | AH71: បញ្ចស័ក ពស. ២៥៦៧
F72: ZHAO PENG | G72: ភេទប្រុស ដែលមានលិខិតឆ្លងដែនលេខៈ EGI569605 ជាប្រធានក្រុមហ៊ុន SHENG DE BAO INVESTMENT CO., LTD អត្តសញ្ញាណកម្មសារពើពន្ធ (VAT)លេខៈ K010-902303036 ទូរសព្ទ័លេខៈ 096 280 3521 | H72: KAMPOT LOGISTICS AND PORT COMPANY LIMITED | I72: មាស ធំ | AB72: 45727 | AC72: ថ្ងៃអង្គារ ១៣កើត ខែផល្គុន ឆ្នាំរោង ឆស័ក ព.ស.២៥៦៨ | AD72: ថ្ងៃអាទិត្យ | AE72: ១ កើត | AF72: ខែផល្គុន | AG72: ឆ្នាំថោះ | AH72: បញ្ចស័ក ពស. ២៥៦៧
H73: ZJC IMPORT EXPORT CO., LTD | I73: ប៊ូ ប៊ុនធឿន | AB73: 45728 | AC73: ថ្ងៃពុធ ១៤កើត ខែផល្គុន ឆ្នាំរោង ឆស័ក ព.ស.២៥៦៨ | AD73: ថ្ងៃចន្ទ | AE73: ២ កើត | AF73: ខែផល្គុន | AG73: ឆ្នាំថោះ | AH73: បញ្ចស័ក ពស. ២៥៦៧
H74: ONE PLUS AUTO TRADING (CAMBODIA) CO., LTD | I74: CUI BAO | AB74: 45729 | AC74: ថ្ងៃព្រហស្បតិ៍ ១៥កើត ខែផល្គុន ឆ្នាំរោង ឆស័ក ព.ស.២៥៦៨ | AD74: ថ្ងៃអង្គារ | AE74: ៣ កើត | AF74: ខែផល្គុន | AG74: ឆ្នាំថោះ | AH74: បញ្ចស័ក ពស. ២៥៦៧
H75: GDB AUTOMOBILE IMPORT & EXPORT CO.,LTD | I75: ZHANG CHENLEI | AB75: 45730 | AC75: ថ្ងៃសុក្រ ១រោច ខែផល្គុន ឆ្នាំរោង ឆស័ក ព.ស.២៥៦៨ | AD75: ថ្ងៃពុធ | AE75: ៤ កើត | AF75: ខែផល្គុន | AG75: ឆ្នាំថោះ | AH75: បញ្ចស័ក ពស. ២៥៦៧
H76: SHENG DE BAO INVESTMENT CO., LTD | I76: ZHAO PENG | AB76: 45731 | AC76: ថ្ងៃសៅរ៍ ២រោច ខែផល្គុន ឆ្នាំរោង ឆស័ក ព.ស.២៥៦៨ | AD76: ថ្ងៃព្រហស្បតិ៍ | AE76: ៥ កើត | AF76: ខែផល្គុន | AG76: ឆ្នាំថោះ | AH76: បញ្ចស័ក ពស. ២៥៦៧
AB77: 45732 | AC77: ថ្ងៃអាទិត្យ ៣រោច ខែផល្គុន ឆ្នាំរោង ឆស័ក ព.ស.២៥៦៨ | AD77: ថ្ងៃសុក្រ | AE77: ៦ កើត | AF77: ខែផល្គុន | AG77: ឆ្នាំថោះ | AH77: បញ្ចស័ក ពស. ២៥៦៧
AB78: 45733 | AC78: ថ្ងៃចន្ទ ៤រោច ខែផល្គុន ឆ្នាំរោង ឆស័ក ព.ស.២៥៦៨ | AD78: ថ្ងៃសៅរ៍ | AE78: ៧ កើត | AF78: ខែផល្គុន | AG78: ឆ្នាំថោះ | AH78: បញ្ចស័ក ពស. ២៥៦៧
AB79: 45734 | AC79: ថ្ងៃអង្គារ ៥រោច ខែផល្គុន ឆ្នាំរោង ឆស័ក ព.ស.២៥៦៨ | AD79: ថ្ងៃអាទិត្យ | AE79: ៨ កើត | AF79: ខែផល្គុន | AG79: ឆ្នាំថោះ | AH79: បញ្ចស័ក ពស. ២៥៦៧
AB80: 45735 | AC80: ថ្ងៃពុធ ៦រោច ខែផល្គុន ឆ្នាំរោង ឆស័ក ព.ស.២៥៦៨ | AD80: ថ្ងៃចន្ទ | AE80: ៩ កើត | AF80: ខែផល្គុន | AG80: ឆ្នាំថោះ | AH80: បញ្ចស័ក ពស. ២៥៦៧
AB81: 45736 | AC81: ថ្ងៃព្រហស្បតិ៍ ៧រោច ខែផល្គុន ឆ្នាំរោង ឆស័ក ព.ស.២៥៦៨ | AD81: ថ្ងៃអង្គារ | AE81: ១០ កើត | AF81: ខែផល្គុន | AG81: ឆ្នាំថោះ | AH81: បញ្ចស័ក ពស. ២៥៦៧
AB82: 45737 | AC82: ថ្ងៃសុក្រ ៨រោច ខែផល្គុន ឆ្នាំរោង ឆស័ក ព.ស.២៥៦៨ | AD82: ថ្ងៃពុធ | AE82: ១១ កើត | AF82: ខែផល្គុន | AG82: ឆ្នាំថោះ | AH82: បញ្ចស័ក ពស. ២៥៦៧
AB83: 45738 | AC83: ថ្ងៃសៅរ៍ ៩រោច ខែផល្គុន ឆ្នាំរោង ឆស័ក ព.ស.២៥៦៨ | AD83: ថ្ងៃព្រហស្បតិ៍ | AE83: ១២ កើត | AF83: ខែផល្គុន | AG83: ឆ្នាំថោះ | AH83: បញ្ចស័ក ពស. ២៥៦៧
AB84: 45739 | AC84: ថ្ងៃអាទិត្យ ១០រោច ខែផល្គុន ឆ្នាំរោង ឆស័ក ព.ស.២៥៦៨ | AD84: ថ្ងៃសុក្រ | AE84: ១៣ កើត | AF84: ខែផល្គុន | AG84: ឆ្នាំថោះ | AH84: បញ្ចស័ក ពស. ២៥៦៧
AB85: 45740 | AC85: ថ្ងៃចន្ទ ១១រោច ខែផល្គុន ឆ្នាំរោង ឆស័ក ព.ស.២៥៦៨ | AD85: ថ្ងៃសៅរ៍ | AE85: ១៤ កើត | AF85: ខែផល្គុន | AG85: ឆ្នាំថោះ | AH85: បញ្ចស័ក ពស. ២៥៦៧
AB86: 45741 | AC86: ថ្ងៃអង្គារ ១២រោច ខែផល្គុន ឆ្នាំរោង ឆស័ក ព.ស.២៥៦៨ | AD86: ថ្ងៃអាទិត្យ | AE86: ១៥ កើត | AF86: ខែផល្គុន | AG86: ឆ្នាំថោះ | AH86: បញ្ចស័ក ពស. ២៥៦៧
AB87: 45742 | AC87: ថ្ងៃពុធ ១៣រោច ខែផល្គុន ឆ្នាំរោង ឆស័ក ព.ស.២៥៦៨ | AD87: ថ្ងៃចន្ទ | AE87: ១ រោច | AF87: ខែផល្គុន | AG87: ឆ្នាំថោះ | AH87: បញ្ចស័ក ពស. ២៥៦៧
AB88: 45743 | AC88: ថ្ងៃព្រហស្បតិ៍ ១៤រោច ខែផល្គុន ឆ្នាំរោង ឆស័ក ព.ស.២៥៦៨ | AD88: ថ្ងៃអង្គារ | AE88: ២ រោច | AF88: ខែផល្គុន | AG88: ឆ្នាំថោះ | AH88: បញ្ចស័ក ពស. ២៥៦៧
... AB366: 46021 | AC366: ថ្ងៃអង្គារ ១១កើត ខែបុស្ស ឆ្នាំម្សាញ់ សប្តស័ក ព.ស.២៥៦៩ | AD366: ថ្ងៃអាទិត្យ | AE366: ១៤ រោច | AF366: ខែមិគសិរ | AG366: ឆ្នាំរោង | AH366: ឆស័ក ពស. ២៥៦៨
AB367: 46022 | AC367: ថ្ងៃពុធ ១២កើត ខែបុស្ស ឆ្នាំម្សាញ់ សប្តស័ក ព.ស.២៥៦៩ | AD367: ថ្ងៃចន្ទ | AE367: ១ កើត | AG367: ឆ្នាំរោង | AH367: ឆស័ក ពស. ២៥៦៨
AD368: ថ្ងៃអង្គារ | AE368: ២ កើត | AG368: ឆ្នាំរោង | AH368: ឆស័ក ពស. ២៥៦៨
Y2509: 17200 | AB2509: 1.MRKU5767154-40DRY, 2.CAAU6520380-40DRY, 3.TCKU6805111-40DRY, 4.MRSU5638442-40DRY | AC2509: 8 | AD2509: 0 | AE2509: 4 | AG2509: SHENZHEN JINCHENGLI | AH2509: 45866 | AI2509: SDB

Sheet SEAL STOCK
B1: =SUM(C3:C9999) -> 305 | E1: =SUM(F3:F9999) -> 243 | H1: =B1-E1 -> 62
A2: INV | B2: FROM | C2: IN | D2: DATE | E2: FOR | F2: OUT | G2: DATE | H2: BALANCE
A3: 2022-0189 | B3: ADEPT | C3: 25 | D3: 44615 | E3: DINA | F3: 7
A4: 2022-0224 | B4: ADEPT | C4: 40 | E4: 22072 | F4: 1
A5: 2022-0289 | B5: ADEPT | C5: 40 | D5: 44644 | E5: 22073 | F5: 7
A6: 000268 | B6: MAO CHAN THY | C6: 100 | E6: 22074 | F6: 1
B7: MAO CHAN THY | C7: 100 | E7: 22084 | F7: 2 | G7: 44629
E8: 22085 | F8: 5 | G8: 44629
E9: 22089 | F9: 2
E10: 22090 | F10: 5
E11: 22091 | F11: 5
E12: 22092 | F12: 10
E13: 22095 | F13: 1
E14: 22098 | F14: 3
E15: 22101 | F15: 1
E16: 22103 | F16: 9
E17: 22104 | F17: 5
E18: 22105 | F18: 1
E19: 22112 | F19: 2
E20: 22113 | F20: 2
... E30: 22149 | F30: 9
E31: 22156 | F31: 1
E32: 22184 | F32: 3
E33: 22185 | F33: 1
E34: 22186 | F34: 1
E35: 22202 | F35: 1
E36: 22218 | F36: 7
E37: 22219 | F37: 1
E38: 22220 | F38: 2
E39: 22223 | F39: 9
E40: 22250 | F40: 2
E41: 22295 | F41: 8
E42: 22296 | F42: 2
... E55: 22359 | F55: 1
E56: 22366 | G56: 2
E57: 22367 | G57: 2
E58: 22368 | F58: 6
E59: 22369 | F59: 14
E60: 22375 | G60: 4
E61: 22376 | G61: 4
E62: 22382 | G62: 1
E63: 22383 | G63: 2

Sheet SYSTEM
A1: No | B1: System | C1: ORG | D1: USER | E1: PASS | F1: Remark
A2: 1 | B2: Asycuda | C2: GDCE | D2: phengsovanna | E2: 123456 | F2: CUSTOMS REGIRSTRATION IM7, IM4
A3: 2 | B3: National Single Window | C3: GDCE | D3: PHENGSOVANNA | E3: 654321 | F3: IMPORT Permit (QIP)
A4: 3 | B4: E-CUMSTOMS | C4: GDCE | D4: phengsovanna | E4: 123456 | F4: TRANSIT REGISTRATION IM8
A5: 4 | B5: TOS | C5: PPAP | D5: VIEW1 | E5: 123456 | F5: CHECK CARGO HISTORY (CONTAINER GATE OUT & IN)
A6: 5 | B6: CV | C6: GDCE | D6: PHENGSOVANNA-Broker@CVDS | E6: FmgU0j%oS | F6: CUSTOMS VALUATION

Sheet Khmer_Lunar_2025
AI2: Date | AJ2: កាលបរិច្ឆេទចន្ទគិតិខ្មែរ ២០២៥
AI3: 45658 | AJ3: ថ្ងៃពុធ ៣កើត ខែបុស្ស ឆ្នាំរោង ឆស័ក ព.ស.២៥៦៨
AI4: 45659 | AJ4: ថ្ងៃព្រហស្បតិ៍ ៤កើត ខែបុស្ស ឆ្នាំរោង ឆស័ក ព.ស.២៥៦៨
AI5: 45660 | AJ5: ថ្ងៃសុក្រ ៥កើត ខែបុស្ស ឆ្នាំរោង ឆស័ក ព.ស.២៥៦៨
AI6: 45661 | AJ6: ថ្ងៃសៅរ៍ ៦កើត ខែបុស្ស ឆ្នាំរោង ឆស័ក ព.ស.២៥៦៨
C7: Kelly Technic | AI7: 45662 | AJ7: ថ្ងៃអាទិត្យ ៧កើត ខែបុស្ស ឆ្នាំរោង ឆស័ក ព.ស.២៥៦៨
AI8: 45663 | AJ8: ថ្ងៃចន្ទ ៨កើត ខែបុស្ស ឆ្នាំរោង ឆស័ក ព.ស.២៥៦៨
AI9: 45664 | AJ9: ថ្ងៃអង្គារ ៩កើត ខែបុស្ស ឆ្នាំរោង ឆស័ក ព.ស.២៥៦៨
AI10: 45665 | AJ10: ថ្ងៃពុធ ១០កើត ខែបុស្ស ឆ្នាំរោង ឆស័ក ព.ស.២៥៦៨
AI11: 45666 | AJ11: ថ្ងៃព្រហស្បតិ៍ ១១កើត ខែបុស្ស ឆ្នាំរោង ឆស័ក ព.ស.២៥៦៨
AI12: 45667 | AJ12: ថ្ងៃសុក្រ ១២កើត ខែបុស្ស ឆ្នាំរោង ឆស័ក ព.ស.២៥៦៨
AI13: 45668 | AJ13: ថ្ងៃសៅរ៍ ១៣កើត ខែបុស្ស ឆ្នាំរោង ឆស័ក ព.ស.២៥៦៨
AI14: 45669 | AJ14: ថ្ងៃអាទិត្យ ១៤កើត ខែបុស្ស ឆ្នាំរោង ឆស័ក ព.ស.២៥៦៨
AI15: 45670 | AJ15: ថ្ងៃចន្ទ ១៥កើត ខែបុស្ស ឆ្នាំរោង ឆស័ក ព.ស.២៥៦៨
AI16: 45671 | AJ16: ថ្ងៃអង្គារ ១រោច ខែបុស្ស ឆ្នាំរោង ឆស័ក ព.ស.២៥៦៨
AI17: 45672 | AJ17: ថ្ងៃពុធ ២រោច ខែបុស្ស ឆ្នាំរោង ឆស័ក ព.ស.២៥៦៨
AI18: 45673 | AJ18: ថ្ងៃព្រហស្បតិ៍ ៣រោច ខែបុស្ស ឆ្នាំរោង ឆស័ក ព.ស.២៥៦៨
AI19: 45674 | AJ19: ថ្ងៃសុក្រ ៤រោច ខែបុស្ស ឆ្នាំរោង ឆស័ក ព.ស.២៥៦៨
... AI367: 46022 | AJ367: ថ្ងៃពុធ ១២កើត ខែបុស្ស ឆ្នាំម្សាញ់ សប្តស័ក ព.ស.២៥៦៩

Sheet Sheet1
A1: 8 | B1: {=_xlfn.SEQUENCE(A1)} -> 1 | C1: 245904 | D1: ="-"&C1 -> -245904
B2: 2 | C2: 245905 | D2: ="-"&C2 -> -245905
B3: 3 | C3: 245906 | D3: ="-"&C3 -> -245906
B4: 4 | C4: 245907 | D4: ="-"&C4 -> -245907
B5: 5 | C5: 245908 | D5: ="-"&C5 -> -245908
B6: 6 | C6: 245909 | D6: ="-"&C6 -> -245909
B7: 7 | C7: 245910 | D7: ="-"&C7 -> -245910
B8: 8 | C8: 245911 | D8: ="-"&C8 -> -245911

Sheet Sheet2
A1: MONTH | B1: YEAR
A2: 4 | B2: 2022
A5: {=_xlfn._xlws.FILTER(DATA!C3:C9999,MONTH(DATA!C3:C9999)&YEAR(DATA!C3:C9999)=Sheet2!A2&Sheet2!B2,"NOT FOUND")} -> #VALUE!
B7: 45658 | C7: =LOOKUP(B7,Khmer_Lunar_Table) -> ថ្ងៃពុធ ៣កើត ខែបុស្ស ឆ្នាំរោង ឆស័ក ព.ស.២៥៦៨
B8: 45659 | C8: =LOOKUP(B8,Khmer_Lunar_Table) -> ថ្ងៃព្រហស្បតិ៍ ៤កើត ខែបុស្ស ឆ្នាំរោង ឆស័ក ព.ស.២៥៦៨
B9: 45660 | C9: =LOOKUP(B9,Khmer_Lunar_Table) -> ថ្ងៃសុក្រ ៥កើត ខែបុស្ស ឆ្នាំរោង ឆស័ក ព.ស.២៥៦៨
B10: 45661 | C10: =LOOKUP(B10,Khmer_Lunar_Table) -> ថ្ងៃសៅរ៍ ៦កើត ខែបុស្ស ឆ្នាំរោង ឆស័ក ព.ស.២៥៦៨
B11: 45662 | C11: =LOOKUP(B11,Khmer_Lunar_Table) -> ថ្ងៃអាទិត្យ ៧កើត ខែបុស្ស ឆ្នាំរោង ឆស័ក ព.ស.២៥៦៨
B12: 45663 | C12: =LOOKUP(B12,Khmer_Lunar_Table) -> ថ្ងៃចន្ទ ៨កើត ខែបុស្ស ឆ្នាំរោង ឆស័ក ព.ស.២៥៦៨
B13: 45664 | C13: =LOOKUP(B13,Khmer_Lunar_Table) -> ថ្ងៃអង្គារ ៩កើត ខែបុស្ស ឆ្នាំរោង ឆស័ក ព.ស.២៥៦៨
B14: 45665 | C14: =LOOKUP(B14,Khmer_Lunar_Table) -> ថ្ងៃពុធ ១០កើត ខែបុស្ស ឆ្នាំរោង ឆស័ក ព.ស.២៥៦៨
B15: 45666 | C15: =LOOKUP(B15,Khmer_Lunar_Table) -> ថ្ងៃព្រហស្បតិ៍ ១១កើត ខែបុស្ស ឆ្នាំរោង ឆស័ក ព.ស.២៥៦៨
B16: 45667 | C16: =LOOKUP(B16,Khmer_Lunar_Table) -> ថ្ងៃសុក្រ ១២កើត ខែបុស្ស ឆ្នាំរោង ឆស័ក ព.ស.២៥៦៨
B17: 45668 | C17: =LOOKUP(B17,Khmer_Lunar_Table) -> ថ្ងៃសៅរ៍ ១៣កើត ខែបុស្ស ឆ្នាំរោង ឆស័ក ព.ស.២៥៦៨
B18: 45669 | C18: =LOOKUP(B18,Khmer_Lunar_Table) -> ថ្ងៃអាទិត្យ ១៤កើត ខែបុស្ស ឆ្នាំរោង ឆស័ក ព.ស.២៥៦៨
... B371: 46022 | C371: =LOOKUP(B371,Khmer_Lunar_Table) -> ថ្ងៃពុធ ១២កើត ខែបុស្ស ឆ្នាំម្សាញ់ សប្តស័ក ព.ស.២៥៦៩
